Workbook
Name PAR_FECHA_INICIO: CONFIG!$B$8
Name PAR_MESES: CONFIG!$B$9
Name PAR_SALDO_CAJA: CONFIG!$B$10
Name PAR_CAPITAL_INICIAL: CONFIG!$B$11
Name PAR_DIAS_MES: CONFIG!$B$12
Name PAR_ISV: CONFIG!$B$14
Name PAR_ALERTA_STOCK: CONFIG!$B$16
Name PAR_MARGEN_OBJ: CONFIG!$B$17
Name LISTA_CATEGORIAS: OFFSET(CONFIG!$B$23,0,0,MAX(1,COUNTA(CONFIG!$B$23:$B$83)),1)
Name LISTA_SUBCATEGORIAS: OFFSET(CONFIG!$C$23,0,0,MAX(1,COUNTA(CONFIG!$C$23:$C$83)),1)
Name LISTA_PRESENTACIONES: OFFSET(CONFIG!$D$23,0,0,MAX(1,COUNTA(CONFIG!$D$23:$D$83)),1)
Name LISTA_UNIDADES: OFFSET(CONFIG!$E$23,0,0,MAX(1,COUNTA(CONFIG!$E$23:$E$83)),1)
Name LISTA_CANALES: OFFSET(CONFIG!$F$23,0,0,MAX(1,COUNTA(CONFIG!$F$23:$F$83)),1)
Name LISTA_METODOS_PAGO: OFFSET(CONFIG!$G$23,0,0,MAX(1,COUNTA(CONFIG!$G$23:$G$83)),1)
Name LISTA_TIPO_GASTO: OFFSET(CONFIG!$H$23,0,0,MAX(1,COUNTA(CONFIG!$H$23:$H$83)),1)
Name LISTA_CAT_GASTO: OFFSET(CONFIG!$I$23,0,0,MAX(1,COUNTA(CONFIG!$I$23:$I$83)),1)
Name LISTA_ESTADO_PRODUCTO: OFFSET(CONFIG!$J$23,0,0,MAX(1,COUNTA(CONFIG!$J$23:$J$83)),1)
Name LISTA_ESTADO_PAGO: OFFSET(CONFIG!$K$23,0,0,MAX(1,COUNTA(CONFIG!$K$23:$K$83)),1)
Name LISTA_ESTADO_REL: OFFSET(CONFIG!$L$23,0,0,MAX(1,COUNTA(CONFIG!$L$23:$L$83)),1)
Name LISTA_CONCEPTO_CAJA: OFFSET(CONFIG!$M$23,0,0,MAX(1,COUNTA(CONFIG!$M$23:$M$83)),1)
Name LISTA_CONDICIONES: OFFSET(CONFIG!$N$23,0,0,MAX(1,COUNTA(CONFIG!$N$23:$N$83)),1)
Name LISTA_SINO: OFFSET(CONFIG!$O$23,0,0,MAX(1,COUNTA(CONFIG!$O$23:$O$83)),1)
Name LISTA_MODO: OFFSET(CONFIG!$P$23,0,0,MAX(1,COUNTA(CONFIG!$P$23:$P$83)),1)
Name LISTA_TIPO_MOV: OFFSET(CONFIG!$Q$23,0,0,MAX(1,COUNTA(CONFIG!$Q$23:$Q$83)),1)
Name LISTA_SKU: OFFSET(PRODUCTOS!$A$7,0,0,MAX(1,COUNTA(PRODUCTOS!$A$7:$A$66)),1)
Name LISTA_CLIENTES: OFFSET(CLIENTES!$B$7,0,0,MAX(1,COUNTA(CLIENTES!$B$7:$B$156)),1)
Name LISTA_PROVEEDORES: OFFSET(PROVEEDORES!$B$7,0,0,MAX(1,COUNTA(PROVEEDORES!$B$7:$B$46)),1)
Name LISTA_MESES: RENTABILIDAD!$A$8:$A$43

Sheet INICIO
B1: AROMATIC · Sistema Financiero y de Gestión Comercial
B2: Guía de uso. Léala una vez y tendrá el control total del sistema.
B4: ¿QUÉ ES ESTE ARCHIVO?
B5: En una frase | C5: Es el centro financiero de AROMATIC: registra productos, costos, compras, ventas y gastos, y a partir de eso calcula solo su inventario, su utilidad, su efectivo, su punto de equilibrio y sus metas.
B6: Lo más importante | C6: Usted solo escribe en las celdas AMARILLAS. Todo lo demás se calcula. Nunca borre una fórmula: si se equivoca, pulse Ctrl+Z.
B7: Precios del catálogo | C7: El catálogo 2016 se usó únicamente para cargar los 40 productos con sus nombres, categorías y presentaciones. Sus precios quedaron guardados aparte, en la columna «Precio de referencia del catálogo 2016», que es informativa y NO entra en ningún cálculo. El sistema trabaja exclusivamente con «Precio de venta actual», que está vacío hasta que usted lo defina.
B8: Nada inventado | C8: No hay ni un solo precio, costo, margen o proyección inventado. Donde falta información el sistema dice PENDIENTE en lugar de mostrar un número falso o un error de Excel.
B10: CÓDIGO DE COLORES
B11: Amarillo | C11: Celda de captura: usted escribe aquí.
B12: Gris claro | C12: Celda calculada: no la toque, contiene una fórmula.
B13: Verde claro | C13: Se llena sola, pero usted puede sobrescribirla en un caso puntual (por ejemplo, el precio de una venta con condiciones especiales).
B14: Gris con letra cursiva | C14: Dato informativo del catálogo 2016. No se usa en ningún cálculo.
B15: Rojo / Ámbar | C15: Alertas automáticas: algo está mal o requiere su atención.
B17: MAPA DE HOJAS
B18: Hoja | C18: Para qué sirve · ¿se escribe en ella?
B19: DASHBOARD | C19: Tablero con los números clave del mes y del negocio. → ¿Escribe usted aquí?: No se escribe (solo el mes)
B20: PRODUCTOS | C20: Catálogo maestro: un SKU por fila, con precio, stock mínimo y máximo. → ¿Escribe usted aquí?: SÍ
B21: COSTOS | C21: Todos los costos de cada producto: compra, transporte, impuestos, empaque, comisiones. → ¿Escribe usted aquí?: SÍ
B22: COMPRAS | C22: Lo que usted le compra a sus proveedores. Aumenta el inventario. → ¿Escribe usted aquí?: SÍ
B23: INVENTARIO | C23: Existencias y valor del inventario. Se calcula solo. → ¿Escribe usted aquí?: Solo stock inicial y ajustes
B24: VENTAS | C24: Cada venta, línea por línea. Disminuye el inventario. → ¿Escribe usted aquí?: SÍ
B25: GASTOS | C25: Gastos del negocio, separados en fijos y variables. → ¿Escribe usted aquí?: SÍ
B26: CAJA | C26: Entradas y salidas de dinero real, mes por mes. → ¿Escribe usted aquí?: Solo aportes, retiros y otros movimientos
B27: CLIENTES | C27: Base de clientes con su historial de compras. → ¿Escribe usted aquí?: SÍ
B28: PROVEEDORES | C28: Base de proveedores con condiciones y saldos. → ¿Escribe usted aquí?: SÍ
B29: RENTABILIDAD | C29: Estado de resultados mensual y análisis por producto, categoría y canal. → ¿Escribe usted aquí?: No
... B34: CONFIG | C34: Moneda, categorías, canales, métodos de pago y demás listas del sistema. → ¿Escribe usted aquí?: SÍ
B36: PRIMEROS PASOS (hágalos en este orden)
C37: 1. Vaya a CONFIG y escriba su saldo inicial de caja, su capital aportado y la fecha de inicio del calendario.
C38: 2. Vaya a PROVEEDORES y registre a quién le compra (el nombre es la llave del sistema).
C39: 3. Vaya a COSTOS y escriba, para cada producto que ya vende, cuánto le cuesta: compra, transporte, impuestos, empaque. Si algo no aplica, déjelo vacío.
C40: 4. Vaya a PRODUCTOS y escriba el «Precio de venta actual» de cada producto. En ese momento el sistema calcula su utilidad, su margen y su markup.
C41: 5. Vaya a INVENTARIO y escriba el «Stock inicial» que tiene hoy de cada producto.
C42: 6. Registre sus COMPRAS y sus VENTAS conforme vayan ocurriendo.
C43: 7. Registre sus GASTOS (alquiler, internet, publicidad, transporte…).
C44: 8. Revise la hoja CONTROL: si aparece algún problema, corríjalo. Luego abra el DASHBOARD.
B46: CÓMO HACER CADA COSA
B47: Agregar un producto nuevo | C47: 1) En PRODUCTOS, escriba en la primera fila vacía: SKU (código único, por ejemplo GEL-250), nombre, categoría, presentación y unidad. 2) En COSTOS, agregue una fila con ese mismo SKU y capture sus costos. 3) Vuelva a PRODUCTOS y escriba el precio de venta actual. El inventario y todos los análisis lo incluirán automáticamente.
B48: Definir o cambiar un precio | C48: En PRODUCTOS, columna «Precio de venta actual». Es el ÚNICO precio que usa el sistema. Al cambiarlo se recalculan utilidad, margen, markup, margen de contribución y punto de equilibrio.
B49: Registrar una compra | C49: En COMPRAS: fecha, proveedor, SKU, cantidad y costo unitario. Agregue transporte, impuestos y otros costos si los hubo: el sistema calcula el costo real de adquisición y actualiza el costo promedio ponderado del inventario. Si ya pagó, escriba la fecha de pago y el monto pagado.
B50: Registrar una venta | C50: En VENTAS: fecha, cliente, canal, SKU y cantidad. El precio y el costo se llenan solos. Si cobró, escriba la fecha de cobro y el monto cobrado; si no, el sistema lo deja como cuenta por cobrar. Una venta a crédito NO entra a la caja hasta que se cobre.
B51: Registrar un gasto | C51: En GASTOS: fecha, tipo (Fijo o Variable), categoría, descripción y monto. El tipo es importante: los gastos fijos son los que determinan su punto de equilibrio.
B52: Revisar el inventario | C52: Abra INVENTARIO. La columna ESTADO le dice qué hacer: OK, REABASTECER, AGOTADO o ERROR (ERROR = stock negativo: vendió algo que no había registrado como comprado). «Unidades sugeridas a comprar» le dice cuánto pedir para llegar al stock máximo.
B53: Revisar la rentabilidad | C53: Abra RENTABILIDAD. El bloque 1 (columnas A:Y) es su estado de resultados mes a mes. El bloque 2 (AA:AP) le dice qué producto deja más utilidad. Los bloques 3 y 4 analizan categorías y canales. El bloque 5 (BJ:BL) resume la inversión, el capital comprometido y el ROI.
B54: Revisar el flujo de efectivo | C54: Abra CAJA. Compare la columna «Utilidad neta del mes» con «Flujo neto del mes»: la diferencia le explica por qué puede tener utilidad y no tener dinero (o al revés).
B55: Usar los escenarios | C55: Abra ESCENARIOS. La columna BASE se llena con sus datos reales. Escriba sus supuestos en las columnas CONSERVADOR y CRECIMIENTO y compare ventas, utilidad, margen, punto de equilibrio, ROI y efectivo. Nada de eso afecta sus datos reales.
B56: Interpretar el dashboard | C56: Elija el mes en la celda amarilla. Arriba verá ventas, rentabilidad, acumulado, inventario, efectivo, metas e indicadores clave; abajo, la evolución en gráficos. Si aparece el aviso rojo de problemas pendientes, vaya a CONTROL antes de tomar decisiones con esos números.
B57: Interpretar el punto de equilibrio | C57: Abra EQUILIBRIO. «Punto de equilibrio en unidades» es cuánto debe vender al mes para no perder. Si su venta promedio está por debajo, está perdiendo dinero. El «margen de seguridad» le dice cuánto pueden caer sus ventas antes de llegar a ese punto.
B58: Corregir errores | C58: Abra CONTROL. Cada línea le dice qué está mal, cuántos casos hay y en qué hoja se corrige. La tabla de la derecha señala producto por producto qué le falta.
B60: CINCO REGLAS FINANCIERAS QUE ESTE SISTEMA RESPETA
B61: Ingresos ≠ utilidad | C61: Vender L 10,000 no es ganar L 10,000. A la venta hay que restarle el costo del producto (utilidad bruta) y después los gastos del negocio (utilidad neta). Vea RENTABILIDAD.
B62: Utilidad ≠ flujo de efectivo | C62: Puede tener utilidad y no tener dinero: si vendió a crédito o si compró inventario. La hoja CAJA muestra el dinero real y la columna «Diferencia utilidad − flujo» explica la brecha.
B63: Margen ≠ markup | C63: Margen = utilidad ÷ PRECIO. Markup = utilidad ÷ COSTO. Un producto que cuesta L 100 y se vende a L 150 tiene 33.3% de margen y 50% de markup. Confundirlos es la forma más común de fijar mal un precio.
B64: Ventas ≠ dinero disponible | C64: Lo que está en «Cuentas por cobrar» todavía no es suyo. El saldo disponible está en CAJA.
B65: Costo de compra ≠ costo real | C65: El costo real incluye transporte, impuestos, aranceles y empaque. Por eso la hoja COSTOS separa costos directos, logísticos y variables de venta: es la única manera de saber si realmente gana dinero.
B67: GLOSARIO: QUÉ SIGNIFICA CADA INDICADOR
B68: Costo real unitario | C68: Compra + materia prima + empaque + transporte + importación + impuestos + otros. Lo que de verdad le cuesta una unidad puesta en su bodega.
B69: Costo variable de venta | C69: Comisiones, delivery y publicidad atribuibles a esa venta. Depende del precio.
B70: Utilidad unitaria | C70: Precio de venta actual − costo real unitario.
B71: Margen bruto % | C71: Utilidad ÷ precio. De cada L 100 vendidos, cuánto queda antes de gastos.
B72: Markup % | C72: Utilidad ÷ costo. Cuánto le agrega al costo para fijar el precio.
B73: Margen de contribución | C73: Precio − costo variable total. Lo que cada unidad aporta para pagar los gastos fijos. Es la base del punto de equilibrio.
B74: Utilidad bruta | C74: Ventas netas − costo de ventas.
B75: Utilidad operativa | C75: Utilidad bruta − gastos fijos y variables.
B76: Utilidad neta | C76: Utilidad operativa + otros ingresos − otros egresos. Lo que realmente ganó.
B77: Margen neto % | C77: Utilidad neta ÷ ventas netas.
B78: Punto de equilibrio | C78: Costos fijos ÷ margen de contribución unitario. Las unidades que debe vender para no ganar ni perder.
B79: ROI sobre la inversión | C79: Utilidad neta acumulada ÷ (compras + gastos). Cuánto rinde cada lempira que ha puesto en el negocio.
... B85: Cobertura de inventario | C85: Días que le durará el stock actual al ritmo de venta de los últimos 30 días.
B87: NOTAS TÉCNICAS Y LÍMITES CONOCIDOS
B88: Capacidad actual | C88: 60 productos, 500 líneas de venta, 300 compras, 300 gastos, 150 clientes, 40 proveedores y 36 meses de calendario. Para ampliar, copie la última fila de la tabla hacia abajo: las fórmulas se replican solas.
B89: Costeo del inventario | C89: Se usa costo promedio ponderado global (no por capas ni FIFO). Es el método correcto y suficiente para este tamaño de operación; un software futuro puede implementar costeo por lotes.
B90: Ticket promedio | C90: Se calcula por línea de venta. Si una factura lleva 3 productos, cuentan 3 líneas. Use la columna «Folio» para agrupar líneas de una misma factura.
B91: Ventas anuladas | C91: Ponga el Estado en «Anulado»: la venta deja de contar en unidades, ingresos, inventario y rentabilidad, pero queda registrada como evidencia.
B92: Impuestos | C92: El ISV de CONFIG es informativo. Si sus precios ya incluyen impuesto, el sistema trabaja con precios brutos; cuando empiece a facturar con ISV conviene registrar los precios sin impuesto para no inflar la utilidad.
B93: Recálculo | C93: Si algún número no se actualiza, pulse F9 (recalcular). El archivo está diseñado para Excel 2016 o superior, Microsoft 365, LibreOffice Calc y Google Sheets.
B95: PREPARADO PARA CONVERTIRSE EN SOFTWARE
B96: Modelo de datos | C96: Cada hoja de captura es una tabla relacional: PRODUCTOS (clave SKU), CLIENTES (ID), PROVEEDORES (ID), COMPRAS (ID), VENTAS (ID), GASTOS (ID) y MOVIMIENTOS DE CAJA (ID). Los cálculos viven en hojas aparte (INVENTARIO, RENTABILIDAD, CAJA, CONTROL) y la parametrización vive en CONFIG. Esa separación entre datos, cálculos y configuración es exactamente la que necesita una base de datos.
B97: Migración | C97: Cuando el negocio lo pida, cada tabla se convierte en una tabla SQL con las mismas columnas y las mismas llaves; las fórmulas de INVENTARIO, RENTABILIDAD y CAJA se convierten en vistas o consultas. En el repositorio se incluye el documento MODELO_DE_DATOS.md con el esquema listo para implementar.
B98: Protección | C98: Las hojas RENTABILIDAD, CONTROL y DASHBOARD están protegidas (sin contraseña) para que nadie borre una fórmula por accidente. Si necesita modificarlas: Revisar → Desproteger hoja. En las demás hojas las celdas con fórmula están bloqueadas y las amarillas desbloqueadas; puede activar la protección desde Revisar → Proteger hoja cuando lo desee.

Sheet DASHBOARD
B1: AROMATIC · TABLERO FINANCIERO
B2: Todo lo que ve aquí se calcula solo. Cambie el mes en la celda amarilla para analizar otro período.
B4: Mes en análisis: | C4: 46266 | E4: ← seleccione el mes | G4: =IF(CONTROL!$B$4=0,"✓ Datos sin problemas pendientes","⚠ "&TEXT(CONTROL!$B$4,"0")&" dato(s) pendiente(s) o problema(s) detectado(s) — vea la hoja CONTROL")
B6: VENTAS DEL MES SELECCIONADO
B7: Ventas netas | E7: Unidades vendidas | H7: Ticket promedio | K7: Transacciones
B8: =IFERROR(INDEX(RENTABILIDAD!$D$8:$D$43,MATCH($C$4,RENTABILIDAD!$A$8:$A$43,0)),"") | E8: =IFERROR(INDEX(RENTABILIDAD!$E$8:$E$43,MATCH($C$4,RENTABILIDAD!$A$8:$A$43,0)),"") | H8: =IFERROR(INDEX(RENTABILIDAD!$R$8:$R$43,MATCH($C$4,RENTABILIDAD!$A$8:$A$43,0)),"") | K8: =IFERROR(INDEX(RENTABILIDAD!$Q$8:$Q$43,MATCH($C$4,RENTABILIDAD!$A$8:$A$43,0)),"")
B10: RENTABILIDAD DEL MES
B11: Utilidad bruta | E11: Margen bruto | H11: Utilidad neta | K11: Margen neto
B12: =IFERROR(INDEX(RENTABILIDAD!$G$8:$G$43,MATCH($C$4,RENTABILIDAD!$A$8:$A$43,0)),"") | E12: =IFERROR(INDEX(RENTABILIDAD!$H$8:$H$43,MATCH($C$4,RENTABILIDAD!$A$8:$A$43,0)),"") | H12: =IFERROR(INDEX(RENTABILIDAD!$O$8:$O$43,MATCH($C$4,RENTABILIDAD!$A$8:$A$43,0)),"") | K12: =IFERROR(INDEX(RENTABILIDAD!$P$8:$P$43,MATCH($C$4,RENTABILIDAD!$A$8:$A$43,0)),"")
B14: ACUMULADO DEL NEGOCIO
B15: Ventas acumuladas | E15: Utilidad neta acumulada | H15: ROI sobre la inversión | K15: Margen neto acumulado
B16: =RENTABILIDAD!$D$44 | E16: =RENTABILIDAD!$O$44 | H16: =RENTABILIDAD!$BK$26 | K16: =RENTABILIDAD!$P$44
B18: INVENTARIO Y CAPITAL
B19: Valor del inventario | E19: Productos con stock bajo | H19: Productos agotados | K19: Capital de trabajo comprometido
B20: =RENTABILIDAD!$BK$29 | E20: =COUNTIF(tblInventario[ESTADO],"REABASTECER") | H20: =COUNTIF(tblInventario[ESTADO],"AGOTADO") | K20: =RENTABILIDAD!$BK$32
B22: EFECTIVO DEL MES
B23: Entradas de efectivo | E23: Salidas de efectivo | H23: Flujo neto del mes | K23: Saldo disponible al cierre
B24: =IFERROR(INDEX(CAJA!$G$7:$G$42,MATCH($C$4,RENTABILIDAD!$A$8:$A$43,0)),"") | E24: =IFERROR(INDEX(CAJA!$M$7:$M$42,MATCH($C$4,RENTABILIDAD!$A$8:$A$43,0)),"") | H24: =IFERROR(INDEX(CAJA!$N$7:$N$42,MATCH($C$4,RENTABILIDAD!$A$8:$A$43,0)),"") | K24: =IFERROR(INDEX(CAJA!$O$7:$O$42,MATCH($C$4,RENTABILIDAD!$A$8:$A$43,0)),"")
B26: CUMPLIMIENTO DE METAS DEL MES
B27: Cumplimiento de ventas | E27: Cumplimiento de utilidad | H27: Cumplimiento de unidades | K27: Estado del mes
B28: =IFERROR(INDEX(METAS!$L$7:$L$42,MATCH($C$4,RENTABILIDAD!$A$8:$A$43,0)),"") | E28: =IFERROR(INDEX(METAS!$M$7:$M$42,MATCH($C$4,RENTABILIDAD!$A$8:$A$43,0)),"") | H28: =IFERROR(INDEX(METAS!$N$7:$N$42,MATCH($C$4,RENTABILIDAD!$A$8:$A$43,0)),"") | K28: =IFERROR(INDEX(METAS!$W$7:$W$42,MATCH($C$4,RENTABILIDAD!$A$8:$A$43,0)),"")
B30: INDICADORES FINANCIEROS CLAVE
B31: Punto de equilibrio (unidades/mes) | E31: Punto de equilibrio (Lempiras/mes) | H31: Margen de contribución % | K31: Cuentas por cobrar
B32: =EQUILIBRIO!$B$16 | E32: =EQUILIBRIO!$B$17 | H32: =EQUILIBRIO!$B$15 | K32: =RENTABILIDAD!$BK$30
P34: Datos auxiliares de los gráficos (no editar)
P35: Producto (utilidad) | Q35: Utilidad | S35: Producto (unidades) | T35: Unidades
P36: =IFERROR(IF(LARGE(RENTABILIDAD!$AO$8:$AO$67,1)<=0,"",INDEX(RENTABILIDAD!$AB$8:$AB$67,MATCH(LARGE(RENTABILIDAD!$AO$8:$AO$67,1),RENTABILIDAD!$AO$8:$AO$67,0))),"") | Q36: =IFERROR(IF(LARGE(RENTABILIDAD!$AO$8:$AO$67,1)<=0,"",INDEX(RENTABILIDAD!$AG$8:$AG$67,MATCH(LARGE(RENTABILIDAD!$AO$8:$AO$67,1),RENTABILIDAD!$AO$8:$AO$67,0))),"") | S36: =IFERROR(IF(LARGE(RENTABILIDAD!$AP$8:$AP$67,1)<=0,"",INDEX(RENTABILIDAD!$AB$8:$AB$67,MATCH(LARGE(RENTABILIDAD!$AP$8:$AP$67,1),RENTABILIDAD!$AP$8:$AP$67,0))),"") | T36: =IFERROR(IF(LARGE(RENTABILIDAD!$AP$8:$AP$67,1)<=0,"",INDEX(RENTABILIDAD!$AD$8:$AD$67,MATCH(LARGE(RENTABILIDAD!$AP$8:$AP$67,1),RENTABILIDAD!$AP$8:$AP$67,0))),"")
P37: =IFERROR(IF(LARGE(RENTABILIDAD!$AO$8:$AO$67,2)<=0,"",INDEX(RENTABILIDAD!$AB$8:$AB$67,MATCH(LARGE(RENTABILIDAD!$AO$8:$AO$67,2),RENTABILIDAD!$AO$8:$AO$67,0))),"") | Q37: =IFERROR(IF(LARGE(RENTABILIDAD!$AO$8:$AO$67,2)<=0,"",INDEX(RENTABILIDAD!$AG$8:$AG$67,MATCH(LARGE(RENTABILIDAD!$AO$8:$AO$67,2),RENTABILIDAD!$AO$8:$AO$67,0))),"") | S37: =IFERROR(IF(LARGE(RENTABILIDAD!$AP$8:$AP$67,2)<=0,"",INDEX(RENTABILIDAD!$AB$8:$AB$67,MATCH(LARGE(RENTABILIDAD!$AP$8:$AP$67,2),RENTABILIDAD!$AP$8:$AP$67,0))),"") | T37: =IFERROR(IF(LARGE(RENTABILIDAD!$AP$8:$AP$67,2)<=0,"",INDEX(RENTABILIDAD!$AD$8:$AD$67,MATCH(LARGE(RENTABILIDAD!$AP$8:$AP$67,2),RENTABILIDAD!$AP$8:$AP$67,0))),"")
P38: =IFERROR(IF(LARGE(RENTABILIDAD!$AO$8:$AO$67,3)<=0,"",INDEX(RENTABILIDAD!$AB$8:$AB$67,MATCH(LARGE(RENTABILIDAD!$AO$8:$AO$67,3),RENTABILIDAD!$AO$8:$AO$67,0))),"") | Q38: =IFERROR(IF(LARGE(RENTABILIDAD!$AO$8:$AO$67,3)<=0,"",INDEX(RENTABILIDAD!$AG$8:$AG$67,MATCH(LARGE(RENTABILIDAD!$AO$8:$AO$67,3),RENTABILIDAD!$AO$8:$AO$67,0))),"") | S38: =IFERROR(IF(LARGE(RENTABILIDAD!$AP$8:$AP$67,3)<=0,"",INDEX(RENTABILIDAD!$AB$8:$AB$67,MATCH(LARGE(RENTABILIDAD!$AP$8:$AP$67,3),RENTABILIDAD!$AP$8:$AP$67,0))),"") | T38: =IFERROR(IF(LARGE(RENTABILIDAD!$AP$8:$AP$67,3)<=0,"",INDEX(RENTABILIDAD!$AD$8:$AD$67,MATCH(LARGE(RENTABILIDAD!$AP$8:$AP$67,3),RENTABILIDAD!$AP$8:$AP$67,0))),"")
P39: =IFERROR(IF(LARGE(RENTABILIDAD!$AO$8:$AO$67,4)<=0,"",INDEX(RENTABILIDAD!$AB$8:$AB$67,MATCH(LARGE(RENTABILIDAD!$AO$8:$AO$67,4),RENTABILIDAD!$AO$8:$AO$67,0))),"") | Q39: =IFERROR(IF(LARGE(RENTABILIDAD!$AO$8:$AO$67,4)<=0,"",INDEX(RENTABILIDAD!$AG$8:$AG$67,MATCH(LARGE(RENTABILIDAD!$AO$8:$AO$67,4),RENTABILIDAD!$AO$8:$AO$67,0))),"") | S39: =IFERROR(IF(LARGE(RENTABILIDAD!$AP$8:$AP$67,4)<=0,"",INDEX(RENTABILIDAD!$AB$8:$AB$67,MATCH(LARGE(RENTABILIDAD!$AP$8:$AP$67,4),RENTABILIDAD!$AP$8:$AP$67,0))),"") | T39: =IFERROR(IF(LARGE(RENTABILIDAD!$AP$8:$AP$67,4)<=0,"",INDEX(RENTABILIDAD!$AD$8:$AD$67,MATCH(LARGE(RENTABILIDAD!$AP$8:$AP$67,4),RENTABILIDAD!$AP$8:$AP$67,0))),"")
P40: =IFERROR(IF(LARGE(RENTABILIDAD!$AO$8:$AO$67,5)<=0,"",INDEX(RENTABILIDAD!$AB$8:$AB$67,MATCH(LARGE(RENTABILIDAD!$AO$8:$AO$67,5),RENTABILIDAD!$AO$8:$AO$67,0))),"") | Q40: =IFERROR(IF(LARGE(RENTABILIDAD!$AO$8:$AO$67,5)<=0,"",INDEX(RENTABILIDAD!$AG$8:$AG$67,MATCH(LARGE(RENTABILIDAD!$AO$8:$AO$67,5),RENTABILIDAD!$AO$8:$AO$67,0))),"") | S40: =IFERROR(IF(LARGE(RENTABILIDAD!$AP$8:$AP$67,5)<=0,"",INDEX(RENTABILIDAD!$AB$8:$AB$67,MATCH(LARGE(RENTABILIDAD!$AP$8:$AP$67,5),RENTABILIDAD!$AP$8:$AP$67,0))),"") | T40: =IFERROR(IF(LARGE(RENTABILIDAD!$AP$8:$AP$67,5)<=0,"",INDEX(RENTABILIDAD!$AD$8:$AD$67,MATCH(LARGE(RENTABILIDAD!$AP$8:$AP$67,5),RENTABILIDAD!$AP$8:$AP$67,0))),"")
P41: =IFERROR(IF(LARGE(RENTABILIDAD!$AO$8:$AO$67,6)<=0,"",INDEX(RENTABILIDAD!$AB$8:$AB$67,MATCH(LARGE(RENTABILIDAD!$AO$8:$AO$67,6),RENTABILIDAD!$AO$8:$AO$67,0))),"") | Q41: =IFERROR(IF(LARGE(RENTABILIDAD!$AO$8:$AO$67,6)<=0,"",INDEX(RENTABILIDAD!$AG$8:$AG$67,MATCH(LARGE(RENTABILIDAD!$AO$8:$AO$67,6),RENTABILIDAD!$AO$8:$AO$67,0))),"") | S41: =IFERROR(IF(LARGE(RENTABILIDAD!$AP$8:$AP$67,6)<=0,"",INDEX(RENTABILIDAD!$AB$8:$AB$67,MATCH(LARGE(RENTABILIDAD!$AP$8:$AP$67,6),RENTABILIDAD!$AP$8:$AP$67,0))),"") | T41: =IFERROR(IF(LARGE(RENTABILIDAD!$AP$8:$AP$67,6)<=0,"",INDEX(RENTABILIDAD!$AD$8:$AD$67,MATCH(LARGE(RENTABILIDAD!$AP$8:$AP$67,6),RENTABILIDAD!$AP$8:$AP$67,0))),"")
P42: =IFERROR(IF(LARGE(RENTABILIDAD!$AO$8:$AO$67,7)<=0,"",INDEX(RENTABILIDAD!$AB$8:$AB$67,MATCH(LARGE(RENTABILIDAD!$AO$8:$AO$67,7),RENTABILIDAD!$AO$8:$AO$67,0))),"") | Q42: =IFERROR(IF(LARGE(RENTABILIDAD!$AO$8:$AO$67,7)<=0,"",INDEX(RENTABILIDAD!$AG$8:$AG$67,MATCH(LARGE(RENTABILIDAD!$AO$8:$AO$67,7),RENTABILIDAD!$AO$8:$AO$67,0))),"") | S42: =IFERROR(IF(LARGE(RENTABILIDAD!$AP$8:$AP$67,7)<=0,"",INDEX(RENTABILIDAD!$AB$8:$AB$67,MATCH(LARGE(RENTABILIDAD!$AP$8:$AP$67,7),RENTABILIDAD!$AP$8:$AP$67,0))),"") | T42: =IFERROR(IF(LARGE(RENTABILIDAD!$AP$8:$AP$67,7)<=0,"",INDEX(RENTABILIDAD!$AD$8:$AD$67,MATCH(LARGE(RENTABILIDAD!$AP$8:$AP$67,7),RENTABILIDAD!$AP$8:$AP$67,0))),"")
P43: =IFERROR(IF(LARGE(RENTABILIDAD!$AO$8:$AO$67,8)<=0,"",INDEX(RENTABILIDAD!$AB$8:$AB$67,MATCH(LARGE(RENTABILIDAD!$AO$8:$AO$67,8),RENTABILIDAD!$AO$8:$AO$67,0))),"") | Q43: =IFERROR(IF(LARGE(RENTABILIDAD!$AO$8:$AO$67,8)<=0,"",INDEX(RENTABILIDAD!$AG$8:$AG$67,MATCH(LARGE(RENTABILIDAD!$AO$8:$AO$67,8),RENTABILIDAD!$AO$8:$AO$67,0))),"") | S43: =IFERROR(IF(LARGE(RENTABILIDAD!$AP$8:$AP$67,8)<=0,"",INDEX(RENTABILIDAD!$AB$8:$AB$67,MATCH(LARGE(RENTABILIDAD!$AP$8:$AP$67,8),RENTABILIDAD!$AP$8:$AP$67,0))),"") | T43: =IFERROR(IF(LARGE(RENTABILIDAD!$AP$8:$AP$67,8)<=0,"",INDEX(RENTABILIDAD!$AD$8:$AD$67,MATCH(LARGE(RENTABILIDAD!$AP$8:$AP$67,8),RENTABILIDAD!$AP$8:$AP$67,0))),"")
P44: =IFERROR(IF(LARGE(RENTABILIDAD!$AO$8:$AO$67,9)<=0,"",INDEX(RENTABILIDAD!$AB$8:$AB$67,MATCH(LARGE(RENTABILIDAD!$AO$8:$AO$67,9),RENTABILIDAD!$AO$8:$AO$67,0))),"") | Q44: =IFERROR(IF(LARGE(RENTABILIDAD!$AO$8:$AO$67,9)<=0,"",INDEX(RENTABILIDAD!$AG$8:$AG$67,MATCH(LARGE(RENTABILIDAD!$AO$8:$AO$67,9),RENTABILIDAD!$AO$8:$AO$67,0))),"") | S44: =IFERROR(IF(LARGE(RENTABILIDAD!$AP$8:$AP$67,9)<=0,"",INDEX(RENTABILIDAD!$AB$8:$AB$67,MATCH(LARGE(RENTABILIDAD!$AP$8:$AP$67,9),RENTABILIDAD!$AP$8:$AP$67,0))),"") | T44: =IFERROR(IF(LARGE(RENTABILIDAD!$AP$8:$AP$67,9)<=0,"",INDEX(RENTABILIDAD!$AD$8:$AD$67,MATCH(LARGE(RENTABILIDAD!$AP$8:$AP$67,9),RENTABILIDAD!$AP$8:$AP$67,0))),"")
P45: =IFERROR(IF(LARGE(RENTABILIDAD!$AO$8:$AO$67,10)<=0,"",INDEX(RENTABILIDAD!$AB$8:$AB$67,MATCH(LARGE(RENTABILIDAD!$AO$8:$AO$67,10),RENTABILIDAD!$AO$8:$AO$67,0))),"") | Q45: =IFERROR(IF(LARGE(RENTABILIDAD!$AO$8:$AO$67,10)<=0,"",INDEX(RENTABILIDAD!$AG$8:$AG$67,MATCH(LARGE(RENTABILIDAD!$AO$8:$AO$67,10),RENTABILIDAD!$AO$8:$AO$67,0))),"") | S45: =IFERROR(IF(LARGE(RENTABILIDAD!$AP$8:$AP$67,10)<=0,"",INDEX(RENTABILIDAD!$AB$8:$AB$67,MATCH(LARGE(RENTABILIDAD!$AP$8:$AP$67,10),RENTABILIDAD!$AP$8:$AP$67,0))),"") | T45: =IFERROR(IF(LARGE(RENTABILIDAD!$AP$8:$AP$67,10)<=0,"",INDEX(RENTABILIDAD!$AD$8:$AD$67,MATCH(LARGE(RENTABILIDAD!$AP$8:$AP$67,10),RENTABILIDAD!$AP$8:$AP$67,0))),"")
B88: Los gráficos se actualizan solos al registrar ventas, compras y gastos. Si un gráfico aparece vacío es porque todavía no hay datos de ese tipo.

Sheet PRODUCTOS
A1: PRODUCTOS — Catálogo maestro
A2: Una fila por SKU. Amarillo = usted lo escribe · Gris = lo calcula el sistema. Los costos se capturan en la hoja COSTOS y se reflejan aquí automáticamente.
A3: ⚠ REGLA DE PRECIOS: | B3: La columna «Precio de referencia del catálogo 2016» es SOLO INFORMATIVA y no entra en ningún cálculo. El sistema únicamente usa «Precio de venta actual», que nace vacío: usted debe escribirlo cuando defina sus precios reales.
A6: SKU | B6: Nombre del producto | C6: Categoría | D6: Subcategoría | E6: Presentación | F6: Unidad de medida | G6: Contenido (mL) | H6: Aromas disponibles | I6: Proveedor principal | J6: Precio de referencia del catálogo 2016 (INFORMATIVO) | K6: Precio de venta actual | L6: Costo de compra unitario | M6: Transporte unitario | N6: Impuestos / aranceles unitarios | O6: Empaque unitario | P6: Otros costos variables unitarios | Q6: COSTO REAL UNITARIO | R6: Costo variable de venta unitario | S6: Costo variable TOTAL unitario | T6: Utilidad unitaria | U6: Margen bruto % | V6: Markup % | W6: Margen de contribución unitario | X6: Stock actual | Y6: Stock mínimo | Z6: Stock máximo | AA6: Estado | AB6: Estado de datos | AC6: Fecha de actualización | AD6: Notas
A7: GEL-250 | B7: Gel Desinfectante Antibacterial | C7: Hogar | D7: Desinfección personal | E7: 250 mL | F7: Unidad | G7: 250 | H7: Original, Papaya, Fresa | J7: 35 | L7: =IF($A7="","",IFERROR(IF(INDEX(tblCostos[Costo de compra unitario],MATCH($A7,tblCostos[SKU],0))="","PENDIENTE",INDEX(tblCostos[Costo de compra unitario],MATCH($A7,tblCostos[SKU],0))),"PENDIENTE")) | M7: =IF($A7="","",IFERROR(IF(INDEX(tblCostos[Transporte unitario],MATCH($A7,tblCostos[SKU],0))="","",INDEX(tblCostos[Transporte unitario],MATCH($A7,tblCostos[SKU],0))),"")) | N7: =IF($A7="","",IFERROR(IF(INDEX(tblCostos[Impuestos / aranceles unitarios],MATCH($A7,tblCostos[SKU],0))="","",INDEX(tblCostos[Impuestos / aranceles unitarios],MATCH($A7,tblCostos[SKU],0))),"")) | O7: =IF($A7="","",IFERROR(IF(INDEX(tblCostos[Empaque unitario],MATCH($A7,tblCostos[SKU],0))="","",INDEX(tblCostos[Empaque unitario],MATCH($A7,tblCostos[SKU],0))),"")) | P7: =IF($A7="","",IFERROR(IF(INDEX(tblCostos[Otros costos variables unitarios],MATCH($A7,tblCostos[SKU],0))="","",INDEX(tblCostos[Otros costos variables unitarios],MATCH($A7,tblCostos[SKU],0))),"")) | Q7: =IF($A7="","",IFERROR(IF(INDEX(tblCostos[COSTO REAL UNITARIO],MATCH($A7,tblCostos[SKU],0))="","PENDIENTE",INDEX(tblCostos[COSTO REAL UNITARIO],MATCH($A7,tblCostos[SKU],0))),"PENDIENTE")) | R7: =IF($A7="","",IFERROR(IF(INDEX(tblCostos[Costo variable de venta unitario],MATCH($A7,tblCostos[SKU],0))="","",INDEX(tblCostos[Costo variable de venta unitario],MATCH($A7,tblCostos[SKU],0))),"")) | S7: =IF($A7="","",IF(NOT(ISNUMBER($Q7)),"PENDIENTE",$Q7+IF(ISNUMBER($R7),$R7,0))) | T7: =IF($A7="","",IF(OR($K7="",NOT(ISNUMBER($K7)),NOT(ISNUMBER($Q7))),"PENDIENTE",$K7-$Q7)) | U7: =IF($A7="","",IF(OR(NOT(ISNUMBER($T7)),NOT(ISNUMBER($K7)),$K7<=0),"PENDIENTE",$T7/$K7)) | V7: =IF($A7="","",IF(OR(NOT(ISNUMBER($T7)),NOT(ISNUMBER($Q7)),$Q7<=0),"PENDIENTE",$T7/$Q7)) | W7: =IF($A7="","",IF(OR($K7="",NOT(ISNUMBER($K7)),NOT(ISNUMBER($S7))),"PENDIENTE",$K7-$S7)) | X7: =IF($A7="","",IFERROR(INDEX(tblInventario[Stock actual],MATCH($A7,tblInventario[SKU],0)),0)) | AA7: Activo | AB7: =IF($A7="","",IF(COUNTIF(tblCostos[SKU],$A7)=0,"SIN FILA EN COSTOS",IF(AND($K7="",NOT(ISNUMBER($Q7))),"FALTA PRECIO Y COSTO",IF($K7="","FALTA PRECIO",IF(NOT(ISNUMBER($Q7)),"FALTA COSTO",IF($T7<0,"MARGEN NEGATIVO",IF($T7=0,"PRECIO = COSTO","COMPLETO")))))))
A8: GEL-500 | B8: Gel Desinfectante Antibacterial | C8: Hogar | D8: Desinfección personal | E8: 500 mL | F8: Unidad | G8: 500 | H8: Original, Papaya, Fresa | J8: 70 | L8: =IF($A8="","",IFERROR(IF(INDEX(tblCostos[Costo de compra unitario],MATCH($A8,tblCostos[SKU],0))="","PENDIENTE",INDEX(tblCostos[Costo de compra unitario],MATCH($A8,tblCostos[SKU],0))),"PENDIENTE")) | M8: =IF($A8="","",IFERROR(IF(INDEX(tblCostos[Transporte unitario],MATCH($A8,tblCostos[SKU],0))="","",INDEX(tblCostos[Transporte unitario],MATCH($A8,tblCostos[SKU],0))),"")) | N8: =IF($A8="","",IFERROR(IF(INDEX(tblCostos[Impuestos / aranceles unitarios],MATCH($A8,tblCostos[SKU],0))="","",INDEX(tblCostos[Impuestos / aranceles unitarios],MATCH($A8,tblCostos[SKU],0))),"")) | O8: =IF($A8="","",IFERROR(IF(INDEX(tblCostos[Empaque unitario],MATCH($A8,tblCostos[SKU],0))="","",INDEX(tblCostos[Empaque unitario],MATCH($A8,tblCostos[SKU],0))),"")) | P8: =IF($A8="","",IFERROR(IF(INDEX(tblCostos[Otros costos variables unitarios],MATCH($A8,tblCostos[SKU],0))="","",INDEX(tblCostos[Otros costos variables unitarios],MATCH($A8,tblCostos[SKU],0))),"")) | Q8: =IF($A8="","",IFERROR(IF(INDEX(tblCostos[COSTO REAL UNITARIO],MATCH($A8,tblCostos[SKU],0))="","PENDIENTE",INDEX(tblCostos[COSTO REAL UNITARIO],MATCH($A8,tblCostos[SKU],0))),"PENDIENTE")) | R8: =IF($A8="","",IFERROR(IF(INDEX(tblCostos[Costo variable de venta unitario],MATCH($A8,tblCostos[SKU],0))="","",INDEX(tblCostos[Costo variable de venta unitario],MATCH($A8,tblCostos[SKU],0))),"")) | S8: =IF($A8="","",IF(NOT(ISNUMBER($Q8)),"PENDIENTE",$Q8+IF(ISNUMBER($R8),$R8,0))) | T8: =IF($A8="","",IF(OR($K8="",NOT(ISNUMBER($K8)),NOT(ISNUMBER($Q8))),"PENDIENTE",$K8-$Q8)) | U8: =IF($A8="","",IF(OR(NOT(ISNUMBER($T8)),NOT(ISNUMBER($K8)),$K8<=0),"PENDIENTE",$T8/$K8)) | V8: =IF($A8="","",IF(OR(NOT(ISNUMBER($T8)),NOT(ISNUMBER($Q8)),$Q8<=0),"PENDIENTE",$T8/$Q8)) | W8: =IF($A8="","",IF(OR($K8="",NOT(ISNUMBER($K8)),NOT(ISNUMBER($S8))),"PENDIENTE",$K8-$S8)) | X8: =IF($A8="","",IFERROR(INDEX(tblInventario[Stock actual],MATCH($A8,tblInventario[SKU],0)),0)) | AA8: Activo | AB8: =IF($A8="","",IF(COUNTIF(tblCostos[SKU],$A8)=0,"SIN FILA EN COSTOS",IF(AND($K8="",NOT(ISNUMBER($Q8))),"FALTA PRECIO Y COSTO",IF($K8="","FALTA PRECIO",IF(NOT(ISNUMBER($Q8)),"FALTA COSTO",IF($T8<0,"MARGEN NEGATIVO",IF($T8=0,"PRECIO = COSTO","COMPLETO")))))))
A9: GEL-2L | B9: Gel Desinfectante Antibacterial | C9: Hogar | D9: Desinfección personal | E9: 2 Litros | F9: Unidad | G9: 2000 | H9: Original, Papaya, Fresa | J9: 140 | L9: =IF($A9="","",IFERROR(IF(INDEX(tblCostos[Costo de compra unitario],MATCH($A9,tblCostos[SKU],0))="","PENDIENTE",INDEX(tblCostos[Costo de compra unitario],MATCH($A9,tblCostos[SKU],0))),"PENDIENTE")) | M9: =IF($A9="","",IFERROR(IF(INDEX(tblCostos[Transporte unitario],MATCH($A9,tblCostos[SKU],0))="","",INDEX(tblCostos[Transporte unitario],MATCH($A9,tblCostos[SKU],0))),"")) | N9: =IF($A9="","",IFERROR(IF(INDEX(tblCostos[Impuestos / aranceles unitarios],MATCH($A9,tblCostos[SKU],0))="","",INDEX(tblCostos[Impuestos / aranceles unitarios],MATCH($A9,tblCostos[SKU],0))),"")) | O9: =IF($A9="","",IFERROR(IF(INDEX(tblCostos[Empaque unitario],MATCH($A9,tblCostos[SKU],0))="","",INDEX(tblCostos[Empaque unitario],MATCH($A9,tblCostos[SKU],0))),"")) | P9: =IF($A9="","",IFERROR(IF(INDEX(tblCostos[Otros costos variables unitarios],MATCH($A9,tblCostos[SKU],0))="","",INDEX(tblCostos[Otros costos variables unitarios],MATCH($A9,tblCostos[SKU],0))),"")) | Q9: =IF($A9="","",IFERROR(IF(INDEX(tblCostos[COSTO REAL UNITARIO],MATCH($A9,tblCostos[SKU],0))="","PENDIENTE",INDEX(tblCostos[COSTO REAL UNITARIO],MATCH($A9,tblCostos[SKU],0))),"PENDIENTE")) | R9: =IF($A9="","",IFERROR(IF(INDEX(tblCostos[Costo variable de venta unitario],MATCH($A9,tblCostos[SKU],0))="","",INDEX(tblCostos[Costo variable de venta unitario],MATCH($A9,tblCostos[SKU],0))),"")) | S9: =IF($A9="","",IF(NOT(ISNUMBER($Q9)),"PENDIENTE",$Q9+IF(ISNUMBER($R9),$R9,0))) | T9: =IF($A9="","",IF(OR($K9="",NOT(ISNUMBER($K9)),NOT(ISNUMBER($Q9))),"PENDIENTE",$K9-$Q9)) | U9: =IF($A9="","",IF(OR(NOT(ISNUMBER($T9)),NOT(ISNUMBER($K9)),$K9<=0),"PENDIENTE",$T9/$K9)) | V9: =IF($A9="","",IF(OR(NOT(ISNUMBER($T9)),NOT(ISNUMBER($Q9)),$Q9<=0),"PENDIENTE",$T9/$Q9)) | W9: =IF($A9="","",IF(OR($K9="",NOT(ISNUMBER($K9)),NOT(ISNUMBER($S9))),"PENDIENTE",$K9-$S9)) | X9: =IF($A9="","",IFERROR(INDEX(tblInventario[Stock actual],MATCH($A9,tblInventario[SKU],0)),0)) | AA9: Activo | AB9: =IF($A9="","",IF(COUNTIF(tblCostos[SKU],$A9)=0,"SIN FILA EN COSTOS",IF(AND($K9="",NOT(ISNUMBER($Q9))),"FALTA PRECIO Y COSTO",IF($K9="","FALTA PRECIO",IF(NOT(ISNUMBER($Q9)),"FALTA COSTO",IF($T9<0,"MARGEN NEGATIVO",IF($T9=0,"PRECIO = COSTO","COMPLETO")))))))
A10: GEL-GAL | B10: Gel Desinfectante Antibacterial | C10: Hogar | D10: Desinfección personal | E10: Galón | F10: Unidad | G10: 3785 | H10: Original, Papaya, Fresa | J10: 330 | L10: =IF($A10="","",IFERROR(IF(INDEX(tblCostos[Costo de compra unitario],MATCH($A10,tblCostos[SKU],0))="","PENDIENTE",INDEX(tblCostos[Costo de compra unitario],MATCH($A10,tblCostos[SKU],0))),"PENDIENTE")) | M10: =IF($A10="","",IFERROR(IF(INDEX(tblCostos[Transporte unitario],MATCH($A10,tblCostos[SKU],0))="","",INDEX(tblCostos[Transporte unitario],MATCH($A10,tblCostos[SKU],0))),"")) | N10: =IF($A10="","",IFERROR(IF(INDEX(tblCostos[Impuestos / aranceles unitarios],MATCH($A10,tblCostos[SKU],0))="","",INDEX(tblCostos[Impuestos / aranceles unitarios],MATCH($A10,tblCostos[SKU],0))),"")) | O10: =IF($A10="","",IFERROR(IF(INDEX(tblCostos[Empaque unitario],MATCH($A10,tblCostos[SKU],0))="","",INDEX(tblCostos[Empaque unitario],MATCH($A10,tblCostos[SKU],0))),"")) | P10: =IF($A10="","",IFERROR(IF(INDEX(tblCostos[Otros costos variables unitarios],MATCH($A10,tblCostos[SKU],0))="","",INDEX(tblCostos[Otros costos variables unitarios],MATCH($A10,tblCostos[SKU],0))),"")) | Q10: =IF($A10="","",IFERROR(IF(INDEX(tblCostos[COSTO REAL UNITARIO],MATCH($A10,tblCostos[SKU],0))="","PENDIENTE",INDEX(tblCostos[COSTO REAL UNITARIO],MATCH($A10,tblCostos[SKU],0))),"PENDIENTE")) | R10: =IF($A10="","",IFERROR(IF(INDEX(tblCostos[Costo variable de venta unitario],MATCH($A10,tblCostos[SKU],0))="","",INDEX(tblCostos[Costo variable de venta unitario],MATCH($A10,tblCostos[SKU],0))),"")) | S10: =IF($A10="","",IF(NOT(ISNUMBER($Q10)),"PENDIENTE",$Q10+IF(ISNUMBER($R10),$R10,0))) | T10: =IF($A10="","",IF(OR($K10="",NOT(ISNUMBER($K10)),NOT(ISNUMBER($Q10))),"PENDIENTE",$K10-$Q10)) | U10: =IF($A10="","",IF(OR(NOT(ISNUMBER($T10)),NOT(ISNUMBER($K10)),$K10<=0),"PENDIENTE",$T10/$K10)) | V10: =IF($A10="","",IF(OR(NOT(ISNUMBER($T10)),NOT(ISNUMBER($Q10)),$Q10<=0),"PENDIENTE",$T10/$Q10)) | W10: =IF($A10="","",IF(OR($K10="",NOT(ISNUMBER($K10)),NOT(ISNUMBER($S10))),"PENDIENTE",$K10-$S10)) | X10: =IF($A10="","",IFERROR(INDEX(tblInventario[Stock actual],MATCH($A10,tblInventario[SKU],0)),0)) | AA10: Activo | AB10: =IF($A10="","",IF(COUNTIF(tblCostos[SKU],$A10)=0,"SIN FILA EN COSTOS",IF(AND($K10="",NOT(ISNUMBER($Q10))),"FALTA PRECIO Y COSTO",IF($K10="","FALTA PRECIO",IF(NOT(ISNUMBER($Q10)),"FALTA COSTO",IF($T10<0,"MARGEN NEGATIVO",IF($T10=0,"PRECIO = COSTO","COMPLETO")))))))
A11: JAB-500 | B11: Jabón Líquido para Manos | C11: Hogar | D11: Cuidado personal | E11: 500 mL | F11: Unidad | G11: 500 | H11: Chicle, Floral, Frutas tropicales, Coco, Cherry, Fresh | J11: 60 | L11: =IF($A11="","",IFERROR(IF(INDEX(tblCostos[Costo de compra unitario],MATCH($A11,tblCostos[SKU],0))="","PENDIENTE",INDEX(tblCostos[Costo de compra unitario],MATCH($A11,tblCostos[SKU],0))),"PENDIENTE")) | M11: =IF($A11="","",IFERROR(IF(INDEX(tblCostos[Transporte unitario],MATCH($A11,tblCostos[SKU],0))="","",INDEX(tblCostos[Transporte unitario],MATCH($A11,tblCostos[SKU],0))),"")) | N11: =IF($A11="","",IFERROR(IF(INDEX(tblCostos[Impuestos / aranceles unitarios],MATCH($A11,tblCostos[SKU],0))="","",INDEX(tblCostos[Impuestos / aranceles unitarios],MATCH($A11,tblCostos[SKU],0))),"")) | O11: =IF($A11="","",IFERROR(IF(INDEX(tblCostos[Empaque unitario],MATCH($A11,tblCostos[SKU],0))="","",INDEX(tblCostos[Empaque unitario],MATCH($A11,tblCostos[SKU],0))),"")) | P11: =IF($A11="","",IFERROR(IF(INDEX(tblCostos[Otros costos variables unitarios],MATCH($A11,tblCostos[SKU],0))="","",INDEX(tblCostos[Otros costos variables unitarios],MATCH($A11,tblCostos[SKU],0))),"")) | Q11: =IF($A11="","",IFERROR(IF(INDEX(tblCostos[COSTO REAL UNITARIO],MATCH($A11,tblCostos[SKU],0))="","PENDIENTE",INDEX(tblCostos[COSTO REAL UNITARIO],MATCH($A11,tblCostos[SKU],0))),"PENDIENTE")) | R11: =IF($A11="","",IFERROR(IF(INDEX(tblCostos[Costo variable de venta unitario],MATCH($A11,tblCostos[SKU],0))="","",INDEX(tblCostos[Costo variable de venta unitario],MATCH($A11,tblCostos[SKU],0))),"")) | S11: =IF($A11="","",IF(NOT(ISNUMBER($Q11)),"PENDIENTE",$Q11+IF(ISNUMBER($R11),$R11,0))) | T11: =IF($A11="","",IF(OR($K11="",NOT(ISNUMBER($K11)),NOT(ISNUMBER($Q11))),"PENDIENTE",$K11-$Q11)) | U11: =IF($A11="","",IF(OR(NOT(ISNUMBER($T11)),NOT(ISNUMBER($K11)),$K11<=0),"PENDIENTE",$T11/$K11)) | V11: =IF($A11="","",IF(OR(NOT(ISNUMBER($T11)),NOT(ISNUMBER($Q11)),$Q11<=0),"PENDIENTE",$T11/$Q11)) | W11: =IF($A11="","",IF(OR($K11="",NOT(ISNUMBER($K11)),NOT(ISNUMBER($S11))),"PENDIENTE",$K11-$S11)) | X11: =IF($A11="","",IFERROR(INDEX(tblInventario[Stock actual],MATCH($A11,tblInventario[SKU],0)),0)) | AA11: Activo | AB11: =IF($A11="","",IF(COUNTIF(tblCostos[SKU],$A11)=0,"SIN FILA EN COSTOS",IF(AND($K11="",NOT(ISNUMBER($Q11))),"FALTA PRECIO Y COSTO",IF($K11="","FALTA PRECIO",IF(NOT(ISNUMBER($Q11)),"FALTA COSTO",IF($T11<0,"MARGEN NEGATIVO",IF($T11=0,"PRECIO = COSTO","COMPLETO")))))))
A12: JAB-2L | B12: Jabón Líquido para Manos | C12: Hogar | D12: Cuidado personal | E12: 2 Litros | F12: Unidad | G12: 2000 | H12: Chicle, Floral, Frutas tropicales, Coco, Cherry, Fresh | J12: 100 | L12: =IF($A12="","",IFERROR(IF(INDEX(tblCostos[Costo de compra unitario],MATCH($A12,tblCostos[SKU],0))="","PENDIENTE",INDEX(tblCostos[Costo de compra unitario],MATCH($A12,tblCostos[SKU],0))),"PENDIENTE")) | M12: =IF($A12="","",IFERROR(IF(INDEX(tblCostos[Transporte unitario],MATCH($A12,tblCostos[SKU],0))="","",INDEX(tblCostos[Transporte unitario],MATCH($A12,tblCostos[SKU],0))),"")) | N12: =IF($A12="","",IFERROR(IF(INDEX(tblCostos[Impuestos / aranceles unitarios],MATCH($A12,tblCostos[SKU],0))="","",INDEX(tblCostos[Impuestos / aranceles unitarios],MATCH($A12,tblCostos[SKU],0))),"")) | O12: =IF($A12="","",IFERROR(IF(INDEX(tblCostos[Empaque unitario],MATCH($A12,tblCostos[SKU],0))="","",INDEX(tblCostos[Empaque unitario],MATCH($A12,tblCostos[SKU],0))),"")) | P12: =IF($A12="","",IFERROR(IF(INDEX(tblCostos[Otros costos variables unitarios],MATCH($A12,tblCostos[SKU],0))="","",INDEX(tblCostos[Otros costos variables unitarios],MATCH($A12,tblCostos[SKU],0))),"")) | Q12: =IF($A12="","",IFERROR(IF(INDEX(tblCostos[COSTO REAL UNITARIO],MATCH($A12,tblCostos[SKU],0))="","PENDIENTE",INDEX(tblCostos[COSTO REAL UNITARIO],MATCH($A12,tblCostos[SKU],0))),"PENDIENTE")) | R12: =IF($A12="","",IFERROR(IF(INDEX(tblCostos[Costo variable de venta unitario],MATCH($A12,tblCostos[SKU],0))="","",INDEX(tblCostos[Costo variable de venta unitario],MATCH($A12,tblCostos[SKU],0))),"")) | S12: =IF($A12="","",IF(NOT(ISNUMBER($Q12)),"PENDIENTE",$Q12+IF(ISNUMBER($R12),$R12,0))) | T12: =IF($A12="","",IF(OR($K12="",NOT(ISNUMBER($K12)),NOT(ISNUMBER($Q12))),"PENDIENTE",$K12-$Q12)) | U12: =IF($A12="","",IF(OR(NOT(ISNUMBER($T12)),NOT(ISNUMBER($K12)),$K12<=0),"PENDIENTE",$T12/$K12)) | V12: =IF($A12="","",IF(OR(NOT(ISNUMBER($T12)),NOT(ISNUMBER($Q12)),$Q12<=0),"PENDIENTE",$T12/$Q12)) | W12: =IF($A12="","",IF(OR($K12="",NOT(ISNUMBER($K12)),NOT(ISNUMBER($S12))),"PENDIENTE",$K12-$S12)) | X12: =IF($A12="","",IFERROR(INDEX(tblInventario[Stock actual],MATCH($A12,tblInventario[SKU],0)),0)) | AA12: Activo | AB12: =IF($A12="","",IF(COUNTIF(tblCostos[SKU],$A12)=0,"SIN FILA EN COSTOS",IF(AND($K12="",NOT(ISNUMBER($Q12))),"FALTA PRECIO Y COSTO",IF($K12="","FALTA PRECIO",IF(NOT(ISNUMBER($Q12)),"FALTA COSTO",IF($T12<0,"MARGEN NEGATIVO",IF($T12=0,"PRECIO = COSTO","COMPLETO")))))))
A13: JAB-GAL | B13: Jabón Líquido para Manos | C13: Hogar | D13: Cuidado personal | E13: Galón | F13: Unidad | G13: 3785 | H13: Chicle, Floral, Frutas tropicales, Coco, Cherry, Fresh | J13: 150 | L13: =IF($A13="","",IFERROR(IF(INDEX(tblCostos[Costo de compra unitario],MATCH($A13,tblCostos[SKU],0))="","PENDIENTE",INDEX(tblCostos[Costo de compra unitario],MATCH($A13,tblCostos[SKU],0))),"PENDIENTE")) | M13: =IF($A13="","",IFERROR(IF(INDEX(tblCostos[Transporte unitario],MATCH($A13,tblCostos[SKU],0))="","",INDEX(tblCostos[Transporte unitario],MATCH($A13,tblCostos[SKU],0))),"")) | N13: =IF($A13="","",IFERROR(IF(INDEX(tblCostos[Impuestos / aranceles unitarios],MATCH($A13,tblCostos[SKU],0))="","",INDEX(tblCostos[Impuestos / aranceles unitarios],MATCH($A13,tblCostos[SKU],0))),"")) | O13: =IF($A13="","",IFERROR(IF(INDEX(tblCostos[Empaque unitario],MATCH($A13,tblCostos[SKU],0))="","",INDEX(tblCostos[Empaque unitario],MATCH($A13,tblCostos[SKU],0))),"")) | P13: =IF($A13="","",IFERROR(IF(INDEX(tblCostos[Otros costos variables unitarios],MATCH($A13,tblCostos[SKU],0))="","",INDEX(tblCostos[Otros costos variables unitarios],MATCH($A13,tblCostos[SKU],0))),"")) | Q13: =IF($A13="","",IFERROR(IF(INDEX(tblCostos[COSTO REAL UNITARIO],MATCH($A13,tblCostos[SKU],0))="","PENDIENTE",INDEX(tblCostos[COSTO REAL UNITARIO],MATCH($A13,tblCostos[SKU],0))),"PENDIENTE")) | R13: =IF($A13="","",IFERROR(IF(INDEX(tblCostos[Costo variable de venta unitario],MATCH($A13,tblCostos[SKU],0))="","",INDEX(tblCostos[Costo variable de venta unitario],MATCH($A13,tblCostos[SKU],0))),"")) | S13: =IF($A13="","",IF(NOT(ISNUMBER($Q13)),"PENDIENTE",$Q13+IF(ISNUMBER($R13),$R13,0))) | T13: =IF($A13="","",IF(OR($K13="",NOT(ISNUMBER($K13)),NOT(ISNUMBER($Q13))),"PENDIENTE",$K13-$Q13)) | U13: =IF($A13="","",IF(OR(NOT(ISNUMBER($T13)),NOT(ISNUMBER($K13)),$K13<=0),"PENDIENTE",$T13/$K13)) | V13: =IF($A13="","",IF(OR(NOT(ISNUMBER($T13)),NOT(ISNUMBER($Q13)),$Q13<=0),"PENDIENTE",$T13/$Q13)) | W13: =IF($A13="","",IF(OR($K13="",NOT(ISNUMBER($K13)),NOT(ISNUMBER($S13))),"PENDIENTE",$K13-$S13)) | X13: =IF($A13="","",IFERROR(INDEX(tblInventario[Stock actual],MATCH($A13,tblInventario[SKU],0)),0)) | AA13: Activo | AB13: =IF($A13="","",IF(COUNTIF(tblCostos[SKU],$A13)=0,"SIN FILA EN COSTOS",IF(AND($K13="",NOT(ISNUMBER($Q13))),"FALTA PRECIO Y COSTO",IF($K13="","FALTA PRECIO",IF(NOT(ISNUMBER($Q13)),"FALTA COSTO",IF($T13<0,"MARGEN NEGATIVO",IF($T13=0,"PRECIO = COSTO","COMPLETO")))))))
A14: SUA-GAL | B14: Suavizante sin Enjuague | C14: Lavandería | D14: Suavizantes | E14: Galón | F14: Unidad | G14: 3785 | H14: Floral | J14: 130 | L14: =IF($A14="","",IFERROR(IF(INDEX(tblCostos[Costo de compra unitario],MATCH($A14,tblCostos[SKU],0))="","PENDIENTE",INDEX(tblCostos[Costo de compra unitario],MATCH($A14,tblCostos[SKU],0))),"PENDIENTE")) | M14: =IF($A14="","",IFERROR(IF(INDEX(tblCostos[Transporte unitario],MATCH($A14,tblCostos[SKU],0))="","",INDEX(tblCostos[Transporte unitario],MATCH($A14,tblCostos[SKU],0))),"")) | N14: =IF($A14="","",IFERROR(IF(INDEX(tblCostos[Impuestos / aranceles unitarios],MATCH($A14,tblCostos[SKU],0))="","",INDEX(tblCostos[Impuestos / aranceles unitarios],MATCH($A14,tblCostos[SKU],0))),"")) | O14: =IF($A14="","",IFERROR(IF(INDEX(tblCostos[Empaque unitario],MATCH($A14,tblCostos[SKU],0))="","",INDEX(tblCostos[Empaque unitario],MATCH($A14,tblCostos[SKU],0))),"")) | P14: =IF($A14="","",IFERROR(IF(INDEX(tblCostos[Otros costos variables unitarios],MATCH($A14,tblCostos[SKU],0))="","",INDEX(tblCostos[Otros costos variables unitarios],MATCH($A14,tblCostos[SKU],0))),"")) | Q14: =IF($A14="","",IFERROR(IF(INDEX(tblCostos[COSTO REAL UNITARIO],MATCH($A14,tblCostos[SKU],0))="","PENDIENTE",INDEX(tblCostos[COSTO REAL UNITARIO],MATCH($A14,tblCostos[SKU],0))),"PENDIENTE")) | R14: =IF($A14="","",IFERROR(IF(INDEX(tblCostos[Costo variable de venta unitario],MATCH($A14,tblCostos[SKU],0))="","",INDEX(tblCostos[Costo variable de venta unitario],MATCH($A14,tblCostos[SKU],0))),"")) | S14: =IF($A14="","",IF(NOT(ISNUMBER($Q14)),"PENDIENTE",$Q14+IF(ISNUMBER($R14),$R14,0))) | T14: =IF($A14="","",IF(OR($K14="",NOT(ISNUMBER($K14)),NOT(ISNUMBER($Q14))),"PENDIENTE",$K14-$Q14)) | U14: =IF($A14="","",IF(OR(NOT(ISNUMBER($T14)),NOT(ISNUMBER($K14)),$K14<=0),"PENDIENTE",$T14/$K14)) | V14: =IF($A14="","",IF(OR(NOT(ISNUMBER($T14)),NOT(ISNUMBER($Q14)),$Q14<=0),"PENDIENTE",$T14/$Q14)) | W14: =IF($A14="","",IF(OR($K14="",NOT(ISNUMBER($K14)),NOT(ISNUMBER($S14))),"PENDIENTE",$K14-$S14)) | X14: =IF($A14="","",IFERROR(INDEX(tblInventario[Stock actual],MATCH($A14,tblInventario[SKU],0)),0)) | AA14: Activo | AB14: =IF($A14="","",IF(COUNTIF(tblCostos[SKU],$A14)=0,"SIN FILA EN COSTOS",IF(AND($K14="",NOT(ISNUMBER($Q14))),"FALTA PRECIO Y COSTO",IF($K14="","FALTA PRECIO",IF(NOT(ISNUMBER($Q14)),"FALTA COSTO",IF($T14<0,"MARGEN NEGATIVO",IF($T14=0,"PRECIO = COSTO","COMPLETO")))))))
A15: DET-GAL | B15: Detergente Líquido para Lavadora | C15: Lavandería | D15: Detergentes | E15: Galón | F15: Unidad | G15: 3785 | H15: Floral | J15: 140 | L15: =IF($A15="","",IFERROR(IF(INDEX(tblCostos[Costo de compra unitario],MATCH($A15,tblCostos[SKU],0))="","PENDIENTE",INDEX(tblCostos[Costo de compra unitario],MATCH($A15,tblCostos[SKU],0))),"PENDIENTE")) | M15: =IF($A15="","",IFERROR(IF(INDEX(tblCostos[Transporte unitario],MATCH($A15,tblCostos[SKU],0))="","",INDEX(tblCostos[Transporte unitario],MATCH($A15,tblCostos[SKU],0))),"")) | N15: =IF($A15="","",IFERROR(IF(INDEX(tblCostos[Impuestos / aranceles unitarios],MATCH($A15,tblCostos[SKU],0))="","",INDEX(tblCostos[Impuestos / aranceles unitarios],MATCH($A15,tblCostos[SKU],0))),"")) | O15: =IF($A15="","",IFERROR(IF(INDEX(tblCostos[Empaque unitario],MATCH($A15,tblCostos[SKU],0))="","",INDEX(tblCostos[Empaque unitario],MATCH($A15,tblCostos[SKU],0))),"")) | P15: =IF($A15="","",IFERROR(IF(INDEX(tblCostos[Otros costos variables unitarios],MATCH($A15,tblCostos[SKU],0))="","",INDEX(tblCostos[Otros costos variables unitarios],MATCH($A15,tblCostos[SKU],0))),"")) | Q15: =IF($A15="","",IFERROR(IF(INDEX(tblCostos[COSTO REAL UNITARIO],MATCH($A15,tblCostos[SKU],0))="","PENDIENTE",INDEX(tblCostos[COSTO REAL UNITARIO],MATCH($A15,tblCostos[SKU],0))),"PENDIENTE")) | R15: =IF($A15="","",IFERROR(IF(INDEX(tblCostos[Costo variable de venta unitario],MATCH($A15,tblCostos[SKU],0))="","",INDEX(tblCostos[Costo variable de venta unitario],MATCH($A15,tblCostos[SKU],0))),"")) | S15: =IF($A15="","",IF(NOT(ISNUMBER($Q15)),"PENDIENTE",$Q15+IF(ISNUMBER($R15),$R15,0))) | T15: =IF($A15="","",IF(OR($K15="",NOT(ISNUMBER($K15)),NOT(ISNUMBER($Q15))),"PENDIENTE",$K15-$Q15)) | U15: =IF($A15="","",IF(OR(NOT(ISNUMBER($T15)),NOT(ISNUMBER($K15)),$K15<=0),"PENDIENTE",$T15/$K15)) | V15: =IF($A15="","",IF(OR(NOT(ISNUMBER($T15)),NOT(ISNUMBER($Q15)),$Q15<=0),"PENDIENTE",$T15/$Q15)) | W15: =IF($A15="","",IF(OR($K15="",NOT(ISNUMBER($K15)),NOT(ISNUMBER($S15))),"PENDIENTE",$K15-$S15)) | X15: =IF($A15="","",IFERROR(INDEX(tblInventario[Stock actual],MATCH($A15,tblInventario[SKU],0)),0)) | AA15: Activo | AB15: =IF($A15="","",IF(COUNTIF(tblCostos[SKU],$A15)=0,"SIN FILA EN COSTOS",IF(AND($K15="",NOT(ISNUMBER($Q15))),"FALTA PRECIO Y COSTO",IF($K15="","FALTA PRECIO",IF(NOT(ISNUMBER($Q15)),"FALTA COSTO",IF($T15<0,"MARGEN NEGATIVO",IF($T15=0,"PRECIO = COSTO","COMPLETO")))))))
A16: VID-750 | B16: Limpiador de Vidrios | C16: Limpieza Hogar | D16: Vidrios y cristales | E16: 750 mL | F16: Unidad | G16: 750 | H16: Sin aroma específico | J16: 60 | L16: =IF($A16="","",IFERROR(IF(INDEX(tblCostos[Costo de compra unitario],MATCH($A16,tblCostos[SKU],0))="","PENDIENTE",INDEX(tblCostos[Costo de compra unitario],MATCH($A16,tblCostos[SKU],0))),"PENDIENTE")) | M16: =IF($A16="","",IFERROR(IF(INDEX(tblCostos[Transporte unitario],MATCH($A16,tblCostos[SKU],0))="","",INDEX(tblCostos[Transporte unitario],MATCH($A16,tblCostos[SKU],0))),"")) | N16: =IF($A16="","",IFERROR(IF(INDEX(tblCostos[Impuestos / aranceles unitarios],MATCH($A16,tblCostos[SKU],0))="","",INDEX(tblCostos[Impuestos / aranceles unitarios],MATCH($A16,tblCostos[SKU],0))),"")) | O16: =IF($A16="","",IFERROR(IF(INDEX(tblCostos[Empaque unitario],MATCH($A16,tblCostos[SKU],0))="","",INDEX(tblCostos[Empaque unitario],MATCH($A16,tblCostos[SKU],0))),"")) | P16: =IF($A16="","",IFERROR(IF(INDEX(tblCostos[Otros costos variables unitarios],MATCH($A16,tblCostos[SKU],0))="","",INDEX(tblCostos[Otros costos variables unitarios],MATCH($A16,tblCostos[SKU],0))),"")) | Q16: =IF($A16="","",IFERROR(IF(INDEX(tblCostos[COSTO REAL UNITARIO],MATCH($A16,tblCostos[SKU],0))="","PENDIENTE",INDEX(tblCostos[COSTO REAL UNITARIO],MATCH($A16,tblCostos[SKU],0))),"PENDIENTE")) | R16: =IF($A16="","",IFERROR(IF(INDEX(tblCostos[Costo variable de venta unitario],MATCH($A16,tblCostos[SKU],0))="","",INDEX(tblCostos[Costo variable de venta unitario],MATCH($A16,tblCostos[SKU],0))),"")) | S16: =IF($A16="","",IF(NOT(ISNUMBER($Q16)),"PENDIENTE",$Q16+IF(ISNUMBER($R16),$R16,0))) | T16: =IF($A16="","",IF(OR($K16="",NOT(ISNUMBER($K16)),NOT(ISNUMBER($Q16))),"PENDIENTE",$K16-$Q16)) | U16: =IF($A16="","",IF(OR(NOT(ISNUMBER($T16)),NOT(ISNUMBER($K16)),$K16<=0),"PENDIENTE",$T16/$K16)) | V16: =IF($A16="","",IF(OR(NOT(ISNUMBER($T16)),NOT(ISNUMBER($Q16)),$Q16<=0),"PENDIENTE",$T16/$Q16)) | W16: =IF($A16="","",IF(OR($K16="",NOT(ISNUMBER($K16)),NOT(ISNUMBER($S16))),"PENDIENTE",$K16-$S16)) | X16: =IF($A16="","",IFERROR(INDEX(tblInventario[Stock actual],MATCH($A16,tblInventario[SKU],0)),0)) | AA16: Activo | AB16: =IF($A16="","",IF(COUNTIF(tblCostos[SKU],$A16)=0,"SIN FILA EN COSTOS",IF(AND($K16="",NOT(ISNUMBER($Q16))),"FALTA PRECIO Y COSTO",IF($K16="","FALTA PRECIO",IF(NOT(ISNUMBER($Q16)),"FALTA COSTO",IF($T16<0,"MARGEN NEGATIVO",IF($T16=0,"PRECIO = COSTO","COMPLETO")))))))
A17: VID-GAL | B17: Limpiador de Vidrios | C17: Limpieza Hogar | D17: Vidrios y cristales | E17: Galón | F17: Unidad | G17: 3785 | H17: Sin aroma específico | J17: 120 | L17: =IF($A17="","",IFERROR(IF(INDEX(tblCostos[Costo de compra unitario],MATCH($A17,tblCostos[SKU],0))="","PENDIENTE",INDEX(tblCostos[Costo de compra unitario],MATCH($A17,tblCostos[SKU],0))),"PENDIENTE")) | M17: =IF($A17="","",IFERROR(IF(INDEX(tblCostos[Transporte unitario],MATCH($A17,tblCostos[SKU],0))="","",INDEX(tblCostos[Transporte unitario],MATCH($A17,tblCostos[SKU],0))),"")) | N17: =IF($A17="","",IFERROR(IF(INDEX(tblCostos[Impuestos / aranceles unitarios],MATCH($A17,tblCostos[SKU],0))="","",INDEX(tblCostos[Impuestos / aranceles unitarios],MATCH($A17,tblCostos[SKU],0))),"")) | O17: =IF($A17="","",IFERROR(IF(INDEX(tblCostos[Empaque unitario],MATCH($A17,tblCostos[SKU],0))="","",INDEX(tblCostos[Empaque unitario],MATCH($A17,tblCostos[SKU],0))),"")) | P17: =IF($A17="","",IFERROR(IF(INDEX(tblCostos[Otros costos variables unitarios],MATCH($A17,tblCostos[SKU],0))="","",INDEX(tblCostos[Otros costos variables unitarios],MATCH($A17,tblCostos[SKU],0))),"")) | Q17: =IF($A17="","",IFERROR(IF(INDEX(tblCostos[COSTO REAL UNITARIO],MATCH($A17,tblCostos[SKU],0))="","PENDIENTE",INDEX(tblCostos[COSTO REAL UNITARIO],MATCH($A17,tblCostos[SKU],0))),"PENDIENTE")) | R17: =IF($A17="","",IFERROR(IF(INDEX(tblCostos[Costo variable de venta unitario],MATCH($A17,tblCostos[SKU],0))="","",INDEX(tblCostos[Costo variable de venta unitario],MATCH($A17,tblCostos[SKU],0))),"")) | S17: =IF($A17="","",IF(NOT(ISNUMBER($Q17)),"PENDIENTE",$Q17+IF(ISNUMBER($R17),$R17,0))) | T17: =IF($A17="","",IF(OR($K17="",NOT(ISNUMBER($K17)),NOT(ISNUMBER($Q17))),"PENDIENTE",$K17-$Q17)) | U17: =IF($A17="","",IF(OR(NOT(ISNUMBER($T17)),NOT(ISNUMBER($K17)),$K17<=0),"PENDIENTE",$T17/$K17)) | V17: =IF($A17="","",IF(OR(NOT(ISNUMBER($T17)),NOT(ISNUMBER($Q17)),$Q17<=0),"PENDIENTE",$T17/$Q17)) | W17: =IF($A17="","",IF(OR($K17="",NOT(ISNUMBER($K17)),NOT(ISNUMBER($S17))),"PENDIENTE",$K17-$S17)) | X17: =IF($A17="","",IFERROR(INDEX(tblInventario[Stock actual],MATCH($A17,tblInventario[SKU],0)),0)) | AA17: Activo | AB17: =IF($A17="","",IF(COUNTIF(tblCostos[SKU],$A17)=0,"SIN FILA EN COSTOS",IF(AND($K17="",NOT(ISNUMBER($Q17))),"FALTA PRECIO Y COSTO",IF($K17="","FALTA PRECIO",IF(NOT(ISNUMBER($Q17)),"FALTA COSTO",IF($T17<0,"MARGEN NEGATIVO",IF($T17=0,"PRECIO = COSTO","COMPLETO")))))))
A18: LAV-500 | B18: Deterlente Lavaplatos | C18: Limpieza Hogar | D18: Cocina | E18: 500 mL | F18: Unidad | G18: 500 | H18: Limón | J18: 50 | L18: =IF($A18="","",IFERROR(IF(INDEX(tblCostos[Costo de compra unitario],MATCH($A18,tblCostos[SKU],0))="","PENDIENTE",INDEX(tblCostos[Costo de compra unitario],MATCH($A18,tblCostos[SKU],0))),"PENDIENTE")) | M18: =IF($A18="","",IFERROR(IF(INDEX(tblCostos[Transporte unitario],MATCH($A18,tblCostos[SKU],0))="","",INDEX(tblCostos[Transporte unitario],MATCH($A18,tblCostos[SKU],0))),"")) | N18: =IF($A18="","",IFERROR(IF(INDEX(tblCostos[Impuestos / aranceles unitarios],MATCH($A18,tblCostos[SKU],0))="","",INDEX(tblCostos[Impuestos / aranceles unitarios],MATCH($A18,tblCostos[SKU],0))),"")) | O18: =IF($A18="","",IFERROR(IF(INDEX(tblCostos[Empaque unitario],MATCH($A18,tblCostos[SKU],0))="","",INDEX(tblCostos[Empaque unitario],MATCH($A18,tblCostos[SKU],0))),"")) | P18: =IF($A18="","",IFERROR(IF(INDEX(tblCostos[Otros costos variables unitarios],MATCH($A18,tblCostos[SKU],0))="","",INDEX(tblCostos[Otros costos variables unitarios],MATCH($A18,tblCostos[SKU],0))),"")) | Q18: =IF($A18="","",IFERROR(IF(INDEX(tblCostos[COSTO REAL UNITARIO],MATCH($A18,tblCostos[SKU],0))="","PENDIENTE",INDEX(tblCostos[COSTO REAL UNITARIO],MATCH($A18,tblCostos[SKU],0))),"PENDIENTE")) | R18: =IF($A18="","",IFERROR(IF(INDEX(tblCostos[Costo variable de venta unitario],MATCH($A18,tblCostos[SKU],0))="","",INDEX(tblCostos[Costo variable de venta unitario],MATCH($A18,tblCostos[SKU],0))),"")) | S18: =IF($A18="","",IF(NOT(ISNUMBER($Q18)),"PENDIENTE",$Q18+IF(ISNUMBER($R18),$R18,0))) | T18: =IF($A18="","",IF(OR($K18="",NOT(ISNUMBER($K18)),NOT(ISNUMBER($Q18))),"PENDIENTE",$K18-$Q18)) | U18: =IF($A18="","",IF(OR(NOT(ISNUMBER($T18)),NOT(ISNUMBER($K18)),$K18<=0),"PENDIENTE",$T18/$K18)) | V18: =IF($A18="","",IF(OR(NOT(ISNUMBER($T18)),NOT(ISNUMBER($Q18)),$Q18<=0),"PENDIENTE",$T18/$Q18)) | W18: =IF($A18="","",IF(OR($K18="",NOT(ISNUMBER($K18)),NOT(ISNUMBER($S18))),"PENDIENTE",$K18-$S18)) | X18: =IF($A18="","",IFERROR(INDEX(tblInventario[Stock actual],MATCH($A18,tblInventario[SKU],0)),0)) | AA18: Activo | AB18: =IF($A18="","",IF(COUNTIF(tblCostos[SKU],$A18)=0,"SIN FILA EN COSTOS",IF(AND($K18="",NOT(ISNUMBER($Q18))),"FALTA PRECIO Y COSTO",IF($K18="","FALTA PRECIO",IF(NOT(ISNUMBER($Q18)),"FALTA COSTO",IF($T18<0,"MARGEN NEGATIVO",IF($T18=0,"PRECIO = COSTO","COMPLETO")))))))
... A39: PLL-710 | B39: Puli-Llanta en Crema | C39: Automotriz | D39: Abrillantadores | E39: 710 mL | F39: Unidad | G39: 710 | H39: Original | J39: 75 | L39: =IF($A39="","",IFERROR(IF(INDEX(tblCostos[Costo de compra unitario],MATCH($A39,tblCostos[SKU],0))="","PENDIENTE",INDEX(tblCostos[Costo de compra unitario],MATCH($A39,tblCostos[SKU],0))),"PENDIENTE")) | M39: =IF($A39="","",IFERROR(IF(INDEX(tblCostos[Transporte unitario],MATCH($A39,tblCostos[SKU],0))="","",INDEX(tblCostos[Transporte unitario],MATCH($A39,tblCostos[SKU],0))),"")) | N39: =IF($A39="","",IFERROR(IF(INDEX(tblCostos[Impuestos / aranceles unitarios],MATCH($A39,tblCostos[SKU],0))="","",INDEX(tblCostos[Impuestos / aranceles unitarios],MATCH($A39,tblCostos[SKU],0))),"")) | O39: =IF($A39="","",IFERROR(IF(INDEX(tblCostos[Empaque unitario],MATCH($A39,tblCostos[SKU],0))="","",INDEX(tblCostos[Empaque unitario],MATCH($A39,tblCostos[SKU],0))),"")) | P39: =IF($A39="","",IFERROR(IF(INDEX(tblCostos[Otros costos variables unitarios],MATCH($A39,tblCostos[SKU],0))="","",INDEX(tblCostos[Otros costos variables unitarios],MATCH($A39,tblCostos[SKU],0))),"")) | Q39: =IF($A39="","",IFERROR(IF(INDEX(tblCostos[COSTO REAL UNITARIO],MATCH($A39,tblCostos[SKU],0))="","PENDIENTE",INDEX(tblCostos[COSTO REAL UNITARIO],MATCH($A39,tblCostos[SKU],0))),"PENDIENTE")) | R39: =IF($A39="","",IFERROR(IF(INDEX(tblCostos[Costo variable de venta unitario],MATCH($A39,tblCostos[SKU],0))="","",INDEX(tblCostos[Costo variable de venta unitario],MATCH($A39,tblCostos[SKU],0))),"")) | S39: =IF($A39="","",IF(NOT(ISNUMBER($Q39)),"PENDIENTE",$Q39+IF(ISNUMBER($R39),$R39,0))) | T39: =IF($A39="","",IF(OR($K39="",NOT(ISNUMBER($K39)),NOT(ISNUMBER($Q39))),"PENDIENTE",$K39-$Q39)) | U39: =IF($A39="","",IF(OR(NOT(ISNUMBER($T39)),NOT(ISNUMBER($K39)),$K39<=0),"PENDIENTE",$T39/$K39)) | V39: =IF($A39="","",IF(OR(NOT(ISNUMBER($T39)),NOT(ISNUMBER($Q39)),$Q39<=0),"PENDIENTE",$T39/$Q39)) | W39: =IF($A39="","",IF(OR($K39="",NOT(ISNUMBER($K39)),NOT(ISNUMBER($S39))),"PENDIENTE",$K39-$S39)) | X39: =IF($A39="","",IFERROR(INDEX(tblInventario[Stock actual],MATCH($A39,tblInventario[SKU],0)),0)) | AA39: Activo | AB39: =IF($A39="","",IF(COUNTIF(tblCostos[SKU],$A39)=0,"SIN FILA EN COSTOS",IF(AND($K39="",NOT(ISNUMBER($Q39))),"FALTA PRECIO Y COSTO",IF($K39="","FALTA PRECIO",IF(NOT(ISNUMBER($Q39)),"FALTA COSTO",IF($T39<0,"MARGEN NEGATIVO",IF($T39=0,"PRECIO = COSTO","COMPLETO")))))))
A40: PLL-TAR | B40: Puli-Llanta en Crema | C40: Automotriz | D40: Abrillantadores | E40: Tarro | F40: Unidad | H40: Original | J40: 50 | L40: =IF($A40="","",IFERROR(IF(INDEX(tblCostos[Costo de compra unitario],MATCH($A40,tblCostos[SKU],0))="","PENDIENTE",INDEX(tblCostos[Costo de compra unitario],MATCH($A40,tblCostos[SKU],0))),"PENDIENTE")) | M40: =IF($A40="","",IFERROR(IF(INDEX(tblCostos[Transporte unitario],MATCH($A40,tblCostos[SKU],0))="","",INDEX(tblCostos[Transporte unitario],MATCH($A40,tblCostos[SKU],0))),"")) | N40: =IF($A40="","",IFERROR(IF(INDEX(tblCostos[Impuestos / aranceles unitarios],MATCH($A40,tblCostos[SKU],0))="","",INDEX(tblCostos[Impuestos / aranceles unitarios],MATCH($A40,tblCostos[SKU],0))),"")) | O40: =IF($A40="","",IFERROR(IF(INDEX(tblCostos[Empaque unitario],MATCH($A40,tblCostos[SKU],0))="","",INDEX(tblCostos[Empaque unitario],MATCH($A40,tblCostos[SKU],0))),"")) | P40: =IF($A40="","",IFERROR(IF(INDEX(tblCostos[Otros costos variables unitarios],MATCH($A40,tblCostos[SKU],0))="","",INDEX(tblCostos[Otros costos variables unitarios],MATCH($A40,tblCostos[SKU],0))),"")) | Q40: =IF($A40="","",IFERROR(IF(INDEX(tblCostos[COSTO REAL UNITARIO],MATCH($A40,tblCostos[SKU],0))="","PENDIENTE",INDEX(tblCostos[COSTO REAL UNITARIO],MATCH($A40,tblCostos[SKU],0))),"PENDIENTE")) | R40: =IF($A40="","",IFERROR(IF(INDEX(tblCostos[Costo variable de venta unitario],MATCH($A40,tblCostos[SKU],0))="","",INDEX(tblCostos[Costo variable de venta unitario],MATCH($A40,tblCostos[SKU],0))),"")) | S40: =IF($A40="","",IF(NOT(ISNUMBER($Q40)),"PENDIENTE",$Q40+IF(ISNUMBER($R40),$R40,0))) | T40: =IF($A40="","",IF(OR($K40="",NOT(ISNUMBER($K40)),NOT(ISNUMBER($Q40))),"PENDIENTE",$K40-$Q40)) | U40: =IF($A40="","",IF(OR(NOT(ISNUMBER($T40)),NOT(ISNUMBER($K40)),$K40<=0),"PENDIENTE",$T40/$K40)) | V40: =IF($A40="","",IF(OR(NOT(ISNUMBER($T40)),NOT(ISNUMBER($Q40)),$Q40<=0),"PENDIENTE",$T40/$Q40)) | W40: =IF($A40="","",IF(OR($K40="",NOT(ISNUMBER($K40)),NOT(ISNUMBER($S40))),"PENDIENTE",$K40-$S40)) | X40: =IF($A40="","",IFERROR(INDEX(tblInventario[Stock actual],MATCH($A40,tblInventario[SKU],0)),0)) | AA40: Activo | AB40: =IF($A40="","",IF(COUNTIF(tblCostos[SKU],$A40)=0,"SIN FILA EN COSTOS",IF(AND($K40="",NOT(ISNUMBER($Q40))),"FALTA PRECIO Y COSTO",IF($K40="","FALTA PRECIO",IF(NOT(ISNUMBER($Q40)),"FALTA COSTO",IF($T40<0,"MARGEN NEGATIVO",IF($T40=0,"PRECIO = COSTO","COMPLETO")))))))
A41: PLL-GAL | B41: Puli-Llanta en Crema | C41: Automotriz | D41: Abrillantadores | E41: Galón | F41: Unidad | G41: 3785 | H41: Original | J41: 190 | L41: =IF($A41="","",IFERROR(IF(INDEX(tblCostos[Costo de compra unitario],MATCH($A41,tblCostos[SKU],0))="","PENDIENTE",INDEX(tblCostos[Costo de compra unitario],MATCH($A41,tblCostos[SKU],0))),"PENDIENTE")) | M41: =IF($A41="","",IFERROR(IF(INDEX(tblCostos[Transporte unitario],MATCH($A41,tblCostos[SKU],0))="","",INDEX(tblCostos[Transporte unitario],MATCH($A41,tblCostos[SKU],0))),"")) | N41: =IF($A41="","",IFERROR(IF(INDEX(tblCostos[Impuestos / aranceles unitarios],MATCH($A41,tblCostos[SKU],0))="","",INDEX(tblCostos[Impuestos / aranceles unitarios],MATCH($A41,tblCostos[SKU],0))),"")) | O41: =IF($A41="","",IFERROR(IF(INDEX(tblCostos[Empaque unitario],MATCH($A41,tblCostos[SKU],0))="","",INDEX(tblCostos[Empaque unitario],MATCH($A41,tblCostos[SKU],0))),"")) | P41: =IF($A41="","",IFERROR(IF(INDEX(tblCostos[Otros costos variables unitarios],MATCH($A41,tblCostos[SKU],0))="","",INDEX(tblCostos[Otros costos variables unitarios],MATCH($A41,tblCostos[SKU],0))),"")) | Q41: =IF($A41="","",IFERROR(IF(INDEX(tblCostos[COSTO REAL UNITARIO],MATCH($A41,tblCostos[SKU],0))="","PENDIENTE",INDEX(tblCostos[COSTO REAL UNITARIO],MATCH($A41,tblCostos[SKU],0))),"PENDIENTE")) | R41: =IF($A41="","",IFERROR(IF(INDEX(tblCostos[Costo variable de venta unitario],MATCH($A41,tblCostos[SKU],0))="","",INDEX(tblCostos[Costo variable de venta unitario],MATCH($A41,tblCostos[SKU],0))),"")) | S41: =IF($A41="","",IF(NOT(ISNUMBER($Q41)),"PENDIENTE",$Q41+IF(ISNUMBER($R41),$R41,0))) | T41: =IF($A41="","",IF(OR($K41="",NOT(ISNUMBER($K41)),NOT(ISNUMBER($Q41))),"PENDIENTE",$K41-$Q41)) | U41: =IF($A41="","",IF(OR(NOT(ISNUMBER($T41)),NOT(ISNUMBER($K41)),$K41<=0),"PENDIENTE",$T41/$K41)) | V41: =IF($A41="","",IF(OR(NOT(ISNUMBER($T41)),NOT(ISNUMBER($Q41)),$Q41<=0),"PENDIENTE",$T41/$Q41)) | W41: =IF($A41="","",IF(OR($K41="",NOT(ISNUMBER($K41)),NOT(ISNUMBER($S41))),"PENDIENTE",$K41-$S41)) | X41: =IF($A41="","",IFERROR(INDEX(tblInventario[Stock actual],MATCH($A41,tblInventario[SKU],0)),0)) | AA41: Activo | AB41: =IF($A41="","",IF(COUNTIF(tblCostos[SKU],$A41)=0,"SIN FILA EN COSTOS",IF(AND($K41="",NOT(ISNUMBER($Q41))),"FALTA PRECIO Y COSTO",IF($K41="","FALTA PRECIO",IF(NOT(ISNUMBER($Q41)),"FALTA COSTO",IF($T41<0,"MARGEN NEGATIVO",IF($T41=0,"PRECIO = COSTO","COMPLETO")))))))
A42: PMA-8OZ | B42: Puli-Manos Crema Limpiadora | C42: Industrial | D42: Limpieza de manos | E42: 8 Onzas | F42: Unidad | G42: 237 | H42: Original | J42: 40 | L42: =IF($A42="","",IFERROR(IF(INDEX(tblCostos[Costo de compra unitario],MATCH($A42,tblCostos[SKU],0))="","PENDIENTE",INDEX(tblCostos[Costo de compra unitario],MATCH($A42,tblCostos[SKU],0))),"PENDIENTE")) | M42: =IF($A42="","",IFERROR(IF(INDEX(tblCostos[Transporte unitario],MATCH($A42,tblCostos[SKU],0))="","",INDEX(tblCostos[Transporte unitario],MATCH($A42,tblCostos[SKU],0))),"")) | N42: =IF($A42="","",IFERROR(IF(INDEX(tblCostos[Impuestos / aranceles unitarios],MATCH($A42,tblCostos[SKU],0))="","",INDEX(tblCostos[Impuestos / aranceles unitarios],MATCH($A42,tblCostos[SKU],0))),"")) | O42: =IF($A42="","",IFERROR(IF(INDEX(tblCostos[Empaque unitario],MATCH($A42,tblCostos[SKU],0))="","",INDEX(tblCostos[Empaque unitario],MATCH($A42,tblCostos[SKU],0))),"")) | P42: =IF($A42="","",IFERROR(IF(INDEX(tblCostos[Otros costos variables unitarios],MATCH($A42,tblCostos[SKU],0))="","",INDEX(tblCostos[Otros costos variables unitarios],MATCH($A42,tblCostos[SKU],0))),"")) | Q42: =IF($A42="","",IFERROR(IF(INDEX(tblCostos[COSTO REAL UNITARIO],MATCH($A42,tblCostos[SKU],0))="","PENDIENTE",INDEX(tblCostos[COSTO REAL UNITARIO],MATCH($A42,tblCostos[SKU],0))),"PENDIENTE")) | R42: =IF($A42="","",IFERROR(IF(INDEX(tblCostos[Costo variable de venta unitario],MATCH($A42,tblCostos[SKU],0))="","",INDEX(tblCostos[Costo variable de venta unitario],MATCH($A42,tblCostos[SKU],0))),"")) | S42: =IF($A42="","",IF(NOT(ISNUMBER($Q42)),"PENDIENTE",$Q42+IF(ISNUMBER($R42),$R42,0))) | T42: =IF($A42="","",IF(OR($K42="",NOT(ISNUMBER($K42)),NOT(ISNUMBER($Q42))),"PENDIENTE",$K42-$Q42)) | U42: =IF($A42="","",IF(OR(NOT(ISNUMBER($T42)),NOT(ISNUMBER($K42)),$K42<=0),"PENDIENTE",$T42/$K42)) | V42: =IF($A42="","",IF(OR(NOT(ISNUMBER($T42)),NOT(ISNUMBER($Q42)),$Q42<=0),"PENDIENTE",$T42/$Q42)) | W42: =IF($A42="","",IF(OR($K42="",NOT(ISNUMBER($K42)),NOT(ISNUMBER($S42))),"PENDIENTE",$K42-$S42)) | X42: =IF($A42="","",IFERROR(INDEX(tblInventario[Stock actual],MATCH($A42,tblInventario[SKU],0)),0)) | AA42: Activo | AB42: =IF($A42="","",IF(COUNTIF(tblCostos[SKU],$A42)=0,"SIN FILA EN COSTOS",IF(AND($K42="",NOT(ISNUMBER($Q42))),"FALTA PRECIO Y COSTO",IF($K42="","FALTA PRECIO",IF(NOT(ISNUMBER($Q42)),"FALTA COSTO",IF($T42<0,"MARGEN NEGATIVO",IF($T42=0,"PRECIO = COSTO","COMPLETO")))))))
A43: PMA-1L | B43: Puli-Manos Crema Limpiadora | C43: Industrial | D43: Limpieza de manos | E43: 1 Litro | F43: Unidad | G43: 1000 | H43: Original | J43: 95 | L43: =IF($A43="","",IFERROR(IF(INDEX(tblCostos[Costo de compra unitario],MATCH($A43,tblCostos[SKU],0))="","PENDIENTE",INDEX(tblCostos[Costo de compra unitario],MATCH($A43,tblCostos[SKU],0))),"PENDIENTE")) | M43: =IF($A43="","",IFERROR(IF(INDEX(tblCostos[Transporte unitario],MATCH($A43,tblCostos[SKU],0))="","",INDEX(tblCostos[Transporte unitario],MATCH($A43,tblCostos[SKU],0))),"")) | N43: =IF($A43="","",IFERROR(IF(INDEX(tblCostos[Impuestos / aranceles unitarios],MATCH($A43,tblCostos[SKU],0))="","",INDEX(tblCostos[Impuestos / aranceles unitarios],MATCH($A43,tblCostos[SKU],0))),"")) | O43: =IF($A43="","",IFERROR(IF(INDEX(tblCostos[Empaque unitario],MATCH($A43,tblCostos[SKU],0))="","",INDEX(tblCostos[Empaque unitario],MATCH($A43,tblCostos[SKU],0))),"")) | P43: =IF($A43="","",IFERROR(IF(INDEX(tblCostos[Otros costos variables unitarios],MATCH($A43,tblCostos[SKU],0))="","",INDEX(tblCostos[Otros costos variables unitarios],MATCH($A43,tblCostos[SKU],0))),"")) | Q43: =IF($A43="","",IFERROR(IF(INDEX(tblCostos[COSTO REAL UNITARIO],MATCH($A43,tblCostos[SKU],0))="","PENDIENTE",INDEX(tblCostos[COSTO REAL UNITARIO],MATCH($A43,tblCostos[SKU],0))),"PENDIENTE")) | R43: =IF($A43="","",IFERROR(IF(INDEX(tblCostos[Costo variable de venta unitario],MATCH($A43,tblCostos[SKU],0))="","",INDEX(tblCostos[Costo variable de venta unitario],MATCH($A43,tblCostos[SKU],0))),"")) | S43: =IF($A43="","",IF(NOT(ISNUMBER($Q43)),"PENDIENTE",$Q43+IF(ISNUMBER($R43),$R43,0))) | T43: =IF($A43="","",IF(OR($K43="",NOT(ISNUMBER($K43)),NOT(ISNUMBER($Q43))),"PENDIENTE",$K43-$Q43)) | U43: =IF($A43="","",IF(OR(NOT(ISNUMBER($T43)),NOT(ISNUMBER($K43)),$K43<=0),"PENDIENTE",$T43/$K43)) | V43: =IF($A43="","",IF(OR(NOT(ISNUMBER($T43)),NOT(ISNUMBER($Q43)),$Q43<=0),"PENDIENTE",$T43/$Q43)) | W43: =IF($A43="","",IF(OR($K43="",NOT(ISNUMBER($K43)),NOT(ISNUMBER($S43))),"PENDIENTE",$K43-$S43)) | X43: =IF($A43="","",IFERROR(INDEX(tblInventario[Stock actual],MATCH($A43,tblInventario[SKU],0)),0)) | AA43: Activo | AB43: =IF($A43="","",IF(COUNTIF(tblCostos[SKU],$A43)=0,"SIN FILA EN COSTOS",IF(AND($K43="",NOT(ISNUMBER($Q43))),"FALTA PRECIO Y COSTO",IF($K43="","FALTA PRECIO",IF(NOT(ISNUMBER($Q43)),"FALTA COSTO",IF($T43<0,"MARGEN NEGATIVO",IF($T43=0,"PRECIO = COSTO","COMPLETO")))))))
A44: PMA-GAL | B44: Puli-Manos Crema Limpiadora | C44: Industrial | D44: Limpieza de manos | E44: Galón | F44: Unidad | G44: 3785 | H44: Original | J44: 300 | L44: =IF($A44="","",IFERROR(IF(INDEX(tblCostos[Costo de compra unitario],MATCH($A44,tblCostos[SKU],0))="","PENDIENTE",INDEX(tblCostos[Costo de compra unitario],MATCH($A44,tblCostos[SKU],0))),"PENDIENTE")) | M44: =IF($A44="","",IFERROR(IF(INDEX(tblCostos[Transporte unitario],MATCH($A44,tblCostos[SKU],0))="","",INDEX(tblCostos[Transporte unitario],MATCH($A44,tblCostos[SKU],0))),"")) | N44: =IF($A44="","",IFERROR(IF(INDEX(tblCostos[Impuestos / aranceles unitarios],MATCH($A44,tblCostos[SKU],0))="","",INDEX(tblCostos[Impuestos / aranceles unitarios],MATCH($A44,tblCostos[SKU],0))),"")) | O44: =IF($A44="","",IFERROR(IF(INDEX(tblCostos[Empaque unitario],MATCH($A44,tblCostos[SKU],0))="","",INDEX(tblCostos[Empaque unitario],MATCH($A44,tblCostos[SKU],0))),"")) | P44: =IF($A44="","",IFERROR(IF(INDEX(tblCostos[Otros costos variables unitarios],MATCH($A44,tblCostos[SKU],0))="","",INDEX(tblCostos[Otros costos variables unitarios],MATCH($A44,tblCostos[SKU],0))),"")) | Q44: =IF($A44="","",IFERROR(IF(INDEX(tblCostos[COSTO REAL UNITARIO],MATCH($A44,tblCostos[SKU],0))="","PENDIENTE",INDEX(tblCostos[COSTO REAL UNITARIO],MATCH($A44,tblCostos[SKU],0))),"PENDIENTE")) | R44: =IF($A44="","",IFERROR(IF(INDEX(tblCostos[Costo variable de venta unitario],MATCH($A44,tblCostos[SKU],0))="","",INDEX(tblCostos[Costo variable de venta unitario],MATCH($A44,tblCostos[SKU],0))),"")) | S44: =IF($A44="","",IF(NOT(ISNUMBER($Q44)),"PENDIENTE",$Q44+IF(ISNUMBER($R44),$R44,0))) | T44: =IF($A44="","",IF(OR($K44="",NOT(ISNUMBER($K44)),NOT(ISNUMBER($Q44))),"PENDIENTE",$K44-$Q44)) | U44: =IF($A44="","",IF(OR(NOT(ISNUMBER($T44)),NOT(ISNUMBER($K44)),$K44<=0),"PENDIENTE",$T44/$K44)) | V44: =IF($A44="","",IF(OR(NOT(ISNUMBER($T44)),NOT(ISNUMBER($Q44)),$Q44<=0),"PENDIENTE",$T44/$Q44)) | W44: =IF($A44="","",IF(OR($K44="",NOT(ISNUMBER($K44)),NOT(ISNUMBER($S44))),"PENDIENTE",$K44-$S44)) | X44: =IF($A44="","",IFERROR(INDEX(tblInventario[Stock actual],MATCH($A44,tblInventario[SKU],0)),0)) | AA44: Activo | AB44: =IF($A44="","",IF(COUNTIF(tblCostos[SKU],$A44)=0,"SIN FILA EN COSTOS",IF(AND($K44="",NOT(ISNUMBER($Q44))),"FALTA PRECIO Y COSTO",IF($K44="","FALTA PRECIO",IF(NOT(ISNUMBER($Q44)),"FALTA COSTO",IF($T44<0,"MARGEN NEGATIVO",IF($T44=0,"PRECIO = COSTO","COMPLETO")))))))
A45: DEI-1L | B45: Desengrasante Industrial | C45: Industrial | D45: Desengrasantes | E45: 1 Litro | F45: Unidad | G45: 1000 | H45: Sin aroma específico | J45: 100 | L45: =IF($A45="","",IFERROR(IF(INDEX(tblCostos[Costo de compra unitario],MATCH($A45,tblCostos[SKU],0))="","PENDIENTE",INDEX(tblCostos[Costo de compra unitario],MATCH($A45,tblCostos[SKU],0))),"PENDIENTE")) | M45: =IF($A45="","",IFERROR(IF(INDEX(tblCostos[Transporte unitario],MATCH($A45,tblCostos[SKU],0))="","",INDEX(tblCostos[Transporte unitario],MATCH($A45,tblCostos[SKU],0))),"")) | N45: =IF($A45="","",IFERROR(IF(INDEX(tblCostos[Impuestos / aranceles unitarios],MATCH($A45,tblCostos[SKU],0))="","",INDEX(tblCostos[Impuestos / aranceles unitarios],MATCH($A45,tblCostos[SKU],0))),"")) | O45: =IF($A45="","",IFERROR(IF(INDEX(tblCostos[Empaque unitario],MATCH($A45,tblCostos[SKU],0))="","",INDEX(tblCostos[Empaque unitario],MATCH($A45,tblCostos[SKU],0))),"")) | P45: =IF($A45="","",IFERROR(IF(INDEX(tblCostos[Otros costos variables unitarios],MATCH($A45,tblCostos[SKU],0))="","",INDEX(tblCostos[Otros costos variables unitarios],MATCH($A45,tblCostos[SKU],0))),"")) | Q45: =IF($A45="","",IFERROR(IF(INDEX(tblCostos[COSTO REAL UNITARIO],MATCH($A45,tblCostos[SKU],0))="","PENDIENTE",INDEX(tblCostos[COSTO REAL UNITARIO],MATCH($A45,tblCostos[SKU],0))),"PENDIENTE")) | R45: =IF($A45="","",IFERROR(IF(INDEX(tblCostos[Costo variable de venta unitario],MATCH($A45,tblCostos[SKU],0))="","",INDEX(tblCostos[Costo variable de venta unitario],MATCH($A45,tblCostos[SKU],0))),"")) | S45: =IF($A45="","",IF(NOT(ISNUMBER($Q45)),"PENDIENTE",$Q45+IF(ISNUMBER($R45),$R45,0))) | T45: =IF($A45="","",IF(OR($K45="",NOT(ISNUMBER($K45)),NOT(ISNUMBER($Q45))),"PENDIENTE",$K45-$Q45)) | U45: =IF($A45="","",IF(OR(NOT(ISNUMBER($T45)),NOT(ISNUMBER($K45)),$K45<=0),"PENDIENTE",$T45/$K45)) | V45: =IF($A45="","",IF(OR(NOT(ISNUMBER($T45)),NOT(ISNUMBER($Q45)),$Q45<=0),"PENDIENTE",$T45/$Q45)) | W45: =IF($A45="","",IF(OR($K45="",NOT(ISNUMBER($K45)),NOT(ISNUMBER($S45))),"PENDIENTE",$K45-$S45)) | X45: =IF($A45="","",IFERROR(INDEX(tblInventario[Stock actual],MATCH($A45,tblInventario[SKU],0)),0)) | AA45: Activo | AB45: =IF($A45="","",IF(COUNTIF(tblCostos[SKU],$A45)=0,"SIN FILA EN COSTOS",IF(AND($K45="",NOT(ISNUMBER($Q45))),"FALTA PRECIO Y COSTO",IF($K45="","FALTA PRECIO",IF(NOT(ISNUMBER($Q45)),"FALTA COSTO",IF($T45<0,"MARGEN NEGATIVO",IF($T45=0,"PRECIO = COSTO","COMPLETO")))))))
A46: DEI-GAL | B46: Desengrasante Industrial | C46: Industrial | D46: Desengrasantes | E46: Galón | F46: Unidad | G46: 3785 | H46: Sin aroma específico | J46: 300 | L46: =IF($A46="","",IFERROR(IF(INDEX(tblCostos[Costo de compra unitario],MATCH($A46,tblCostos[SKU],0))="","PENDIENTE",INDEX(tblCostos[Costo de compra unitario],MATCH($A46,tblCostos[SKU],0))),"PENDIENTE")) | M46: =IF($A46="","",IFERROR(IF(INDEX(tblCostos[Transporte unitario],MATCH($A46,tblCostos[SKU],0))="","",INDEX(tblCostos[Transporte unitario],MATCH($A46,tblCostos[SKU],0))),"")) | N46: =IF($A46="","",IFERROR(IF(INDEX(tblCostos[Impuestos / aranceles unitarios],MATCH($A46,tblCostos[SKU],0))="","",INDEX(tblCostos[Impuestos / aranceles unitarios],MATCH($A46,tblCostos[SKU],0))),"")) | O46: =IF($A46="","",IFERROR(IF(INDEX(tblCostos[Empaque unitario],MATCH($A46,tblCostos[SKU],0))="","",INDEX(tblCostos[Empaque unitario],MATCH($A46,tblCostos[SKU],0))),"")) | P46: =IF($A46="","",IFERROR(IF(INDEX(tblCostos[Otros costos variables unitarios],MATCH($A46,tblCostos[SKU],0))="","",INDEX(tblCostos[Otros costos variables unitarios],MATCH($A46,tblCostos[SKU],0))),"")) | Q46: =IF($A46="","",IFERROR(IF(INDEX(tblCostos[COSTO REAL UNITARIO],MATCH($A46,tblCostos[SKU],0))="","PENDIENTE",INDEX(tblCostos[COSTO REAL UNITARIO],MATCH($A46,tblCostos[SKU],0))),"PENDIENTE")) | R46: =IF($A46="","",IFERROR(IF(INDEX(tblCostos[Costo variable de venta unitario],MATCH($A46,tblCostos[SKU],0))="","",INDEX(tblCostos[Costo variable de venta unitario],MATCH($A46,tblCostos[SKU],0))),"")) | S46: =IF($A46="","",IF(NOT(ISNUMBER($Q46)),"PENDIENTE",$Q46+IF(ISNUMBER($R46),$R46,0))) | T46: =IF($A46="","",IF(OR($K46="",NOT(ISNUMBER($K46)),NOT(ISNUMBER($Q46))),"PENDIENTE",$K46-$Q46)) | U46: =IF($A46="","",IF(OR(NOT(ISNUMBER($T46)),NOT(ISNUMBER($K46)),$K46<=0),"PENDIENTE",$T46/$K46)) | V46: =IF($A46="","",IF(OR(NOT(ISNUMBER($T46)),NOT(ISNUMBER($Q46)),$Q46<=0),"PENDIENTE",$T46/$Q46)) | W46: =IF($A46="","",IF(OR($K46="",NOT(ISNUMBER($K46)),NOT(ISNUMBER($S46))),"PENDIENTE",$K46-$S46)) | X46: =IF($A46="","",IFERROR(INDEX(tblInventario[Stock actual],MATCH($A46,tblInventario[SKU],0)),0)) | AA46: Activo | AB46: =IF($A46="","",IF(COUNTIF(tblCostos[SKU],$A46)=0,"SIN FILA EN COSTOS",IF(AND($K46="",NOT(ISNUMBER($Q46))),"FALTA PRECIO Y COSTO",IF($K46="","FALTA PRECIO",IF(NOT(ISNUMBER($Q46)),"FALTA COSTO",IF($T46<0,"MARGEN NEGATIVO",IF($T46=0,"PRECIO = COSTO","COMPLETO")))))))
L47: =IF($A47="","",IFERROR(IF(INDEX(tblCostos[Costo de compra unitario],MATCH($A47,tblCostos[SKU],0))="","PENDIENTE",INDEX(tblCostos[Costo de compra unitario],MATCH($A47,tblCostos[SKU],0))),"PENDIENTE")) | M47: =IF($A47="","",IFERROR(IF(INDEX(tblCostos[Transporte unitario],MATCH($A47,tblCostos[SKU],0))="","",INDEX(tblCostos[Transporte unitario],MATCH($A47,tblCostos[SKU],0))),"")) | N47: =IF($A47="","",IFERROR(IF(INDEX(tblCostos[Impuestos / aranceles unitarios],MATCH($A47,tblCostos[SKU],0))="","",INDEX(tblCostos[Impuestos / aranceles unitarios],MATCH($A47,tblCostos[SKU],0))),"")) | O47: =IF($A47="","",IFERROR(IF(INDEX(tblCostos[Empaque unitario],MATCH($A47,tblCostos[SKU],0))="","",INDEX(tblCostos[Empaque unitario],MATCH($A47,tblCostos[SKU],0))),"")) | P47: =IF($A47="","",IFERROR(IF(INDEX(tblCostos[Otros costos variables unitarios],MATCH($A47,tblCostos[SKU],0))="","",INDEX(tblCostos[Otros costos variables unitarios],MATCH($A47,tblCostos[SKU],0))),"")) | Q47: =IF($A47="","",IFERROR(IF(INDEX(tblCostos[COSTO REAL UNITARIO],MATCH($A47,tblCostos[SKU],0))="","PENDIENTE",INDEX(tblCostos[COSTO REAL UNITARIO],MATCH($A47,tblCostos[SKU],0))),"PENDIENTE")) | R47: =IF($A47="","",IFERROR(IF(INDEX(tblCostos[Costo variable de venta unitario],MATCH($A47,tblCostos[SKU],0))="","",INDEX(tblCostos[Costo variable de venta unitario],MATCH($A47,tblCostos[SKU],0))),"")) | S47: =IF($A47="","",IF(NOT(ISNUMBER($Q47)),"PENDIENTE",$Q47+IF(ISNUMBER($R47),$R47,0))) | T47: =IF($A47="","",IF(OR($K47="",NOT(ISNUMBER($K47)),NOT(ISNUMBER($Q47))),"PENDIENTE",$K47-$Q47)) | U47: =IF($A47="","",IF(OR(NOT(ISNUMBER($T47)),NOT(ISNUMBER($K47)),$K47<=0),"PENDIENTE",$T47/$K47)) | V47: =IF($A47="","",IF(OR(NOT(ISNUMBER($T47)),NOT(ISNUMBER($Q47)),$Q47<=0),"PENDIENTE",$T47/$Q47)) | W47: =IF($A47="","",IF(OR($K47="",NOT(ISNUMBER($K47)),NOT(ISNUMBER($S47))),"PENDIENTE",$K47-$S47)) | X47: =IF($A47="","",IFERROR(INDEX(tblInventario[Stock actual],MATCH($A47,tblInventario[SKU],0)),0)) | AB47: =IF($A47="","",IF(COUNTIF(tblCostos[SKU],$A47)=0,"SIN FILA EN COSTOS",IF(AND($K47="",NOT(ISNUMBER($Q47))),"FALTA PRECIO Y COSTO",IF($K47="","FALTA PRECIO",IF(NOT(ISNUMBER($Q47)),"FALTA COSTO",IF($T47<0,"MARGEN NEGATIVO",IF($T47=0,"PRECIO = COSTO","COMPLETO")))))))
L48: =IF($A48="","",IFERROR(IF(INDEX(tblCostos[Costo de compra unitario],MATCH($A48,tblCostos[SKU],0))="","PENDIENTE",INDEX(tblCostos[Costo de compra unitario],MATCH($A48,tblCostos[SKU],0))),"PENDIENTE")) | M48: =IF($A48="","",IFERROR(IF(INDEX(tblCostos[Transporte unitario],MATCH($A48,tblCostos[SKU],0))="","",INDEX(tblCostos[Transporte unitario],MATCH($A48,tblCostos[SKU],0))),"")) | N48: =IF($A48="","",IFERROR(IF(INDEX(tblCostos[Impuestos / aranceles unitarios],MATCH($A48,tblCostos[SKU],0))="","",INDEX(tblCostos[Impuestos / aranceles unitarios],MATCH($A48,tblCostos[SKU],0))),"")) | O48: =IF($A48="","",IFERROR(IF(INDEX(tblCostos[Empaque unitario],MATCH($A48,tblCostos[SKU],0))="","",INDEX(tblCostos[Empaque unitario],MATCH($A48,tblCostos[SKU],0))),"")) | P48: =IF($A48="","",IFERROR(IF(INDEX(tblCostos[Otros costos variables unitarios],MATCH($A48,tblCostos[SKU],0))="","",INDEX(tblCostos[Otros costos variables unitarios],MATCH($A48,tblCostos[SKU],0))),"")) | Q48: =IF($A48="","",IFERROR(IF(INDEX(tblCostos[COSTO REAL UNITARIO],MATCH($A48,tblCostos[SKU],0))="","PENDIENTE",INDEX(tblCostos[COSTO REAL UNITARIO],MATCH($A48,tblCostos[SKU],0))),"PENDIENTE")) | R48: =IF($A48="","",IFERROR(IF(INDEX(tblCostos[Costo variable de venta unitario],MATCH($A48,tblCostos[SKU],0))="","",INDEX(tblCostos[Costo variable de venta unitario],MATCH($A48,tblCostos[SKU],0))),"")) | S48: =IF($A48="","",IF(NOT(ISNUMBER($Q48)),"PENDIENTE",$Q48+IF(ISNUMBER($R48),$R48,0))) | T48: =IF($A48="","",IF(OR($K48="",NOT(ISNUMBER($K48)),NOT(ISNUMBER($Q48))),"PENDIENTE",$K48-$Q48)) | U48: =IF($A48="","",IF(OR(NOT(ISNUMBER($T48)),NOT(ISNUMBER($K48)),$K48<=0),"PENDIENTE",$T48/$K48)) | V48: =IF($A48="","",IF(OR(NOT(ISNUMBER($T48)),NOT(ISNUMBER($Q48)),$Q48<=0),"PENDIENTE",$T48/$Q48)) | W48: =IF($A48="","",IF(OR($K48="",NOT(ISNUMBER($K48)),NOT(ISNUMBER($S48))),"PENDIENTE",$K48-$S48)) | X48: =IF($A48="","",IFERROR(INDEX(tblInventario[Stock actual],MATCH($A48,tblInventario[SKU],0)),0)) | AB48: =IF($A48="","",IF(COUNTIF(tblCostos[SKU],$A48)=0,"SIN FILA EN COSTOS",IF(AND($K48="",NOT(ISNUMBER($Q48))),"FALTA PRECIO Y COSTO",IF($K48="","FALTA PRECIO",IF(NOT(ISNUMBER($Q48)),"FALTA COSTO",IF($T48<0,"MARGEN NEGATIVO",IF($T48=0,"PRECIO = COSTO","COMPLETO")))))))
L49: =IF($A49="","",IFERROR(IF(INDEX(tblCostos[Costo de compra unitario],MATCH($A49,tblCostos[SKU],0))="","PENDIENTE",INDEX(tblCostos[Costo de compra unitario],MATCH($A49,tblCostos[SKU],0))),"PENDIENTE")) | M49: =IF($A49="","",IFERROR(IF(INDEX(tblCostos[Transporte unitario],MATCH($A49,tblCostos[SKU],0))="","",INDEX(tblCostos[Transporte unitario],MATCH($A49,tblCostos[SKU],0))),"")) | N49: =IF($A49="","",IFERROR(IF(INDEX(tblCostos[Impuestos / aranceles unitarios],MATCH($A49,tblCostos[SKU],0))="","",INDEX(tblCostos[Impuestos / aranceles unitarios],MATCH($A49,tblCostos[SKU],0))),"")) | O49: =IF($A49="","",IFERROR(IF(INDEX(tblCostos[Empaque unitario],MATCH($A49,tblCostos[SKU],0))="","",INDEX(tblCostos[Empaque unitario],MATCH($A49,tblCostos[SKU],0))),"")) | P49: =IF($A49="","",IFERROR(IF(INDEX(tblCostos[Otros costos variables unitarios],MATCH($A49,tblCostos[SKU],0))="","",INDEX(tblCostos[Otros costos variables unitarios],MATCH($A49,tblCostos[SKU],0))),"")) | Q49: =IF($A49="","",IFERROR(IF(INDEX(tblCostos[COSTO REAL UNITARIO],MATCH($A49,tblCostos[SKU],0))="","PENDIENTE",INDEX(tblCostos[COSTO REAL UNITARIO],MATCH($A49,tblCostos[SKU],0))),"PENDIENTE")) | R49: =IF($A49="","",IFERROR(IF(INDEX(tblCostos[Costo variable de venta unitario],MATCH($A49,tblCostos[SKU],0))="","",INDEX(tblCostos[Costo variable de venta unitario],MATCH($A49,tblCostos[SKU],0))),"")) | S49: =IF($A49="","",IF(NOT(ISNUMBER($Q49)),"PENDIENTE",$Q49+IF(ISNUMBER($R49),$R49,0))) | T49: =IF($A49="","",IF(OR($K49="",NOT(ISNUMBER($K49)),NOT(ISNUMBER($Q49))),"PENDIENTE",$K49-$Q49)) | U49: =IF($A49="","",IF(OR(NOT(ISNUMBER($T49)),NOT(ISNUMBER($K49)),$K49<=0),"PENDIENTE",$T49/$K49)) | V49: =IF($A49="","",IF(OR(NOT(ISNUMBER($T49)),NOT(ISNUMBER($Q49)),$Q49<=0),"PENDIENTE",$T49/$Q49)) | W49: =IF($A49="","",IF(OR($K49="",NOT(ISNUMBER($K49)),NOT(ISNUMBER($S49))),"PENDIENTE",$K49-$S49)) | X49: =IF($A49="","",IFERROR(INDEX(tblInventario[Stock actual],MATCH($A49,tblInventario[SKU],0)),0)) | AB49: =IF($A49="","",IF(COUNTIF(tblCostos[SKU],$A49)=0,"SIN FILA EN COSTOS",IF(AND($K49="",NOT(ISNUMBER($Q49))),"FALTA PRECIO Y COSTO",IF($K49="","FALTA PRECIO",IF(NOT(ISNUMBER($Q49)),"FALTA COSTO",IF($T49<0,"MARGEN NEGATIVO",IF($T49=0,"PRECIO = COSTO","COMPLETO")))))))
L50: =IF($A50="","",IFERROR(IF(INDEX(tblCostos[Costo de compra unitario],MATCH($A50,tblCostos[SKU],0))="","PENDIENTE",INDEX(tblCostos[Costo de compra unitario],MATCH($A50,tblCostos[SKU],0))),"PENDIENTE")) | M50: =IF($A50="","",IFERROR(IF(INDEX(tblCostos[Transporte unitario],MATCH($A50,tblCostos[SKU],0))="","",INDEX(tblCostos[Transporte unitario],MATCH($A50,tblCostos[SKU],0))),"")) | N50: =IF($A50="","",IFERROR(IF(INDEX(tblCostos[Impuestos / aranceles unitarios],MATCH($A50,tblCostos[SKU],0))="","",INDEX(tblCostos[Impuestos / aranceles unitarios],MATCH($A50,tblCostos[SKU],0))),"")) | O50: =IF($A50="","",IFERROR(IF(INDEX(tblCostos[Empaque unitario],MATCH($A50,tblCostos[SKU],0))="","",INDEX(tblCostos[Empaque unitario],MATCH($A50,tblCostos[SKU],0))),"")) | P50: =IF($A50="","",IFERROR(IF(INDEX(tblCostos[Otros costos variables unitarios],MATCH($A50,tblCostos[SKU],0))="","",INDEX(tblCostos[Otros costos variables unitarios],MATCH($A50,tblCostos[SKU],0))),"")) | Q50: =IF($A50="","",IFERROR(IF(INDEX(tblCostos[COSTO REAL UNITARIO],MATCH($A50,tblCostos[SKU],0))="","PENDIENTE",INDEX(tblCostos[COSTO REAL UNITARIO],MATCH($A50,tblCostos[SKU],0))),"PENDIENTE")) | R50: =IF($A50="","",IFERROR(IF(INDEX(tblCostos[Costo variable de venta unitario],MATCH($A50,tblCostos[SKU],0))="","",INDEX(tblCostos[Costo variable de venta unitario],MATCH($A50,tblCostos[SKU],0))),"")) | S50: =IF($A50="","",IF(NOT(ISNUMBER($Q50)),"PENDIENTE",$Q50+IF(ISNUMBER($R50),$R50,0))) | T50: =IF($A50="","",IF(OR($K50="",NOT(ISNUMBER($K50)),NOT(ISNUMBER($Q50))),"PENDIENTE",$K50-$Q50)) | U50: =IF($A50="","",IF(OR(NOT(ISNUMBER($T50)),NOT(ISNUMBER($K50)),$K50<=0),"PENDIENTE",$T50/$K50)) | V50: =IF($A50="","",IF(OR(NOT(ISNUMBER($T50)),NOT(ISNUMBER($Q50)),$Q50<=0),"PENDIENTE",$T50/$Q50)) | W50: =IF($A50="","",IF(OR($K50="",NOT(ISNUMBER($K50)),NOT(ISNUMBER($S50))),"PENDIENTE",$K50-$S50)) | X50: =IF($A50="","",IFERROR(INDEX(tblInventario[Stock actual],MATCH($A50,tblInventario[SKU],0)),0)) | AB50: =IF($A50="","",IF(COUNTIF(tblCostos[SKU],$A50)=0,"SIN FILA EN COSTOS",IF(AND($K50="",NOT(ISNUMBER($Q50))),"FALTA PRECIO Y COSTO",IF($K50="","FALTA PRECIO",IF(NOT(ISNUMBER($Q50)),"FALTA COSTO",IF($T50<0,"MARGEN NEGATIVO",IF($T50=0,"PRECIO = COSTO","COMPLETO")))))))
L51: =IF($A51="","",IFERROR(IF(INDEX(tblCostos[Costo de compra unitario],MATCH($A51,tblCostos[SKU],0))="","PENDIENTE",INDEX(tblCostos[Costo de compra unitario],MATCH($A51,tblCostos[SKU],0))),"PENDIENTE")) | M51: =IF($A51="","",IFERROR(IF(INDEX(tblCostos[Transporte unitario],MATCH($A51,tblCostos[SKU],0))="","",INDEX(tblCostos[Transporte unitario],MATCH($A51,tblCostos[SKU],0))),"")) | N51: =IF($A51="","",IFERROR(IF(INDEX(tblCostos[Impuestos / aranceles unitarios],MATCH($A51,tblCostos[SKU],0))="","",INDEX(tblCostos[Impuestos / aranceles unitarios],MATCH($A51,tblCostos[SKU],0))),"")) | O51: =IF($A51="","",IFERROR(IF(INDEX(tblCostos[Empaque unitario],MATCH($A51,tblCostos[SKU],0))="","",INDEX(tblCostos[Empaque unitario],MATCH($A51,tblCostos[SKU],0))),"")) | P51: =IF($A51="","",IFERROR(IF(INDEX(tblCostos[Otros costos variables unitarios],MATCH($A51,tblCostos[SKU],0))="","",INDEX(tblCostos[Otros costos variables unitarios],MATCH($A51,tblCostos[SKU],0))),"")) | Q51: =IF($A51="","",IFERROR(IF(INDEX(tblCostos[COSTO REAL UNITARIO],MATCH($A51,tblCostos[SKU],0))="","PENDIENTE",INDEX(tblCostos[COSTO REAL UNITARIO],MATCH($A51,tblCostos[SKU],0))),"PENDIENTE")) | R51: =IF($A51="","",IFERROR(IF(INDEX(tblCostos[Costo variable de venta unitario],MATCH($A51,tblCostos[SKU],0))="","",INDEX(tblCostos[Costo variable de venta unitario],MATCH($A51,tblCostos[SKU],0))),"")) | S51: =IF($A51="","",IF(NOT(ISNUMBER($Q51)),"PENDIENTE",$Q51+IF(ISNUMBER($R51),$R51,0))) | T51: =IF($A51="","",IF(OR($K51="",NOT(ISNUMBER($K51)),NOT(ISNUMBER($Q51))),"PENDIENTE",$K51-$Q51)) | U51: =IF($A51="","",IF(OR(NOT(ISNUMBER($T51)),NOT(ISNUMBER($K51)),$K51<=0),"PENDIENTE",$T51/$K51)) | V51: =IF($A51="","",IF(OR(NOT(ISNUMBER($T51)),NOT(ISNUMBER($Q51)),$Q51<=0),"PENDIENTE",$T51/$Q51)) | W51: =IF($A51="","",IF(OR($K51="",NOT(ISNUMBER($K51)),NOT(ISNUMBER($S51))),"PENDIENTE",$K51-$S51)) | X51: =IF($A51="","",IFERROR(INDEX(tblInventario[Stock actual],MATCH($A51,tblInventario[SKU],0)),0)) | AB51: =IF($A51="","",IF(COUNTIF(tblCostos[SKU],$A51)=0,"SIN FILA EN COSTOS",IF(AND($K51="",NOT(ISNUMBER($Q51))),"FALTA PRECIO Y COSTO",IF($K51="","FALTA PRECIO",IF(NOT(ISNUMBER($Q51)),"FALTA COSTO",IF($T51<0,"MARGEN NEGATIVO",IF($T51=0,"PRECIO = COSTO","COMPLETO")))))))
L52: =IF($A52="","",IFERROR(IF(INDEX(tblCostos[Costo de compra unitario],MATCH($A52,tblCostos[SKU],0))="","PENDIENTE",INDEX(tblCostos[Costo de compra unitario],MATCH($A52,tblCostos[SKU],0))),"PENDIENTE")) | M52: =IF($A52="","",IFERROR(IF(INDEX(tblCostos[Transporte unitario],MATCH($A52,tblCostos[SKU],0))="","",INDEX(tblCostos[Transporte unitario],MATCH($A52,tblCostos[SKU],0))),"")) | N52: =IF($A52="","",IFERROR(IF(INDEX(tblCostos[Impuestos / aranceles unitarios],MATCH($A52,tblCostos[SKU],0))="","",INDEX(tblCostos[Impuestos / aranceles unitarios],MATCH($A52,tblCostos[SKU],0))),"")) | O52: =IF($A52="","",IFERROR(IF(INDEX(tblCostos[Empaque unitario],MATCH($A52,tblCostos[SKU],0))="","",INDEX(tblCostos[Empaque unitario],MATCH($A52,tblCostos[SKU],0))),"")) | P52: =IF($A52="","",IFERROR(IF(INDEX(tblCostos[Otros costos variables unitarios],MATCH($A52,tblCostos[SKU],0))="","",INDEX(tblCostos[Otros costos variables unitarios],MATCH($A52,tblCostos[SKU],0))),"")) | Q52: =IF($A52="","",IFERROR(IF(INDEX(tblCostos[COSTO REAL UNITARIO],MATCH($A52,tblCostos[SKU],0))="","PENDIENTE",INDEX(tblCostos[COSTO REAL UNITARIO],MATCH($A52,tblCostos[SKU],0))),"PENDIENTE")) | R52: =IF($A52="","",IFERROR(IF(INDEX(tblCostos[Costo variable de venta unitario],MATCH($A52,tblCostos[SKU],0))="","",INDEX(tblCostos[Costo variable de venta unitario],MATCH($A52,tblCostos[SKU],0))),"")) | S52: =IF($A52="","",IF(NOT(ISNUMBER($Q52)),"PENDIENTE",$Q52+IF(ISNUMBER($R52),$R52,0))) | T52: =IF($A52="","",IF(OR($K52="",NOT(ISNUMBER($K52)),NOT(ISNUMBER($Q52))),"PENDIENTE",$K52-$Q52)) | U52: =IF($A52="","",IF(OR(NOT(ISNUMBER($T52)),NOT(ISNUMBER($K52)),$K52<=0),"PENDIENTE",$T52/$K52)) | V52: =IF($A52="","",IF(OR(NOT(ISNUMBER($T52)),NOT(ISNUMBER($Q52)),$Q52<=0),"PENDIENTE",$T52/$Q52)) | W52: =IF($A52="","",IF(OR($K52="",NOT(ISNUMBER($K52)),NOT(ISNUMBER($S52))),"PENDIENTE",$K52-$S52)) | X52: =IF($A52="","",IFERROR(INDEX(tblInventario[Stock actual],MATCH($A52,tblInventario[SKU],0)),0)) | AB52: =IF($A52="","",IF(COUNTIF(tblCostos[SKU],$A52)=0,"SIN FILA EN COSTOS",IF(AND($K52="",NOT(ISNUMBER($Q52))),"FALTA PRECIO Y COSTO",IF($K52="","FALTA PRECIO",IF(NOT(ISNUMBER($Q52)),"FALTA COSTO",IF($T52<0,"MARGEN NEGATIVO",IF($T52=0,"PRECIO = COSTO","COMPLETO")))))))
L53: =IF($A53="","",IFERROR(IF(INDEX(tblCostos[Costo de compra unitario],MATCH($A53,tblCostos[SKU],0))="","PENDIENTE",INDEX(tblCostos[Costo de compra unitario],MATCH($A53,tblCostos[SKU],0))),"PENDIENTE")) | M53: =IF($A53="","",IFERROR(IF(INDEX(tblCostos[Transporte unitario],MATCH($A53,tblCostos[SKU],0))="","",INDEX(tblCostos[Transporte unitario],MATCH($A53,tblCostos[SKU],0))),"")) | N53: =IF($A53="","",IFERROR(IF(INDEX(tblCostos[Impuestos / aranceles unitarios],MATCH($A53,tblCostos[SKU],0))="","",INDEX(tblCostos[Impuestos / aranceles unitarios],MATCH($A53,tblCostos[SKU],0))),"")) | O53: =IF($A53="","",IFERROR(IF(INDEX(tblCostos[Empaque unitario],MATCH($A53,tblCostos[SKU],0))="","",INDEX(tblCostos[Empaque unitario],MATCH($A53,tblCostos[SKU],0))),"")) | P53: =IF($A53="","",IFERROR(IF(INDEX(tblCostos[Otros costos variables unitarios],MATCH($A53,tblCostos[SKU],0))="","",INDEX(tblCostos[Otros costos variables unitarios],MATCH($A53,tblCostos[SKU],0))),"")) | Q53: =IF($A53="","",IFERROR(IF(INDEX(tblCostos[COSTO REAL UNITARIO],MATCH($A53,tblCostos[SKU],0))="","PENDIENTE",INDEX(tblCostos[COSTO REAL UNITARIO],MATCH($A53,tblCostos[SKU],0))),"PENDIENTE")) | R53: =IF($A53="","",IFERROR(IF(INDEX(tblCostos[Costo variable de venta unitario],MATCH($A53,tblCostos[SKU],0))="","",INDEX(tblCostos[Costo variable de venta unitario],MATCH($A53,tblCostos[SKU],0))),"")) | S53: =IF($A53="","",IF(NOT(ISNUMBER($Q53)),"PENDIENTE",$Q53+IF(ISNUMBER($R53),$R53,0))) | T53: =IF($A53="","",IF(OR($K53="",NOT(ISNUMBER($K53)),NOT(ISNUMBER($Q53))),"PENDIENTE",$K53-$Q53)) | U53: =IF($A53="","",IF(OR(NOT(ISNUMBER($T53)),NOT(ISNUMBER($K53)),$K53<=0),"PENDIENTE",$T53/$K53)) | V53: =IF($A53="","",IF(OR(NOT(ISNUMBER($T53)),NOT(ISNUMBER($Q53)),$Q53<=0),"PENDIENTE",$T53/$Q53)) | W53: =IF($A53="","",IF(OR($K53="",NOT(ISNUMBER($K53)),NOT(ISNUMBER($S53))),"PENDIENTE",$K53-$S53)) | X53: =IF($A53="","",IFERROR(INDEX(tblInventario[Stock actual],MATCH($A53,tblInventario[SKU],0)),0)) | AB53: =IF($A53="","",IF(COUNTIF(tblCostos[SKU],$A53)=0,"SIN FILA EN COSTOS",IF(AND($K53="",NOT(ISNUMBER($Q53))),"FALTA PRECIO Y COSTO",IF($K53="","FALTA PRECIO",IF(NOT(ISNUMBER($Q53)),"FALTA COSTO",IF($T53<0,"MARGEN NEGATIVO",IF($T53=0,"PRECIO = COSTO","COMPLETO")))))))
L54: =IF($A54="","",IFERROR(IF(INDEX(tblCostos[Costo de compra unitario],MATCH($A54,tblCostos[SKU],0))="","PENDIENTE",INDEX(tblCostos[Costo de compra unitario],MATCH($A54,tblCostos[SKU],0))),"PENDIENTE")) | M54: =IF($A54="","",IFERROR(IF(INDEX(tblCostos[Transporte unitario],MATCH($A54,tblCostos[SKU],0))="","",INDEX(tblCostos[Transporte unitario],MATCH($A54,tblCostos[SKU],0))),"")) | N54: =IF($A54="","",IFERROR(IF(INDEX(tblCostos[Impuestos / aranceles unitarios],MATCH($A54,tblCostos[SKU],0))="","",INDEX(tblCostos[Impuestos / aranceles unitarios],MATCH($A54,tblCostos[SKU],0))),"")) | O54: =IF($A54="","",IFERROR(IF(INDEX(tblCostos[Empaque unitario],MATCH($A54,tblCostos[SKU],0))="","",INDEX(tblCostos[Empaque unitario],MATCH($A54,tblCostos[SKU],0))),"")) | P54: =IF($A54="","",IFERROR(IF(INDEX(tblCostos[Otros costos variables unitarios],MATCH($A54,tblCostos[SKU],0))="","",INDEX(tblCostos[Otros costos variables unitarios],MATCH($A54,tblCostos[SKU],0))),"")) | Q54: =IF($A54="","",IFERROR(IF(INDEX(tblCostos[COSTO REAL UNITARIO],MATCH($A54,tblCostos[SKU],0))="","PENDIENTE",INDEX(tblCostos[COSTO REAL UNITARIO],MATCH($A54,tblCostos[SKU],0))),"PENDIENTE")) | R54: =IF($A54="","",IFERROR(IF(INDEX(tblCostos[Costo variable de venta unitario],MATCH($A54,tblCostos[SKU],0))="","",INDEX(tblCostos[Costo variable de venta unitario],MATCH($A54,tblCostos[SKU],0))),"")) | S54: =IF($A54="","",IF(NOT(ISNUMBER($Q54)),"PENDIENTE",$Q54+IF(ISNUMBER($R54),$R54,0))) | T54: =IF($A54="","",IF(OR($K54="",NOT(ISNUMBER($K54)),NOT(ISNUMBER($Q54))),"PENDIENTE",$K54-$Q54)) | U54: =IF($A54="","",IF(OR(NOT(ISNUMBER($T54)),NOT(ISNUMBER($K54)),$K54<=0),"PENDIENTE",$T54/$K54)) | V54: =IF($A54="","",IF(OR(NOT(ISNUMBER($T54)),NOT(ISNUMBER($Q54)),$Q54<=0),"PENDIENTE",$T54/$Q54)) | W54: =IF($A54="","",IF(OR($K54="",NOT(ISNUMBER($K54)),NOT(ISNUMBER($S54))),"PENDIENTE",$K54-$S54)) | X54: =IF($A54="","",IFERROR(INDEX(tblInventario[Stock actual],MATCH($A54,tblInventario[SKU],0)),0)) | AB54: =IF($A54="","",IF(COUNTIF(tblCostos[SKU],$A54)=0,"SIN FILA EN COSTOS",IF(AND($K54="",NOT(ISNUMBER($Q54))),"FALTA PRECIO Y COSTO",IF($K54="","FALTA PRECIO",IF(NOT(ISNUMBER($Q54)),"FALTA COSTO",IF($T54<0,"MARGEN NEGATIVO",IF($T54=0,"PRECIO = COSTO","COMPLETO")))))))
L55: =IF($A55="","",IFERROR(IF(INDEX(tblCostos[Costo de compra unitario],MATCH($A55,tblCostos[SKU],0))="","PENDIENTE",INDEX(tblCostos[Costo de compra unitario],MATCH($A55,tblCostos[SKU],0))),"PENDIENTE")) | M55: =IF($A55="","",IFERROR(IF(INDEX(tblCostos[Transporte unitario],MATCH($A55,tblCostos[SKU],0))="","",INDEX(tblCostos[Transporte unitario],MATCH($A55,tblCostos[SKU],0))),"")) | N55: =IF($A55="","",IFERROR(IF(INDEX(tblCostos[Impuestos / aranceles unitarios],MATCH($A55,tblCostos[SKU],0))="","",INDEX(tblCostos[Impuestos / aranceles unitarios],MATCH($A55,tblCostos[SKU],0))),"")) | O55: =IF($A55="","",IFERROR(IF(INDEX(tblCostos[Empaque unitario],MATCH($A55,tblCostos[SKU],0))="","",INDEX(tblCostos[Empaque unitario],MATCH($A55,tblCostos[SKU],0))),"")) | P55: =IF($A55="","",IFERROR(IF(INDEX(tblCostos[Otros costos variables unitarios],MATCH($A55,tblCostos[SKU],0))="","",INDEX(tblCostos[Otros costos variables unitarios],MATCH($A55,tblCostos[SKU],0))),"")) | Q55: =IF($A55="","",IFERROR(IF(INDEX(tblCostos[COSTO REAL UNITARIO],MATCH($A55,tblCostos[SKU],0))="","PENDIENTE",INDEX(tblCostos[COSTO REAL UNITARIO],MATCH($A55,tblCostos[SKU],0))),"PENDIENTE")) | R55: =IF($A55="","",IFERROR(IF(INDEX(tblCostos[Costo variable de venta unitario],MATCH($A55,tblCostos[SKU],0))="","",INDEX(tblCostos[Costo variable de venta unitario],MATCH($A55,tblCostos[SKU],0))),"")) | S55: =IF($A55="","",IF(NOT(ISNUMBER($Q55)),"PENDIENTE",$Q55+IF(ISNUMBER($R55),$R55,0))) | T55: =IF($A55="","",IF(OR($K55="",NOT(ISNUMBER($K55)),NOT(ISNUMBER($Q55))),"PENDIENTE",$K55-$Q55)) | U55: =IF($A55="","",IF(OR(NOT(ISNUMBER($T55)),NOT(ISNUMBER($K55)),$K55<=0),"PENDIENTE",$T55/$K55)) | V55: =IF($A55="","",IF(OR(NOT(ISNUMBER($T55)),NOT(ISNUMBER($Q55)),$Q55<=0),"PENDIENTE",$T55/$Q55)) | W55: =IF($A55="","",IF(OR($K55="",NOT(ISNUMBER($K55)),NOT(ISNUMBER($S55))),"PENDIENTE",$K55-$S55)) | X55: =IF($A55="","",IFERROR(INDEX(tblInventario[Stock actual],MATCH($A55,tblInventario[SKU],0)),0)) | AB55: =IF($A55="","",IF(COUNTIF(tblCostos[SKU],$A55)=0,"SIN FILA EN COSTOS",IF(AND($K55="",NOT(ISNUMBER($Q55))),"FALTA PRECIO Y COSTO",IF($K55="","FALTA PRECIO",IF(NOT(ISNUMBER($Q55)),"FALTA COSTO",IF($T55<0,"MARGEN NEGATIVO",IF($T55=0,"PRECIO = COSTO","COMPLETO")))))))
L56: =IF($A56="","",IFERROR(IF(INDEX(tblCostos[Costo de compra unitario],MATCH($A56,tblCostos[SKU],0))="","PENDIENTE",INDEX(tblCostos[Costo de compra unitario],MATCH($A56,tblCostos[SKU],0))),"PENDIENTE")) | M56: =IF($A56="","",IFERROR(IF(INDEX(tblCostos[Transporte unitario],MATCH($A56,tblCostos[SKU],0))="","",INDEX(tblCostos[Transporte unitario],MATCH($A56,tblCostos[SKU],0))),"")) | N56: =IF($A56="","",IFERROR(IF(INDEX(tblCostos[Impuestos / aranceles unitarios],MATCH($A56,tblCostos[SKU],0))="","",INDEX(tblCostos[Impuestos / aranceles unitarios],MATCH($A56,tblCostos[SKU],0))),"")) | O56: =IF($A56="","",IFERROR(IF(INDEX(tblCostos[Empaque unitario],MATCH($A56,tblCostos[SKU],0))="","",INDEX(tblCostos[Empaque unitario],MATCH($A56,tblCostos[SKU],0))),"")) | P56: =IF($A56="","",IFERROR(IF(INDEX(tblCostos[Otros costos variables unitarios],MATCH($A56,tblCostos[SKU],0))="","",INDEX(tblCostos[Otros costos variables unitarios],MATCH($A56,tblCostos[SKU],0))),"")) | Q56: =IF($A56="","",IFERROR(IF(INDEX(tblCostos[COSTO REAL UNITARIO],MATCH($A56,tblCostos[SKU],0))="","PENDIENTE",INDEX(tblCostos[COSTO REAL UNITARIO],MATCH($A56,tblCostos[SKU],0))),"PENDIENTE")) | R56: =IF($A56="","",IFERROR(IF(INDEX(tblCostos[Costo variable de venta unitario],MATCH($A56,tblCostos[SKU],0))="","",INDEX(tblCostos[Costo variable de venta unitario],MATCH($A56,tblCostos[SKU],0))),"")) | S56: =IF($A56="","",IF(NOT(ISNUMBER($Q56)),"PENDIENTE",$Q56+IF(ISNUMBER($R56),$R56,0))) | T56: =IF($A56="","",IF(OR($K56="",NOT(ISNUMBER($K56)),NOT(ISNUMBER($Q56))),"PENDIENTE",$K56-$Q56)) | U56: =IF($A56="","",IF(OR(NOT(ISNUMBER($T56)),NOT(ISNUMBER($K56)),$K56<=0),"PENDIENTE",$T56/$K56)) | V56: =IF($A56="","",IF(OR(NOT(ISNUMBER($T56)),NOT(ISNUMBER($Q56)),$Q56<=0),"PENDIENTE",$T56/$Q56)) | W56: =IF($A56="","",IF(OR($K56="",NOT(ISNUMBER($K56)),NOT(ISNUMBER($S56))),"PENDIENTE",$K56-$S56)) | X56: =IF($A56="","",IFERROR(INDEX(tblInventario[Stock actual],MATCH($A56,tblInventario[SKU],0)),0)) | AB56: =IF($A56="","",IF(COUNTIF(tblCostos[SKU],$A56)=0,"SIN FILA EN COSTOS",IF(AND($K56="",NOT(ISNUMBER($Q56))),"FALTA PRECIO Y COSTO",IF($K56="","FALTA PRECIO",IF(NOT(ISNUMBER($Q56)),"FALTA COSTO",IF($T56<0,"MARGEN NEGATIVO",IF($T56=0,"PRECIO = COSTO","COMPLETO")))))))
L57: =IF($A57="","",IFERROR(IF(INDEX(tblCostos[Costo de compra unitario],MATCH($A57,tblCostos[SKU],0))="","PENDIENTE",INDEX(tblCostos[Costo de compra unitario],MATCH($A57,tblCostos[SKU],0))),"PENDIENTE")) | M57: =IF($A57="","",IFERROR(IF(INDEX(tblCostos[Transporte unitario],MATCH($A57,tblCostos[SKU],0))="","",INDEX(tblCostos[Transporte unitario],MATCH($A57,tblCostos[SKU],0))),"")) | N57: =IF($A57="","",IFERROR(IF(INDEX(tblCostos[Impuestos / aranceles unitarios],MATCH($A57,tblCostos[SKU],0))="","",INDEX(tblCostos[Impuestos / aranceles unitarios],MATCH($A57,tblCostos[SKU],0))),"")) | O57: =IF($A57="","",IFERROR(IF(INDEX(tblCostos[Empaque unitario],MATCH($A57,tblCostos[SKU],0))="","",INDEX(tblCostos[Empaque unitario],MATCH($A57,tblCostos[SKU],0))),"")) | P57: =IF($A57="","",IFERROR(IF(INDEX(tblCostos[Otros costos variables unitarios],MATCH($A57,tblCostos[SKU],0))="","",INDEX(tblCostos[Otros costos variables unitarios],MATCH($A57,tblCostos[SKU],0))),"")) | Q57: =IF($A57="","",IFERROR(IF(INDEX(tblCostos[COSTO REAL UNITARIO],MATCH($A57,tblCostos[SKU],0))="","PENDIENTE",INDEX(tblCostos[COSTO REAL UNITARIO],MATCH($A57,tblCostos[SKU],0))),"PENDIENTE")) | R57: =IF($A57="","",IFERROR(IF(INDEX(tblCostos[Costo variable de venta unitario],MATCH($A57,tblCostos[SKU],0))="","",INDEX(tblCostos[Costo variable de venta unitario],MATCH($A57,tblCostos[SKU],0))),"")) | S57: =IF($A57="","",IF(NOT(ISNUMBER($Q57)),"PENDIENTE",$Q57+IF(ISNUMBER($R57),$R57,0))) | T57: =IF($A57="","",IF(OR($K57="",NOT(ISNUMBER($K57)),NOT(ISNUMBER($Q57))),"PENDIENTE",$K57-$Q57)) | U57: =IF($A57="","",IF(OR(NOT(ISNUMBER($T57)),NOT(ISNUMBER($K57)),$K57<=0),"PENDIENTE",$T57/$K57)) | V57: =IF($A57="","",IF(OR(NOT(ISNUMBER($T57)),NOT(ISNUMBER($Q57)),$Q57<=0),"PENDIENTE",$T57/$Q57)) | W57: =IF($A57="","",IF(OR($K57="",NOT(ISNUMBER($K57)),NOT(ISNUMBER($S57))),"PENDIENTE",$K57-$S57)) | X57: =IF($A57="","",IFERROR(INDEX(tblInventario[Stock actual],MATCH($A57,tblInventario[SKU],0)),0)) | AB57: =IF($A57="","",IF(COUNTIF(tblCostos[SKU],$A57)=0,"SIN FILA EN COSTOS",IF(AND($K57="",NOT(ISNUMBER($Q57))),"FALTA PRECIO Y COSTO",IF($K57="","FALTA PRECIO",IF(NOT(ISNUMBER($Q57)),"FALTA COSTO",IF($T57<0,"MARGEN NEGATIVO",IF($T57=0,"PRECIO = COSTO","COMPLETO")))))))
L58: =IF($A58="","",IFERROR(IF(INDEX(tblCostos[Costo de compra unitario],MATCH($A58,tblCostos[SKU],0))="","PENDIENTE",INDEX(tblCostos[Costo de compra unitario],MATCH($A58,tblCostos[SKU],0))),"PENDIENTE")) | M58: =IF($A58="","",IFERROR(IF(INDEX(tblCostos[Transporte unitario],MATCH($A58,tblCostos[SKU],0))="","",INDEX(tblCostos[Transporte unitario],MATCH($A58,tblCostos[SKU],0))),"")) | N58: =IF($A58="","",IFERROR(IF(INDEX(tblCostos[Impuestos / aranceles unitarios],MATCH($A58,tblCostos[SKU],0))="","",INDEX(tblCostos[Impuestos / aranceles unitarios],MATCH($A58,tblCostos[SKU],0))),"")) | O58: =IF($A58="","",IFERROR(IF(INDEX(tblCostos[Empaque unitario],MATCH($A58,tblCostos[SKU],0))="","",INDEX(tblCostos[Empaque unitario],MATCH($A58,tblCostos[SKU],0))),"")) | P58: =IF($A58="","",IFERROR(IF(INDEX(tblCostos[Otros costos variables unitarios],MATCH($A58,tblCostos[SKU],0))="","",INDEX(tblCostos[Otros costos variables unitarios],MATCH($A58,tblCostos[SKU],0))),"")) | Q58: =IF($A58="","",IFERROR(IF(INDEX(tblCostos[COSTO REAL UNITARIO],MATCH($A58,tblCostos[SKU],0))="","PENDIENTE",INDEX(tblCostos[COSTO REAL UNITARIO],MATCH($A58,tblCostos[SKU],0))),"PENDIENTE")) | R58: =IF($A58="","",IFERROR(IF(INDEX(tblCostos[Costo variable de venta unitario],MATCH($A58,tblCostos[SKU],0))="","",INDEX(tblCostos[Costo variable de venta unitario],MATCH($A58,tblCostos[SKU],0))),"")) | S58: =IF($A58="","",IF(NOT(ISNUMBER($Q58)),"PENDIENTE",$Q58+IF(ISNUMBER($R58),$R58,0))) | T58: =IF($A58="","",IF(OR($K58="",NOT(ISNUMBER($K58)),NOT(ISNUMBER($Q58))),"PENDIENTE",$K58-$Q58)) | U58: =IF($A58="","",IF(OR(NOT(ISNUMBER($T58)),NOT(ISNUMBER($K58)),$K58<=0),"PENDIENTE",$T58/$K58)) | V58: =IF($A58="","",IF(OR(NOT(ISNUMBER($T58)),NOT(ISNUMBER($Q58)),$Q58<=0),"PENDIENTE",$T58/$Q58)) | W58: =IF($A58="","",IF(OR($K58="",NOT(ISNUMBER($K58)),NOT(ISNUMBER($S58))),"PENDIENTE",$K58-$S58)) | X58: =IF($A58="","",IFERROR(INDEX(tblInventario[Stock actual],MATCH($A58,tblInventario[SKU],0)),0)) | AB58: =IF($A58="","",IF(COUNTIF(tblCostos[SKU],$A58)=0,"SIN FILA EN COSTOS",IF(AND($K58="",NOT(ISNUMBER($Q58))),"FALTA PRECIO Y COSTO",IF($K58="","FALTA PRECIO",IF(NOT(ISNUMBER($Q58)),"FALTA COSTO",IF($T58<0,"MARGEN NEGATIVO",IF($T58=0,"PRECIO = COSTO","COMPLETO")))))))
... L66: =IF($A66="","",IFERROR(IF(INDEX(tblCostos[Costo de compra unitario],MATCH($A66,tblCostos[SKU],0))="","PENDIENTE",INDEX(tblCostos[Costo de compra unitario],MATCH($A66,tblCostos[SKU],0))),"PENDIENTE")) | M66: =IF($A66="","",IFERROR(IF(INDEX(tblCostos[Transporte unitario],MATCH($A66,tblCostos[SKU],0))="","",INDEX(tblCostos[Transporte unitario],MATCH($A66,tblCostos[SKU],0))),"")) | N66: =IF($A66="","",IFERROR(IF(INDEX(tblCostos[Impuestos / aranceles unitarios],MATCH($A66,tblCostos[SKU],0))="","",INDEX(tblCostos[Impuestos / aranceles unitarios],MATCH($A66,tblCostos[SKU],0))),"")) | O66: =IF($A66="","",IFERROR(IF(INDEX(tblCostos[Empaque unitario],MATCH($A66,tblCostos[SKU],0))="","",INDEX(tblCostos[Empaque unitario],MATCH($A66,tblCostos[SKU],0))),"")) | P66: =IF($A66="","",IFERROR(IF(INDEX(tblCostos[Otros costos variables unitarios],MATCH($A66,tblCostos[SKU],0))="","",INDEX(tblCostos[Otros costos variables unitarios],MATCH($A66,tblCostos[SKU],0))),"")) | Q66: =IF($A66="","",IFERROR(IF(INDEX(tblCostos[COSTO REAL UNITARIO],MATCH($A66,tblCostos[SKU],0))="","PENDIENTE",INDEX(tblCostos[COSTO REAL UNITARIO],MATCH($A66,tblCostos[SKU],0))),"PENDIENTE")) | R66: =IF($A66="","",IFERROR(IF(INDEX(tblCostos[Costo variable de venta unitario],MATCH($A66,tblCostos[SKU],0))="","",INDEX(tblCostos[Costo variable de venta unitario],MATCH($A66,tblCostos[SKU],0))),"")) | S66: =IF($A66="","",IF(NOT(ISNUMBER($Q66)),"PENDIENTE",$Q66+IF(ISNUMBER($R66),$R66,0))) | T66: =IF($A66="","",IF(OR($K66="",NOT(ISNUMBER($K66)),NOT(ISNUMBER($Q66))),"PENDIENTE",$K66-$Q66)) | U66: =IF($A66="","",IF(OR(NOT(ISNUMBER($T66)),NOT(ISNUMBER($K66)),$K66<=0),"PENDIENTE",$T66/$K66)) | V66: =IF($A66="","",IF(OR(NOT(ISNUMBER($T66)),NOT(ISNUMBER($Q66)),$Q66<=0),"PENDIENTE",$T66/$Q66)) | W66: =IF($A66="","",IF(OR($K66="",NOT(ISNUMBER($K66)),NOT(ISNUMBER($S66))),"PENDIENTE",$K66-$S66)) | X66: =IF($A66="","",IFERROR(INDEX(tblInventario[Stock actual],MATCH($A66,tblInventario[SKU],0)),0)) | AB66: =IF($A66="","",IF(COUNTIF(tblCostos[SKU],$A66)=0,"SIN FILA EN COSTOS",IF(AND($K66="",NOT(ISNUMBER($Q66))),"FALTA PRECIO Y COSTO",IF($K66="","FALTA PRECIO",IF(NOT(ISNUMBER($Q66)),"FALTA COSTO",IF($T66<0,"MARGEN NEGATIVO",IF($T66=0,"PRECIO = COSTO","COMPLETO")))))))

Sheet COSTOS
A1: COSTOS — Estructura de costo por producto
A2: Aquí se capturan TODOS los costos. Nunca mezcle costos fijos (hoja GASTOS) con costos variables unitarios (esta hoja). Deje vacío lo que aún no conozca: el sistema mostrará PENDIENTE.
A3: COSTO REAL UNITARIO = costo de compra + materia prima + empaque + transporte + importación + impuestos/aranceles + otros logísticos + otros variables. · COSTO VARIABLE TOTAL = costo real unitario + costos variables de venta (comisiones, delivery, publicidad atribuible). El costo variable total es el que se usa para el margen de contribución y el punto de equilibrio.
D6: COSTOS DE PRODUCTO (directos, logísticos y otros variables) | L6: CONSOLIDADO DE COSTO REAL | P6: COSTOS VARIABLES DE VENTA
A7: SKU | B7: Producto | C7: Categoría | D7: Costo de compra unitario | E7: Materia prima unitaria | F7: Empaque unitario | G7: Transporte unitario | H7: Importación / flete internacional unitario | I7: Impuestos / aranceles unitarios | J7: Otros costos logísticos unitarios | K7: Otros costos variables no listados | L7: Subtotal costos directos | M7: Subtotal costos logísticos | N7: Otros costos variables unitarios | O7: COSTO REAL UNITARIO | P7: Comisión de venta % | Q7: Comisión bancaria / plataforma % | R7: Delivery asumido por unidad | S7: Publicidad atribuible por unidad | T7: Otros costos variables de venta | U7: Costo variable de venta unitario | V7: COSTO VARIABLE TOTAL UNITARIO | W7: Fecha de actualización | X7: Observaciones
A8: GEL-250 | B8: =IF($A8="","",IFERROR(IF(INDEX(tblProductos[Nombre del producto],MATCH($A8,tblProductos[SKU],0))="","",INDEX(tblProductos[Nombre del producto],MATCH($A8,tblProductos[SKU],0))),"")) | C8: =IF($A8="","",IFERROR(IF(INDEX(tblProductos[Categoría],MATCH($A8,tblProductos[SKU],0))="","",INDEX(tblProductos[Categoría],MATCH($A8,tblProductos[SKU],0))),"")) | L8: =IF(OR($A8="",COUNT($D8:$F8)=0),"",SUM($D8:$F8)) | M8: =IF(OR($A8="",COUNT($G8:$J8)=0),"",SUM($G8:$J8)) | N8: =IF(OR($A8="",COUNT($E8,$H8,$J8,$K8)=0),"",SUM($E8,$H8,$J8,$K8)) | O8: =IF($A8="","",IF($D8="","PENDIENTE",SUM($D8:$K8))) | U8: =IF($A8="","",IF(COUNT($P8:$T8)=0,0,IF(AND(SUM($P8:$Q8)>0,NOT(ISNUMBER(IFERROR(IF(INDEX(tblProductos[Precio de venta actual],MATCH($A8,tblProductos[SKU],0))="","",INDEX(tblProductos[Precio de venta actual],MATCH($A8,tblProductos[SKU],0))),"")))),"PENDIENTE",IF(ISNUMBER(IFERROR(IF(INDEX(tblProductos[Precio de venta actual],MATCH($A8,tblProductos[SKU],0))="","",INDEX(tblProductos[Precio de venta actual],MATCH($A8,tblProductos[SKU],0))),"")),IFERROR(IF(INDEX(tblProductos[Precio de venta actual],MATCH($A8,tblProductos[SKU],0))="","",INDEX(tblProductos[Precio de venta actual],MATCH($A8,tblProductos[SKU],0))),""),0)*SUM($P8:$Q8)+SUM($R8:$T8)))) | V8: =IF($A8="","",IF(OR(NOT(ISNUMBER($O8)),NOT(ISNUMBER($U8))),"PENDIENTE",$O8+$U8))
A9: GEL-500 | B9: =IF($A9="","",IFERROR(IF(INDEX(tblProductos[Nombre del producto],MATCH($A9,tblProductos[SKU],0))="","",INDEX(tblProductos[Nombre del producto],MATCH($A9,tblProductos[SKU],0))),"")) | C9: =IF($A9="","",IFERROR(IF(INDEX(tblProductos[Categoría],MATCH($A9,tblProductos[SKU],0))="","",INDEX(tblProductos[Categoría],MATCH($A9,tblProductos[SKU],0))),"")) | L9: =IF(OR($A9="",COUNT($D9:$F9)=0),"",SUM($D9:$F9)) | M9: =IF(OR($A9="",COUNT($G9:$J9)=0),"",SUM($G9:$J9)) | N9: =IF(OR($A9="",COUNT($E9,$H9,$J9,$K9)=0),"",SUM($E9,$H9,$J9,$K9)) | O9: =IF($A9="","",IF($D9="","PENDIENTE",SUM($D9:$K9))) | U9: =IF($A9="","",IF(COUNT($P9:$T9)=0,0,IF(AND(SUM($P9:$Q9)>0,NOT(ISNUMBER(IFERROR(IF(INDEX(tblProductos[Precio de venta actual],MATCH($A9,tblProductos[SKU],0))="","",INDEX(tblProductos[Precio de venta actual],MATCH($A9,tblProductos[SKU],0))),"")))),"PENDIENTE",IF(ISNUMBER(IFERROR(IF(INDEX(tblProductos[Precio de venta actual],MATCH($A9,tblProductos[SKU],0))="","",INDEX(tblProductos[Precio de venta actual],MATCH($A9,tblProductos[SKU],0))),"")),IFERROR(IF(INDEX(tblProductos[Precio de venta actual],MATCH($A9,tblProductos[SKU],0))="","",INDEX(tblProductos[Precio de venta actual],MATCH($A9,tblProductos[SKU],0))),""),0)*SUM($P9:$Q9)+SUM($R9:$T9)))) | V9: =IF($A9="","",IF(OR(NOT(ISNUMBER($O9)),NOT(ISNUMBER($U9))),"PENDIENTE",$O9+$U9))
A10: GEL-2L | B10: =IF($A10="","",IFERROR(IF(INDEX(tblProductos[Nombre del producto],MATCH($A10,tblProductos[SKU],0))="","",INDEX(tblProductos[Nombre del producto],MATCH($A10,tblProductos[SKU],0))),"")) | C10: =IF($A10="","",IFERROR(IF(INDEX(tblProductos[Categoría],MATCH($A10,tblProductos[SKU],0))="","",INDEX(tblProductos[Categoría],MATCH($A10,tblProductos[SKU],0))),"")) | L10: =IF(OR($A10="",COUNT($D10:$F10)=0),"",SUM($D10:$F10)) | M10: =IF(OR($A10="",COUNT($G10:$J10)=0),"",SUM($G10:$J10)) | N10: =IF(OR($A10="",COUNT($E10,$H10,$J10,$K10)=0),"",SUM($E10,$H10,$J10,$K10)) | O10: =IF($A10="","",IF($D10="","PENDIENTE",SUM($D10:$K10))) | U10: =IF($A10="","",IF(COUNT($P10:$T10)=0,0,IF(AND(SUM($P10:$Q10)>0,NOT(ISNUMBER(IFERROR(IF(INDEX(tblProductos[Precio de venta actual],MATCH($A10,tblProductos[SKU],0))="","",INDEX(tblProductos[Precio de venta actual],MATCH($A10,tblProductos[SKU],0))),"")))),"PENDIENTE",IF(ISNUMBER(IFERROR(IF(INDEX(tblProductos[Precio de venta actual],MATCH($A10,tblProductos[SKU],0))="","",INDEX(tblProductos[Precio de venta actual],MATCH($A10,tblProductos[SKU],0))),"")),IFERROR(IF(INDEX(tblProductos[Precio de venta actual],MATCH($A10,tblProductos[SKU],0))="","",INDEX(tblProductos[Precio de venta actual],MATCH($A10,tblProductos[SKU],0))),""),0)*SUM($P10:$Q10)+SUM($R10:$T10)))) | V10: =IF($A10="","",IF(OR(NOT(ISNUMBER($O10)),NOT(ISNUMBER($U10))),"PENDIENTE",$O10+$U10))
A11: GEL-GAL | B11: =IF($A11="","",IFERROR(IF(INDEX(tblProductos[Nombre del producto],MATCH($A11,tblProductos[SKU],0))="","",INDEX(tblProductos[Nombre del producto],MATCH($A11,tblProductos[SKU],0))),"")) | C11: =IF($A11="","",IFERROR(IF(INDEX(tblProductos[Categoría],MATCH($A11,tblProductos[SKU],0))="","",INDEX(tblProductos[Categoría],MATCH($A11,tblProductos[SKU],0))),"")) | L11: =IF(OR($A11="",COUNT($D11:$F11)=0),"",SUM($D11:$F11)) | M11: =IF(OR($A11="",COUNT($G11:$J11)=0),"",SUM($G11:$J11)) | N11: =IF(OR($A11="",COUNT($E11,$H11,$J11,$K11)=0),"",SUM($E11,$H11,$J11,$K11)) | O11: =IF($A11="","",IF($D11="","PENDIENTE",SUM($D11:$K11))) | U11: =IF($A11="","",IF(COUNT($P11:$T11)=0,0,IF(AND(SUM($P11:$Q11)>0,NOT(ISNUMBER(IFERROR(IF(INDEX(tblProductos[Precio de venta actual],MATCH($A11,tblProductos[SKU],0))="","",INDEX(tblProductos[Precio de venta actual],MATCH($A11,tblProductos[SKU],0))),"")))),"PENDIENTE",IF(ISNUMBER(IFERROR(IF(INDEX(tblProductos[Precio de venta actual],MATCH($A11,tblProductos[SKU],0))="","",INDEX(tblProductos[Precio de venta actual],MATCH($A11,tblProductos[SKU],0))),"")),IFERROR(IF(INDEX(tblProductos[Precio de venta actual],MATCH($A11,tblProductos[SKU],0))="","",INDEX(tblProductos[Precio de venta actual],MATCH($A11,tblProductos[SKU],0))),""),0)*SUM($P11:$Q11)+SUM($R11:$T11)))) | V11: =IF($A11="","",IF(OR(NOT(ISNUMBER($O11)),NOT(ISNUMBER($U11))),"PENDIENTE",$O11+$U11))
A12: JAB-500 | B12: =IF($A12="","",IFERROR(IF(INDEX(tblProductos[Nombre del producto],MATCH($A12,tblProductos[SKU],0))="","",INDEX(tblProductos[Nombre del producto],MATCH($A12,tblProductos[SKU],0))),"")) | C12: =IF($A12="","",IFERROR(IF(INDEX(tblProductos[Categoría],MATCH($A12,tblProductos[SKU],0))="","",INDEX(tblProductos[Categoría],MATCH($A12,tblProductos[SKU],0))),"")) | L12: =IF(OR($A12="",COUNT($D12:$F12)=0),"",SUM($D12:$F12)) | M12: =IF(OR($A12="",COUNT($G12:$J12)=0),"",SUM($G12:$J12)) | N12: =IF(OR($A12="",COUNT($E12,$H12,$J12,$K12)=0),"",SUM($E12,$H12,$J12,$K12)) | O12: =IF($A12="","",IF($D12="","PENDIENTE",SUM($D12:$K12))) | U12: =IF($A12="","",IF(COUNT($P12:$T12)=0,0,IF(AND(SUM($P12:$Q12)>0,NOT(ISNUMBER(IFERROR(IF(INDEX(tblProductos[Precio de venta actual],MATCH($A12,tblProductos[SKU],0))="","",INDEX(tblProductos[Precio de venta actual],MATCH($A12,tblProductos[SKU],0))),"")))),"PENDIENTE",IF(ISNUMBER(IFERROR(IF(INDEX(tblProductos[Precio de venta actual],MATCH($A12,tblProductos[SKU],0))="","",INDEX(tblProductos[Precio de venta actual],MATCH($A12,tblProductos[SKU],0))),"")),IFERROR(IF(INDEX(tblProductos[Precio de venta actual],MATCH($A12,tblProductos[SKU],0))="","",INDEX(tblProductos[Precio de venta actual],MATCH($A12,tblProductos[SKU],0))),""),0)*SUM($P12:$Q12)+SUM($R12:$T12)))) | V12: =IF($A12="","",IF(OR(NOT(ISNUMBER($O12)),NOT(ISNUMBER($U12))),"PENDIENTE",$O12+$U12))
A13: JAB-2L | B13: =IF($A13="","",IFERROR(IF(INDEX(tblProductos[Nombre del producto],MATCH($A13,tblProductos[SKU],0))="","",INDEX(tblProductos[Nombre del producto],MATCH($A13,tblProductos[SKU],0))),"")) | C13: =IF($A13="","",IFERROR(IF(INDEX(tblProductos[Categoría],MATCH($A13,tblProductos[SKU],0))="","",INDEX(tblProductos[Categoría],MATCH($A13,tblProductos[SKU],0))),"")) | L13: =IF(OR($A13="",COUNT($D13:$F13)=0),"",SUM($D13:$F13)) | M13: =IF(OR($A13="",COUNT($G13:$J13)=0),"",SUM($G13:$J13)) | N13: =IF(OR($A13="",COUNT($E13,$H13,$J13,$K13)=0),"",SUM($E13,$H13,$J13,$K13)) | O13: =IF($A13="","",IF($D13="","PENDIENTE",SUM($D13:$K13))) | U13: =IF($A13="","",IF(COUNT($P13:$T13)=0,0,IF(AND(SUM($P13:$Q13)>0,NOT(ISNUMBER(IFERROR(IF(INDEX(tblProductos[Precio de venta actual],MATCH($A13,tblProductos[SKU],0))="","",INDEX(tblProductos[Precio de venta actual],MATCH($A13,tblProductos[SKU],0))),"")))),"PENDIENTE",IF(ISNUMBER(IFERROR(IF(INDEX(tblProductos[Precio de venta actual],MATCH($A13,tblProductos[SKU],0))="","",INDEX(tblProductos[Precio de venta actual],MATCH($A13,tblProductos[SKU],0))),"")),IFERROR(IF(INDEX(tblProductos[Precio de venta actual],MATCH($A13,tblProductos[SKU],0))="","",INDEX(tblProductos[Precio de venta actual],MATCH($A13,tblProductos[SKU],0))),""),0)*SUM($P13:$Q13)+SUM($R13:$T13)))) | V13: =IF($A13="","",IF(OR(NOT(ISNUMBER($O13)),NOT(ISNUMBER($U13))),"PENDIENTE",$O13+$U13))
A14: JAB-GAL | B14: =IF($A14="","",IFERROR(IF(INDEX(tblProductos[Nombre del producto],MATCH($A14,tblProductos[SKU],0))="","",INDEX(tblProductos[Nombre del producto],MATCH($A14,tblProductos[SKU],0))),"")) | C14: =IF($A14="","",IFERROR(IF(INDEX(tblProductos[Categoría],MATCH($A14,tblProductos[SKU],0))="","",INDEX(tblProductos[Categoría],MATCH($A14,tblProductos[SKU],0))),"")) | L14: =IF(OR($A14="",COUNT($D14:$F14)=0),"",SUM($D14:$F14)) | M14: =IF(OR($A14="",COUNT($G14:$J14)=0),"",SUM($G14:$J14)) | N14: =IF(OR($A14="",COUNT($E14,$H14,$J14,$K14)=0),"",SUM($E14,$H14,$J14,$K14)) | O14: =IF($A14="","",IF($D14="","PENDIENTE",SUM($D14:$K14))) | U14: =IF($A14="","",IF(COUNT($P14:$T14)=0,0,IF(AND(SUM($P14:$Q14)>0,NOT(ISNUMBER(IFERROR(IF(INDEX(tblProductos[Precio de venta actual],MATCH($A14,tblProductos[SKU],0))="","",INDEX(tblProductos[Precio de venta actual],MATCH($A14,tblProductos[SKU],0))),"")))),"PENDIENTE",IF(ISNUMBER(IFERROR(IF(INDEX(tblProductos[Precio de venta actual],MATCH($A14,tblProductos[SKU],0))="","",INDEX(tblProductos[Precio de venta actual],MATCH($A14,tblProductos[SKU],0))),"")),IFERROR(IF(INDEX(tblProductos[Precio de venta actual],MATCH($A14,tblProductos[SKU],0))="","",INDEX(tblProductos[Precio de venta actual],MATCH($A14,tblProductos[SKU],0))),""),0)*SUM($P14:$Q14)+SUM($R14:$T14)))) | V14: =IF($A14="","",IF(OR(NOT(ISNUMBER($O14)),NOT(ISNUMBER($U14))),"PENDIENTE",$O14+$U14))
A15: SUA-GAL | B15: =IF($A15="","",IFERROR(IF(INDEX(tblProductos[Nombre del producto],MATCH($A15,tblProductos[SKU],0))="","",INDEX(tblProductos[Nombre del producto],MATCH($A15,tblProductos[SKU],0))),"")) | C15: =IF($A15="","",IFERROR(IF(INDEX(tblProductos[Categoría],MATCH($A15,tblProductos[SKU],0))="","",INDEX(tblProductos[Categoría],MATCH($A15,tblProductos[SKU],0))),"")) | L15: =IF(OR($A15="",COUNT($D15:$F15)=0),"",SUM($D15:$F15)) | M15: =IF(OR($A15="",COUNT($G15:$J15)=0),"",SUM($G15:$J15)) | N15: =IF(OR($A15="",COUNT($E15,$H15,$J15,$K15)=0),"",SUM($E15,$H15,$J15,$K15)) | O15: =IF($A15="","",IF($D15="","PENDIENTE",SUM($D15:$K15))) | U15: =IF($A15="","",IF(COUNT($P15:$T15)=0,0,IF(AND(SUM($P15:$Q15)>0,NOT(ISNUMBER(IFERROR(IF(INDEX(tblProductos[Precio de venta actual],MATCH($A15,tblProductos[SKU],0))="","",INDEX(tblProductos[Precio de venta actual],MATCH($A15,tblProductos[SKU],0))),"")))),"PENDIENTE",IF(ISNUMBER(IFERROR(IF(INDEX(tblProductos[Precio de venta actual],MATCH($A15,tblProductos[SKU],0))="","",INDEX(tblProductos[Precio de venta actual],MATCH($A15,tblProductos[SKU],0))),"")),IFERROR(IF(INDEX(tblProductos[Precio de venta actual],MATCH($A15,tblProductos[SKU],0))="","",INDEX(tblProductos[Precio de venta actual],MATCH($A15,tblProductos[SKU],0))),""),0)*SUM($P15:$Q15)+SUM($R15:$T15)))) | V15: =IF($A15="","",IF(OR(NOT(ISNUMBER($O15)),NOT(ISNUMBER($U15))),"PENDIENTE",$O15+$U15))
A16: DET-GAL | B16: =IF($A16="","",IFERROR(IF(INDEX(tblProductos[Nombre del producto],MATCH($A16,tblProductos[SKU],0))="","",INDEX(tblProductos[Nombre del producto],MATCH($A16,tblProductos[SKU],0))),"")) | C16: =IF($A16="","",IFERROR(IF(INDEX(tblProductos[Categoría],MATCH($A16,tblProductos[SKU],0))="","",INDEX(tblProductos[Categoría],MATCH($A16,tblProductos[SKU],0))),"")) | L16: =IF(OR($A16="",COUNT($D16:$F16)=0),"",SUM($D16:$F16)) | M16: =IF(OR($A16="",COUNT($G16:$J16)=0),"",SUM($G16:$J16)) | N16: =IF(OR($A16="",COUNT($E16,$H16,$J16,$K16)=0),"",SUM($E16,$H16,$J16,$K16)) | O16: =IF($A16="","",IF($D16="","PENDIENTE",SUM($D16:$K16))) | U16: =IF($A16="","",IF(COUNT($P16:$T16)=0,0,IF(AND(SUM($P16:$Q16)>0,NOT(ISNUMBER(IFERROR(IF(INDEX(tblProductos[Precio de venta actual],MATCH($A16,tblProductos[SKU],0))="","",INDEX(tblProductos[Precio de venta actual],MATCH($A16,tblProductos[SKU],0))),"")))),"PENDIENTE",IF(ISNUMBER(IFERROR(IF(INDEX(tblProductos[Precio de venta actual],MATCH($A16,tblProductos[SKU],0))="","",INDEX(tblProductos[Precio de venta actual],MATCH($A16,tblProductos[SKU],0))),"")),IFERROR(IF(INDEX(tblProductos[Precio de venta actual],MATCH($A16,tblProductos[SKU],0))="","",INDEX(tblProductos[Precio de venta actual],MATCH($A16,tblProductos[SKU],0))),""),0)*SUM($P16:$Q16)+SUM($R16:$T16)))) | V16: =IF($A16="","",IF(OR(NOT(ISNUMBER($O16)),NOT(ISNUMBER($U16))),"PENDIENTE",$O16+$U16))
A17: VID-750 | B17: =IF($A17="","",IFERROR(IF(INDEX(tblProductos[Nombre del producto],MATCH($A17,tblProductos[SKU],0))="","",INDEX(tblProductos[Nombre del producto],MATCH($A17,tblProductos[SKU],0))),"")) | C17: =IF($A17="","",IFERROR(IF(INDEX(tblProductos[Categoría],MATCH($A17,tblProductos[SKU],0))="","",INDEX(tblProductos[Categoría],MATCH($A17,tblProductos[SKU],0))),"")) | L17: =IF(OR($A17="",COUNT($D17:$F17)=0),"",SUM($D17:$F17)) | M17: =IF(OR($A17="",COUNT($G17:$J17)=0),"",SUM($G17:$J17)) | N17: =IF(OR($A17="",COUNT($E17,$H17,$J17,$K17)=0),"",SUM($E17,$H17,$J17,$K17)) | O17: =IF($A17="","",IF($D17="","PENDIENTE",SUM($D17:$K17))) | U17: =IF($A17="","",IF(COUNT($P17:$T17)=0,0,IF(AND(SUM($P17:$Q17)>0,NOT(ISNUMBER(IFERROR(IF(INDEX(tblProductos[Precio de venta actual],MATCH($A17,tblProductos[SKU],0))="","",INDEX(tblProductos[Precio de venta actual],MATCH($A17,tblProductos[SKU],0))),"")))),"PENDIENTE",IF(ISNUMBER(IFERROR(IF(INDEX(tblProductos[Precio de venta actual],MATCH($A17,tblProductos[SKU],0))="","",INDEX(tblProductos[Precio de venta actual],MATCH($A17,tblProductos[SKU],0))),"")),IFERROR(IF(INDEX(tblProductos[Precio de venta actual],MATCH($A17,tblProductos[SKU],0))="","",INDEX(tblProductos[Precio de venta actual],MATCH($A17,tblProductos[SKU],0))),""),0)*SUM($P17:$Q17)+SUM($R17:$T17)))) | V17: =IF($A17="","",IF(OR(NOT(ISNUMBER($O17)),NOT(ISNUMBER($U17))),"PENDIENTE",$O17+$U17))
A18: VID-GAL | B18: =IF($A18="","",IFERROR(IF(INDEX(tblProductos[Nombre del producto],MATCH($A18,tblProductos[SKU],0))="","",INDEX(tblProductos[Nombre del producto],MATCH($A18,tblProductos[SKU],0))),"")) | C18: =IF($A18="","",IFERROR(IF(INDEX(tblProductos[Categoría],MATCH($A18,tblProductos[SKU],0))="","",INDEX(tblProductos[Categoría],MATCH($A18,tblProductos[SKU],0))),"")) | L18: =IF(OR($A18="",COUNT($D18:$F18)=0),"",SUM($D18:$F18)) | M18: =IF(OR($A18="",COUNT($G18:$J18)=0),"",SUM($G18:$J18)) | N18: =IF(OR($A18="",COUNT($E18,$H18,$J18,$K18)=0),"",SUM($E18,$H18,$J18,$K18)) | O18: =IF($A18="","",IF($D18="","PENDIENTE",SUM($D18:$K18))) | U18: =IF($A18="","",IF(COUNT($P18:$T18)=0,0,IF(AND(SUM($P18:$Q18)>0,NOT(ISNUMBER(IFERROR(IF(INDEX(tblProductos[Precio de venta actual],MATCH($A18,tblProductos[SKU],0))="","",INDEX(tblProductos[Precio de venta actual],MATCH($A18,tblProductos[SKU],0))),"")))),"PENDIENTE",IF(ISNUMBER(IFERROR(IF(INDEX(tblProductos[Precio de venta actual],MATCH($A18,tblProductos[SKU],0))="","",INDEX(tblProductos[Precio de venta actual],MATCH($A18,tblProductos[SKU],0))),"")),IFERROR(IF(INDEX(tblProductos[Precio de venta actual],MATCH($A18,tblProductos[SKU],0))="","",INDEX(tblProductos[Precio de venta actual],MATCH($A18,tblProductos[SKU],0))),""),0)*SUM($P18:$Q18)+SUM($R18:$T18)))) | V18: =IF($A18="","",IF(OR(NOT(ISNUMBER($O18)),NOT(ISNUMBER($U18))),"PENDIENTE",$O18+$U18))
A19: LAV-500 | B19: =IF($A19="","",IFERROR(IF(INDEX(tblProductos[Nombre del producto],MATCH($A19,tblProductos[SKU],0))="","",INDEX(tblProductos[Nombre del producto],MATCH($A19,tblProductos[SKU],0))),"")) | C19: =IF($A19="","",IFERROR(IF(INDEX(tblProductos[Categoría],MATCH($A19,tblProductos[SKU],0))="","",INDEX(tblProductos[Categoría],MATCH($A19,tblProductos[SKU],0))),"")) | L19: =IF(OR($A19="",COUNT($D19:$F19)=0),"",SUM($D19:$F19)) | M19: =IF(OR($A19="",COUNT($G19:$J19)=0),"",SUM($G19:$J19)) | N19: =IF(OR($A19="",COUNT($E19,$H19,$J19,$K19)=0),"",SUM($E19,$H19,$J19,$K19)) | O19: =IF($A19="","",IF($D19="","PENDIENTE",SUM($D19:$K19))) | U19: =IF($A19="","",IF(COUNT($P19:$T19)=0,0,IF(AND(SUM($P19:$Q19)>0,NOT(ISNUMBER(IFERROR(IF(INDEX(tblProductos[Precio de venta actual],MATCH($A19,tblProductos[SKU],0))="","",INDEX(tblProductos[Precio de venta actual],MATCH($A19,tblProductos[SKU],0))),"")))),"PENDIENTE",IF(ISNUMBER(IFERROR(IF(INDEX(tblProductos[Precio de venta actual],MATCH($A19,tblProductos[SKU],0))="","",INDEX(tblProductos[Precio de venta actual],MATCH($A19,tblProductos[SKU],0))),"")),IFERROR(IF(INDEX(tblProductos[Precio de venta actual],MATCH($A19,tblProductos[SKU],0))="","",INDEX(tblProductos[Precio de venta actual],MATCH($A19,tblProductos[SKU],0))),""),0)*SUM($P19:$Q19)+SUM($R19:$T19)))) | V19: =IF($A19="","",IF(OR(NOT(ISNUMBER($O19)),NOT(ISNUMBER($U19))),"PENDIENTE",$O19+$U19))
... A47: DEI-GAL | B47: =IF($A47="","",IFERROR(IF(INDEX(tblProductos[Nombre del producto],MATCH($A47,tblProductos[SKU],0))="","",INDEX(tblProductos[Nombre del producto],MATCH($A47,tblProductos[SKU],0))),"")) | C47: =IF($A47="","",IFERROR(IF(INDEX(tblProductos[Categoría],MATCH($A47,tblProductos[SKU],0))="","",INDEX(tblProductos[Categoría],MATCH($A47,tblProductos[SKU],0))),"")) | L47: =IF(OR($A47="",COUNT($D47:$F47)=0),"",SUM($D47:$F47)) | M47: =IF(OR($A47="",COUNT($G47:$J47)=0),"",SUM($G47:$J47)) | N47: =IF(OR($A47="",COUNT($E47,$H47,$J47,$K47)=0),"",SUM($E47,$H47,$J47,$K47)) | O47: =IF($A47="","",IF($D47="","PENDIENTE",SUM($D47:$K47))) | U47: =IF($A47="","",IF(COUNT($P47:$T47)=0,0,IF(AND(SUM($P47:$Q47)>0,NOT(ISNUMBER(IFERROR(IF(INDEX(tblProductos[Precio de venta actual],MATCH($A47,tblProductos[SKU],0))="","",INDEX(tblProductos[Precio de venta actual],MATCH($A47,tblProductos[SKU],0))),"")))),"PENDIENTE",IF(ISNUMBER(IFERROR(IF(INDEX(tblProductos[Precio de venta actual],MATCH($A47,tblProductos[SKU],0))="","",INDEX(tblProductos[Precio de venta actual],MATCH($A47,tblProductos[SKU],0))),"")),IFERROR(IF(INDEX(tblProductos[Precio de venta actual],MATCH($A47,tblProductos[SKU],0))="","",INDEX(tblProductos[Precio de venta actual],MATCH($A47,tblProductos[SKU],0))),""),0)*SUM($P47:$Q47)+SUM($R47:$T47)))) | V47: =IF($A47="","",IF(OR(NOT(ISNUMBER($O47)),NOT(ISNUMBER($U47))),"PENDIENTE",$O47+$U47))
B48: =IF($A48="","",IFERROR(IF(INDEX(tblProductos[Nombre del producto],MATCH($A48,tblProductos[SKU],0))="","",INDEX(tblProductos[Nombre del producto],MATCH($A48,tblProductos[SKU],0))),"")) | C48: =IF($A48="","",IFERROR(IF(INDEX(tblProductos[Categoría],MATCH($A48,tblProductos[SKU],0))="","",INDEX(tblProductos[Categoría],MATCH($A48,tblProductos[SKU],0))),"")) | L48: =IF(OR($A48="",COUNT($D48:$F48)=0),"",SUM($D48:$F48)) | M48: =IF(OR($A48="",COUNT($G48:$J48)=0),"",SUM($G48:$J48)) | N48: =IF(OR($A48="",COUNT($E48,$H48,$J48,$K48)=0),"",SUM($E48,$H48,$J48,$K48)) | O48: =IF($A48="","",IF($D48="","PENDIENTE",SUM($D48:$K48))) | U48: =IF($A48="","",IF(COUNT($P48:$T48)=0,0,IF(AND(SUM($P48:$Q48)>0,NOT(ISNUMBER(IFERROR(IF(INDEX(tblProductos[Precio de venta actual],MATCH($A48,tblProductos[SKU],0))="","",INDEX(tblProductos[Precio de venta actual],MATCH($A48,tblProductos[SKU],0))),"")))),"PENDIENTE",IF(ISNUMBER(IFERROR(IF(INDEX(tblProductos[Precio de venta actual],MATCH($A48,tblProductos[SKU],0))="","",INDEX(tblProductos[Precio de venta actual],MATCH($A48,tblProductos[SKU],0))),"")),IFERROR(IF(INDEX(tblProductos[Precio de venta actual],MATCH($A48,tblProductos[SKU],0))="","",INDEX(tblProductos[Precio de venta actual],MATCH($A48,tblProductos[SKU],0))),""),0)*SUM($P48:$Q48)+SUM($R48:$T48)))) | V48: =IF($A48="","",IF(OR(NOT(ISNUMBER($O48)),NOT(ISNUMBER($U48))),"PENDIENTE",$O48+$U48))
B49: =IF($A49="","",IFERROR(IF(INDEX(tblProductos[Nombre del producto],MATCH($A49,tblProductos[SKU],0))="","",INDEX(tblProductos[Nombre del producto],MATCH($A49,tblProductos[SKU],0))),"")) | C49: =IF($A49="","",IFERROR(IF(INDEX(tblProductos[Categoría],MATCH($A49,tblProductos[SKU],0))="","",INDEX(tblProductos[Categoría],MATCH($A49,tblProductos[SKU],0))),"")) | L49: =IF(OR($A49="",COUNT($D49:$F49)=0),"",SUM($D49:$F49)) | M49: =IF(OR($A49="",COUNT($G49:$J49)=0),"",SUM($G49:$J49)) | N49: =IF(OR($A49="",COUNT($E49,$H49,$J49,$K49)=0),"",SUM($E49,$H49,$J49,$K49)) | O49: =IF($A49="","",IF($D49="","PENDIENTE",SUM($D49:$K49))) | U49: =IF($A49="","",IF(COUNT($P49:$T49)=0,0,IF(AND(SUM($P49:$Q49)>0,NOT(ISNUMBER(IFERROR(IF(INDEX(tblProductos[Precio de venta actual],MATCH($A49,tblProductos[SKU],0))="","",INDEX(tblProductos[Precio de venta actual],MATCH($A49,tblProductos[SKU],0))),"")))),"PENDIENTE",IF(ISNUMBER(IFERROR(IF(INDEX(tblProductos[Precio de venta actual],MATCH($A49,tblProductos[SKU],0))="","",INDEX(tblProductos[Precio de venta actual],MATCH($A49,tblProductos[SKU],0))),"")),IFERROR(IF(INDEX(tblProductos[Precio de venta actual],MATCH($A49,tblProductos[SKU],0))="","",INDEX(tblProductos[Precio de venta actual],MATCH($A49,tblProductos[SKU],0))),""),0)*SUM($P49:$Q49)+SUM($R49:$T49)))) | V49: =IF($A49="","",IF(OR(NOT(ISNUMBER($O49)),NOT(ISNUMBER($U49))),"PENDIENTE",$O49+$U49))
B50: =IF($A50="","",IFERROR(IF(INDEX(tblProductos[Nombre del producto],MATCH($A50,tblProductos[SKU],0))="","",INDEX(tblProductos[Nombre del producto],MATCH($A50,tblProductos[SKU],0))),"")) | C50: =IF($A50="","",IFERROR(IF(INDEX(tblProductos[Categoría],MATCH($A50,tblProductos[SKU],0))="","",INDEX(tblProductos[Categoría],MATCH($A50,tblProductos[SKU],0))),"")) | L50: =IF(OR($A50="",COUNT($D50:$F50)=0),"",SUM($D50:$F50)) | M50: =IF(OR($A50="",COUNT($G50:$J50)=0),"",SUM($G50:$J50)) | N50: =IF(OR($A50="",COUNT($E50,$H50,$J50,$K50)=0),"",SUM($E50,$H50,$J50,$K50)) | O50: =IF($A50="","",IF($D50="","PENDIENTE",SUM($D50:$K50))) | U50: =IF($A50="","",IF(COUNT($P50:$T50)=0,0,IF(AND(SUM($P50:$Q50)>0,NOT(ISNUMBER(IFERROR(IF(INDEX(tblProductos[Precio de venta actual],MATCH($A50,tblProductos[SKU],0))="","",INDEX(tblProductos[Precio de venta actual],MATCH($A50,tblProductos[SKU],0))),"")))),"PENDIENTE",IF(ISNUMBER(IFERROR(IF(INDEX(tblProductos[Precio de venta actual],MATCH($A50,tblProductos[SKU],0))="","",INDEX(tblProductos[Precio de venta actual],MATCH($A50,tblProductos[SKU],0))),"")),IFERROR(IF(INDEX(tblProductos[Precio de venta actual],MATCH($A50,tblProductos[SKU],0))="","",INDEX(tblProductos[Precio de venta actual],MATCH($A50,tblProductos[SKU],0))),""),0)*SUM($P50:$Q50)+SUM($R50:$T50)))) | V50: =IF($A50="","",IF(OR(NOT(ISNUMBER($O50)),NOT(ISNUMBER($U50))),"PENDIENTE",$O50+$U50))
B51: =IF($A51="","",IFERROR(IF(INDEX(tblProductos[Nombre del producto],MATCH($A51,tblProductos[SKU],0))="","",INDEX(tblProductos[Nombre del producto],MATCH($A51,tblProductos[SKU],0))),"")) | C51: =IF($A51="","",IFERROR(IF(INDEX(tblProductos[Categoría],MATCH($A51,tblProductos[SKU],0))="","",INDEX(tblProductos[Categoría],MATCH($A51,tblProductos[SKU],0))),"")) | L51: =IF(OR($A51="",COUNT($D51:$F51)=0),"",SUM($D51:$F51)) | M51: =IF(OR($A51="",COUNT($G51:$J51)=0),"",SUM($G51:$J51)) | N51: =IF(OR($A51="",COUNT($E51,$H51,$J51,$K51)=0),"",SUM($E51,$H51,$J51,$K51)) | O51: =IF($A51="","",IF($D51="","PENDIENTE",SUM($D51:$K51))) | U51: =IF($A51="","",IF(COUNT($P51:$T51)=0,0,IF(AND(SUM($P51:$Q51)>0,NOT(ISNUMBER(IFERROR(IF(INDEX(tblProductos[Precio de venta actual],MATCH($A51,tblProductos[SKU],0))="","",INDEX(tblProductos[Precio de venta actual],MATCH($A51,tblProductos[SKU],0))),"")))),"PENDIENTE",IF(ISNUMBER(IFERROR(IF(INDEX(tblProductos[Precio de venta actual],MATCH($A51,tblProductos[SKU],0))="","",INDEX(tblProductos[Precio de venta actual],MATCH($A51,tblProductos[SKU],0))),"")),IFERROR(IF(INDEX(tblProductos[Precio de venta actual],MATCH($A51,tblProductos[SKU],0))="","",INDEX(tblProductos[Precio de venta actual],MATCH($A51,tblProductos[SKU],0))),""),0)*SUM($P51:$Q51)+SUM($R51:$T51)))) | V51: =IF($A51="","",IF(OR(NOT(ISNUMBER($O51)),NOT(ISNUMBER($U51))),"PENDIENTE",$O51+$U51))
B52: =IF($A52="","",IFERROR(IF(INDEX(tblProductos[Nombre del producto],MATCH($A52,tblProductos[SKU],0))="","",INDEX(tblProductos[Nombre del producto],MATCH($A52,tblProductos[SKU],0))),"")) | C52: =IF($A52="","",IFERROR(IF(INDEX(tblProductos[Categoría],MATCH($A52,tblProductos[SKU],0))="","",INDEX(tblProductos[Categoría],MATCH($A52,tblProductos[SKU],0))),"")) | L52: =IF(OR($A52="",COUNT($D52:$F52)=0),"",SUM($D52:$F52)) | M52: =IF(OR($A52="",COUNT($G52:$J52)=0),"",SUM($G52:$J52)) | N52: =IF(OR($A52="",COUNT($E52,$H52,$J52,$K52)=0),"",SUM($E52,$H52,$J52,$K52)) | O52: =IF($A52="","",IF($D52="","PENDIENTE",SUM($D52:$K52))) | U52: =IF($A52="","",IF(COUNT($P52:$T52)=0,0,IF(AND(SUM($P52:$Q52)>0,NOT(ISNUMBER(IFERROR(IF(INDEX(tblProductos[Precio de venta actual],MATCH($A52,tblProductos[SKU],0))="","",INDEX(tblProductos[Precio de venta actual],MATCH($A52,tblProductos[SKU],0))),"")))),"PENDIENTE",IF(ISNUMBER(IFERROR(IF(INDEX(tblProductos[Precio de venta actual],MATCH($A52,tblProductos[SKU],0))="","",INDEX(tblProductos[Precio de venta actual],MATCH($A52,tblProductos[SKU],0))),"")),IFERROR(IF(INDEX(tblProductos[Precio de venta actual],MATCH($A52,tblProductos[SKU],0))="","",INDEX(tblProductos[Precio de venta actual],MATCH($A52,tblProductos[SKU],0))),""),0)*SUM($P52:$Q52)+SUM($R52:$T52)))) | V52: =IF($A52="","",IF(OR(NOT(ISNUMBER($O52)),NOT(ISNUMBER($U52))),"PENDIENTE",$O52+$U52))
B53: =IF($A53="","",IFERROR(IF(INDEX(tblProductos[Nombre del producto],MATCH($A53,tblProductos[SKU],0))="","",INDEX(tblProductos[Nombre del producto],MATCH($A53,tblProductos[SKU],0))),"")) | C53: =IF($A53="","",IFERROR(IF(INDEX(tblProductos[Categoría],MATCH($A53,tblProductos[SKU],0))="","",INDEX(tblProductos[Categoría],MATCH($A53,tblProductos[SKU],0))),"")) | L53: =IF(OR($A53="",COUNT($D53:$F53)=0),"",SUM($D53:$F53)) | M53: =IF(OR($A53="",COUNT($G53:$J53)=0),"",SUM($G53:$J53)) | N53: =IF(OR($A53="",COUNT($E53,$H53,$J53,$K53)=0),"",SUM($E53,$H53,$J53,$K53)) | O53: =IF($A53="","",IF($D53="","PENDIENTE",SUM($D53:$K53))) | U53: =IF($A53="","",IF(COUNT($P53:$T53)=0,0,IF(AND(SUM($P53:$Q53)>0,NOT(ISNUMBER(IFERROR(IF(INDEX(tblProductos[Precio de venta actual],MATCH($A53,tblProductos[SKU],0))="","",INDEX(tblProductos[Precio de venta actual],MATCH($A53,tblProductos[SKU],0))),"")))),"PENDIENTE",IF(ISNUMBER(IFERROR(IF(INDEX(tblProductos[Precio de venta actual],MATCH($A53,tblProductos[SKU],0))="","",INDEX(tblProductos[Precio de venta actual],MATCH($A53,tblProductos[SKU],0))),"")),IFERROR(IF(INDEX(tblProductos[Precio de venta actual],MATCH($A53,tblProductos[SKU],0))="","",INDEX(tblProductos[Precio de venta actual],MATCH($A53,tblProductos[SKU],0))),""),0)*SUM($P53:$Q53)+SUM($R53:$T53)))) | V53: =IF($A53="","",IF(OR(NOT(ISNUMBER($O53)),NOT(ISNUMBER($U53))),"PENDIENTE",$O53+$U53))
B54: =IF($A54="","",IFERROR(IF(INDEX(tblProductos[Nombre del producto],MATCH($A54,tblProductos[SKU],0))="","",INDEX(tblProductos[Nombre del producto],MATCH($A54,tblProductos[SKU],0))),"")) | C54: =IF($A54="","",IFERROR(IF(INDEX(tblProductos[Categoría],MATCH($A54,tblProductos[SKU],0))="","",INDEX(tblProductos[Categoría],MATCH($A54,tblProductos[SKU],0))),"")) | L54: =IF(OR($A54="",COUNT($D54:$F54)=0),"",SUM($D54:$F54)) | M54: =IF(OR($A54="",COUNT($G54:$J54)=0),"",SUM($G54:$J54)) | N54: =IF(OR($A54="",COUNT($E54,$H54,$J54,$K54)=0),"",SUM($E54,$H54,$J54,$K54)) | O54: =IF($A54="","",IF($D54="","PENDIENTE",SUM($D54:$K54))) | U54: =IF($A54="","",IF(COUNT($P54:$T54)=0,0,IF(AND(SUM($P54:$Q54)>0,NOT(ISNUMBER(IFERROR(IF(INDEX(tblProductos[Precio de venta actual],MATCH($A54,tblProductos[SKU],0))="","",INDEX(tblProductos[Precio de venta actual],MATCH($A54,tblProductos[SKU],0))),"")))),"PENDIENTE",IF(ISNUMBER(IFERROR(IF(INDEX(tblProductos[Precio de venta actual],MATCH($A54,tblProductos[SKU],0))="","",INDEX(tblProductos[Precio de venta actual],MATCH($A54,tblProductos[SKU],0))),"")),IFERROR(IF(INDEX(tblProductos[Precio de venta actual],MATCH($A54,tblProductos[SKU],0))="","",INDEX(tblProductos[Precio de venta actual],MATCH($A54,tblProductos[SKU],0))),""),0)*SUM($P54:$Q54)+SUM($R54:$T54)))) | V54: =IF($A54="","",IF(OR(NOT(ISNUMBER($O54)),NOT(ISNUMBER($U54))),"PENDIENTE",$O54+$U54))
B55: =IF($A55="","",IFERROR(IF(INDEX(tblProductos[Nombre del producto],MATCH($A55,tblProductos[SKU],0))="","",INDEX(tblProductos[Nombre del producto],MATCH($A55,tblProductos[SKU],0))),"")) | C55: =IF($A55="","",IFERROR(IF(INDEX(tblProductos[Categoría],MATCH($A55,tblProductos[SKU],0))="","",INDEX(tblProductos[Categoría],MATCH($A55,tblProductos[SKU],0))),"")) | L55: =IF(OR($A55="",COUNT($D55:$F55)=0),"",SUM($D55:$F55)) | M55: =IF(OR($A55="",COUNT($G55:$J55)=0),"",SUM($G55:$J55)) | N55: =IF(OR($A55="",COUNT($E55,$H55,$J55,$K55)=0),"",SUM($E55,$H55,$J55,$K55)) | O55: =IF($A55="","",IF($D55="","PENDIENTE",SUM($D55:$K55))) | U55: =IF($A55="","",IF(COUNT($P55:$T55)=0,0,IF(AND(SUM($P55:$Q55)>0,NOT(ISNUMBER(IFERROR(IF(INDEX(tblProductos[Precio de venta actual],MATCH($A55,tblProductos[SKU],0))="","",INDEX(tblProductos[Precio de venta actual],MATCH($A55,tblProductos[SKU],0))),"")))),"PENDIENTE",IF(ISNUMBER(IFERROR(IF(INDEX(tblProductos[Precio de venta actual],MATCH($A55,tblProductos[SKU],0))="","",INDEX(tblProductos[Precio de venta actual],MATCH($A55,tblProductos[SKU],0))),"")),IFERROR(IF(INDEX(tblProductos[Precio de venta actual],MATCH($A55,tblProductos[SKU],0))="","",INDEX(tblProductos[Precio de venta actual],MATCH($A55,tblProductos[SKU],0))),""),0)*SUM($P55:$Q55)+SUM($R55:$T55)))) | V55: =IF($A55="","",IF(OR(NOT(ISNUMBER($O55)),NOT(ISNUMBER($U55))),"PENDIENTE",$O55+$U55))
B56: =IF($A56="","",IFERROR(IF(INDEX(tblProductos[Nombre del producto],MATCH($A56,tblProductos[SKU],0))="","",INDEX(tblProductos[Nombre del producto],MATCH($A56,tblProductos[SKU],0))),"")) | C56: =IF($A56="","",IFERROR(IF(INDEX(tblProductos[Categoría],MATCH($A56,tblProductos[SKU],0))="","",INDEX(tblProductos[Categoría],MATCH($A56,tblProductos[SKU],0))),"")) | L56: =IF(OR($A56="",COUNT($D56:$F56)=0),"",SUM($D56:$F56)) | M56: =IF(OR($A56="",COUNT($G56:$J56)=0),"",SUM($G56:$J56)) | N56: =IF(OR($A56="",COUNT($E56,$H56,$J56,$K56)=0),"",SUM($E56,$H56,$J56,$K56)) | O56: =IF($A56="","",IF($D56="","PENDIENTE",SUM($D56:$K56))) | U56: =IF($A56="","",IF(COUNT($P56:$T56)=0,0,IF(AND(SUM($P56:$Q56)>0,NOT(ISNUMBER(IFERROR(IF(INDEX(tblProductos[Precio de venta actual],MATCH($A56,tblProductos[SKU],0))="","",INDEX(tblProductos[Precio de venta actual],MATCH($A56,tblProductos[SKU],0))),"")))),"PENDIENTE",IF(ISNUMBER(IFERROR(IF(INDEX(tblProductos[Precio de venta actual],MATCH($A56,tblProductos[SKU],0))="","",INDEX(tblProductos[Precio de venta actual],MATCH($A56,tblProductos[SKU],0))),"")),IFERROR(IF(INDEX(tblProductos[Precio de venta actual],MATCH($A56,tblProductos[SKU],0))="","",INDEX(tblProductos[Precio de venta actual],MATCH($A56,tblProductos[SKU],0))),""),0)*SUM($P56:$Q56)+SUM($R56:$T56)))) | V56: =IF($A56="","",IF(OR(NOT(ISNUMBER($O56)),NOT(ISNUMBER($U56))),"PENDIENTE",$O56+$U56))
B57: =IF($A57="","",IFERROR(IF(INDEX(tblProductos[Nombre del producto],MATCH($A57,tblProductos[SKU],0))="","",INDEX(tblProductos[Nombre del producto],MATCH($A57,tblProductos[SKU],0))),"")) | C57: =IF($A57="","",IFERROR(IF(INDEX(tblProductos[Categoría],MATCH($A57,tblProductos[SKU],0))="","",INDEX(tblProductos[Categoría],MATCH($A57,tblProductos[SKU],0))),"")) | L57: =IF(OR($A57="",COUNT($D57:$F57)=0),"",SUM($D57:$F57)) | M57: =IF(OR($A57="",COUNT($G57:$J57)=0),"",SUM($G57:$J57)) | N57: =IF(OR($A57="",COUNT($E57,$H57,$J57,$K57)=0),"",SUM($E57,$H57,$J57,$K57)) | O57: =IF($A57="","",IF($D57="","PENDIENTE",SUM($D57:$K57))) | U57: =IF($A57="","",IF(COUNT($P57:$T57)=0,0,IF(AND(SUM($P57:$Q57)>0,NOT(ISNUMBER(IFERROR(IF(INDEX(tblProductos[Precio de venta actual],MATCH($A57,tblProductos[SKU],0))="","",INDEX(tblProductos[Precio de venta actual],MATCH($A57,tblProductos[SKU],0))),"")))),"PENDIENTE",IF(ISNUMBER(IFERROR(IF(INDEX(tblProductos[Precio de venta actual],MATCH($A57,tblProductos[SKU],0))="","",INDEX(tblProductos[Precio de venta actual],MATCH($A57,tblProductos[SKU],0))),"")),IFERROR(IF(INDEX(tblProductos[Precio de venta actual],MATCH($A57,tblProductos[SKU],0))="","",INDEX(tblProductos[Precio de venta actual],MATCH($A57,tblProductos[SKU],0))),""),0)*SUM($P57:$Q57)+SUM($R57:$T57)))) | V57: =IF($A57="","",IF(OR(NOT(ISNUMBER($O57)),NOT(ISNUMBER($U57))),"PENDIENTE",$O57+$U57))
B58: =IF($A58="","",IFERROR(IF(INDEX(tblProductos[Nombre del producto],MATCH($A58,tblProductos[SKU],0))="","",INDEX(tblProductos[Nombre del producto],MATCH($A58,tblProductos[SKU],0))),"")) | C58: =IF($A58="","",IFERROR(IF(INDEX(tblProductos[Categoría],MATCH($A58,tblProductos[SKU],0))="","",INDEX(tblProductos[Categoría],MATCH($A58,tblProductos[SKU],0))),"")) | L58: =IF(OR($A58="",COUNT($D58:$F58)=0),"",SUM($D58:$F58)) | M58: =IF(OR($A58="",COUNT($G58:$J58)=0),"",SUM($G58:$J58)) | N58: =IF(OR($A58="",COUNT($E58,$H58,$J58,$K58)=0),"",SUM($E58,$H58,$J58,$K58)) | O58: =IF($A58="","",IF($D58="","PENDIENTE",SUM($D58:$K58))) | U58: =IF($A58="","",IF(COUNT($P58:$T58)=0,0,IF(AND(SUM($P58:$Q58)>0,NOT(ISNUMBER(IFERROR(IF(INDEX(tblProductos[Precio de venta actual],MATCH($A58,tblProductos[SKU],0))="","",INDEX(tblProductos[Precio de venta actual],MATCH($A58,tblProductos[SKU],0))),"")))),"PENDIENTE",IF(ISNUMBER(IFERROR(IF(INDEX(tblProductos[Precio de venta actual],MATCH($A58,tblProductos[SKU],0))="","",INDEX(tblProductos[Precio de venta actual],MATCH($A58,tblProductos[SKU],0))),"")),IFERROR(IF(INDEX(tblProductos[Precio de venta actual],MATCH($A58,tblProductos[SKU],0))="","",INDEX(tblProductos[Precio de venta actual],MATCH($A58,tblProductos[SKU],0))),""),0)*SUM($P58:$Q58)+SUM($R58:$T58)))) | V58: =IF($A58="","",IF(OR(NOT(ISNUMBER($O58)),NOT(ISNUMBER($U58))),"PENDIENTE",$O58+$U58))
B59: =IF($A59="","",IFERROR(IF(INDEX(tblProductos[Nombre del producto],MATCH($A59,tblProductos[SKU],0))="","",INDEX(tblProductos[Nombre del producto],MATCH($A59,tblProductos[SKU],0))),"")) | C59: =IF($A59="","",IFERROR(IF(INDEX(tblProductos[Categoría],MATCH($A59,tblProductos[SKU],0))="","",INDEX(tblProductos[Categoría],MATCH($A59,tblProductos[SKU],0))),"")) | L59: =IF(OR($A59="",COUNT($D59:$F59)=0),"",SUM($D59:$F59)) | M59: =IF(OR($A59="",COUNT($G59:$J59)=0),"",SUM($G59:$J59)) | N59: =IF(OR($A59="",COUNT($E59,$H59,$J59,$K59)=0),"",SUM($E59,$H59,$J59,$K59)) | O59: =IF($A59="","",IF($D59="","PENDIENTE",SUM($D59:$K59))) | U59: =IF($A59="","",IF(COUNT($P59:$T59)=0,0,IF(AND(SUM($P59:$Q59)>0,NOT(ISNUMBER(IFERROR(IF(INDEX(tblProductos[Precio de venta actual],MATCH($A59,tblProductos[SKU],0))="","",INDEX(tblProductos[Precio de venta actual],MATCH($A59,tblProductos[SKU],0))),"")))),"PENDIENTE",IF(ISNUMBER(IFERROR(IF(INDEX(tblProductos[Precio de venta actual],MATCH($A59,tblProductos[SKU],0))="","",INDEX(tblProductos[Precio de venta actual],MATCH($A59,tblProductos[SKU],0))),"")),IFERROR(IF(INDEX(tblProductos[Precio de venta actual],MATCH($A59,tblProductos[SKU],0))="","",INDEX(tblProductos[Precio de venta actual],MATCH($A59,tblProductos[SKU],0))),""),0)*SUM($P59:$Q59)+SUM($R59:$T59)))) | V59: =IF($A59="","",IF(OR(NOT(ISNUMBER($O59)),NOT(ISNUMBER($U59))),"PENDIENTE",$O59+$U59))
... B67: =IF($A67="","",IFERROR(IF(INDEX(tblProductos[Nombre del producto],MATCH($A67,tblProductos[SKU],0))="","",INDEX(tblProductos[Nombre del producto],MATCH($A67,tblProductos[SKU],0))),"")) | C67: =IF($A67="","",IFERROR(IF(INDEX(tblProductos[Categoría],MATCH($A67,tblProductos[SKU],0))="","",INDEX(tblProductos[Categoría],MATCH($A67,tblProductos[SKU],0))),"")) | L67: =IF(OR($A67="",COUNT($D67:$F67)=0),"",SUM($D67:$F67)) | M67: =IF(OR($A67="",COUNT($G67:$J67)=0),"",SUM($G67:$J67)) | N67: =IF(OR($A67="",COUNT($E67,$H67,$J67,$K67)=0),"",SUM($E67,$H67,$J67,$K67)) | O67: =IF($A67="","",IF($D67="","PENDIENTE",SUM($D67:$K67))) | U67: =IF($A67="","",IF(COUNT($P67:$T67)=0,0,IF(AND(SUM($P67:$Q67)>0,NOT(ISNUMBER(IFERROR(IF(INDEX(tblProductos[Precio de venta actual],MATCH($A67,tblProductos[SKU],0))="","",INDEX(tblProductos[Precio de venta actual],MATCH($A67,tblProductos[SKU],0))),"")))),"PENDIENTE",IF(ISNUMBER(IFERROR(IF(INDEX(tblProductos[Precio de venta actual],MATCH($A67,tblProductos[SKU],0))="","",INDEX(tblProductos[Precio de venta actual],MATCH($A67,tblProductos[SKU],0))),"")),IFERROR(IF(INDEX(tblProductos[Precio de venta actual],MATCH($A67,tblProductos[SKU],0))="","",INDEX(tblProductos[Precio de venta actual],MATCH($A67,tblProductos[SKU],0))),""),0)*SUM($P67:$Q67)+SUM($R67:$T67)))) | V67: =IF($A67="","",IF(OR(NOT(ISNUMBER($O67)),NOT(ISNUMBER($U67))),"PENDIENTE",$O67+$U67))

Sheet COMPRAS
A1: COMPRAS — Registro de adquisiciones
A2: Cada fila es una línea de compra. Alimenta automáticamente el INVENTARIO (entradas), el costo promedio ponderado y la CAJA (salidas de efectivo por lo efectivamente pagado).
A3: Costo total de adquisición = (cantidad × costo unitario) + transporte + impuestos + otros costos. Ese total —no solo el precio de factura— es el costo real que entra al inventario. La CAJA registra únicamente el «Monto pagado» en su «Fecha de pago»: comprar a crédito NO saca efectivo.
A6: ID de compra | B6: Fecha | C6: Proveedor | D6: SKU | E6: Producto | F6: Categoría | G6: Cantidad | H6: Costo unitario | I6: Costo total | J6: Transporte | K6: Impuestos / aranceles | L6: Otros costos | M6: Costo total de adquisición | N6: Costo unitario de adquisición | O6: Método de pago | P6: Estado de pago | Q6: Fecha de pago | R6: Monto pagado | S6: Saldo por pagar | T6: Observaciones | U6: ALERTA
A7: =IF(COUNTA($B7,$C7,$D7,$G7,$H7)=0,"","C-"&TEXT(ROW()-6,"0000")) | E7: =IF($D7="","",IFERROR(IF(INDEX(tblProductos[Nombre del producto],MATCH($D7,tblProductos[SKU],0))="","",INDEX(tblProductos[Nombre del producto],MATCH($D7,tblProductos[SKU],0))),"")) | F7: =IF($D7="","",IFERROR(IF(INDEX(tblProductos[Categoría],MATCH($D7,tblProductos[SKU],0))="","",INDEX(tblProductos[Categoría],MATCH($D7,tblProductos[SKU],0))),"")) | I7: =IF(OR($G7="",$H7=""),"",$G7*$H7) | M7: =IF(NOT(ISNUMBER($I7)),"",$I7+SUM($J7:$L7)) | N7: =IF(OR(NOT(ISNUMBER($M7)),NOT(ISNUMBER($G7)),$G7<=0),"",$M7/$G7) | S7: =IF(NOT(ISNUMBER($M7)),"",$M7-IF(ISNUMBER($R7),$R7,0)) | U7: =IF(COUNTA($B7,$C7,$D7,$G7,$H7)=0,"",IF(IF($B7=""," · Falta fecha","")&IF($C7=""," · Falta proveedor","")&IF(AND($D7<>"",COUNTIF(tblProductos[SKU],$D7)=0)," · SKU no existe","")&IF($D7=""," · Falta SKU","")&IF(OR($G7="",NOT(ISNUMBER($G7)),$G7<=0)," · Cantidad inválida","")&IF($H7=""," · Falta costo unitario","")&IF(AND($P7="Pagado",$Q7="")," · Pago sin fecha","")&IF(AND(ISNUMBER($R7),ISNUMBER($M7),$R7>N($M7)+0.01)," · Pagado > total","")&IF(AND(ISNUMBER($R7),$R7>0,$Q7="")," · Monto pagado sin fecha","")="","OK",MID(IF($B7=""," · Falta fecha","")&IF($C7=""," · Falta proveedor","")&IF(AND($D7<>"",COUNTIF(tblProductos[SKU],$D7)=0)," · SKU no existe","")&IF($D7=""," · Falta SKU","")&IF(OR($G7="",NOT(ISNUMBER($G7)),$G7<=0)," · Cantidad inválida","")&IF($H7=""," · Falta costo unitario","")&IF(AND($P7="Pagado",$Q7="")," · Pago sin fecha","")&IF(AND(ISNUMBER($R7),ISNUMBER($M7),$R7>N($M7)+0.01)," · Pagado > total","")&IF(AND(ISNUMBER($R7),$R7>0,$Q7="")," · Monto pagado sin fecha",""),4,900)))
A8: =IF(COUNTA($B8,$C8,$D8,$G8,$H8)=0,"","C-"&TEXT(ROW()-6,"0000")) | E8: =IF($D8="","",IFERROR(IF(INDEX(tblProductos[Nombre del producto],MATCH($D8,tblProductos[SKU],0))="","",INDEX(tblProductos[Nombre del producto],MATCH($D8,tblProductos[SKU],0))),"")) | F8: =IF($D8="","",IFERROR(IF(INDEX(tblProductos[Categoría],MATCH($D8,tblProductos[SKU],0))="","",INDEX(tblProductos[Categoría],MATCH($D8,tblProductos[SKU],0))),"")) | I8: =IF(OR($G8="",$H8=""),"",$G8*$H8) | M8: =IF(NOT(ISNUMBER($I8)),"",$I8+SUM($J8:$L8)) | N8: =IF(OR(NOT(ISNUMBER($M8)),NOT(ISNUMBER($G8)),$G8<=0),"",$M8/$G8) | S8: =IF(NOT(ISNUMBER($M8)),"",$M8-IF(ISNUMBER($R8),$R8,0)) | U8: =IF(COUNTA($B8,$C8,$D8,$G8,$H8)=0,"",IF(IF($B8=""," · Falta fecha","")&IF($C8=""," · Falta proveedor","")&IF(AND($D8<>"",COUNTIF(tblProductos[SKU],$D8)=0)," · SKU no existe","")&IF($D8=""," · Falta SKU","")&IF(OR($G8="",NOT(ISNUMBER($G8)),$G8<=0)," · Cantidad inválida","")&IF($H8=""," · Falta costo unitario","")&IF(AND($P8="Pagado",$Q8="")," · Pago sin fecha","")&IF(AND(ISNUMBER($R8),ISNUMBER($M8),$R8>N($M8)+0.01)," · Pagado > total","")&IF(AND(ISNUMBER($R8),$R8>0,$Q8="")," · Monto pagado sin fecha","")="","OK",MID(IF($B8=""," · Falta fecha","")&IF($C8=""," · Falta proveedor","")&IF(AND($D8<>"",COUNTIF(tblProductos[SKU],$D8)=0)," · SKU no existe","")&IF($D8=""," · Falta SKU","")&IF(OR($G8="",NOT(ISNUMBER($G8)),$G8<=0)," · Cantidad inválida","")&IF($H8=""," · Falta costo unitario","")&IF(AND($P8="Pagado",$Q8="")," · Pago sin fecha","")&IF(AND(ISNUMBER($R8),ISNUMBER($M8),$R8>N($M8)+0.01)," · Pagado > total","")&IF(AND(ISNUMBER($R8),$R8>0,$Q8="")," · Monto pagado sin fecha",""),4,900)))
A9: =IF(COUNTA($B9,$C9,$D9,$G9,$H9)=0,"","C-"&TEXT(ROW()-6,"0000")) | E9: =IF($D9="","",IFERROR(IF(INDEX(tblProductos[Nombre del producto],MATCH($D9,tblProductos[SKU],0))="","",INDEX(tblProductos[Nombre del producto],MATCH($D9,tblProductos[SKU],0))),"")) | F9: =IF($D9="","",IFERROR(IF(INDEX(tblProductos[Categoría],MATCH($D9,tblProductos[SKU],0))="","",INDEX(tblProductos[Categoría],MATCH($D9,tblProductos[SKU],0))),"")) | I9: =IF(OR($G9="",$H9=""),"",$G9*$H9) | M9: =IF(NOT(ISNUMBER($I9)),"",$I9+SUM($J9:$L9)) | N9: =IF(OR(NOT(ISNUMBER($M9)),NOT(ISNUMBER($G9)),$G9<=0),"",$M9/$G9) | S9: =IF(NOT(ISNUMBER($M9)),"",$M9-IF(ISNUMBER($R9),$R9,0)) | U9: =IF(COUNTA($B9,$C9,$D9,$G9,$H9)=0,"",IF(IF($B9=""," · Falta fecha","")&IF($C9=""," · Falta proveedor","")&IF(AND($D9<>"",COUNTIF(tblProductos[SKU],$D9)=0)," · SKU no existe","")&IF($D9=""," · Falta SKU","")&IF(OR($G9="",NOT(ISNUMBER($G9)),$G9<=0)," · Cantidad inválida","")&IF($H9=""," · Falta costo unitario","")&IF(AND($P9="Pagado",$Q9="")," · Pago sin fecha","")&IF(AND(ISNUMBER($R9),ISNUMBER($M9),$R9>N($M9)+0.01)," · Pagado > total","")&IF(AND(ISNUMBER($R9),$R9>0,$Q9="")," · Monto pagado sin fecha","")="","OK",MID(IF($B9=""," · Falta fecha","")&IF($C9=""," · Falta proveedor","")&IF(AND($D9<>"",COUNTIF(tblProductos[SKU],$D9)=0)," · SKU no existe","")&IF($D9=""," · Falta SKU","")&IF(OR($G9="",NOT(ISNUMBER($G9)),$G9<=0)," · Cantidad inválida","")&IF($H9=""," · Falta costo unitario","")&IF(AND($P9="Pagado",$Q9="")," · Pago sin fecha","")&IF(AND(ISNUMBER($R9),ISNUMBER($M9),$R9>N($M9)+0.01)," · Pagado > total","")&IF(AND(ISNUMBER($R9),$R9>0,$Q9="")," · Monto pagado sin fecha",""),4,900)))
A10: =IF(COUNTA($B10,$C10,$D10,$G10,$H10)=0,"","C-"&TEXT(ROW()-6,"0000")) | E10: =IF($D10="","",IFERROR(IF(INDEX(tblProductos[Nombre del producto],MATCH($D10,tblProductos[SKU],0))="","",INDEX(tblProductos[Nombre del producto],MATCH($D10,tblProductos[SKU],0))),"")) | F10: =IF($D10="","",IFERROR(IF(INDEX(tblProductos[Categoría],MATCH($D10,tblProductos[SKU],0))="","",INDEX(tblProductos[Categoría],MATCH($D10,tblProductos[SKU],0))),"")) | I10: =IF(OR($G10="",$H10=""),"",$G10*$H10) | M10: =IF(NOT(ISNUMBER($I10)),"",$I10+SUM($J10:$L10)) | N10: =IF(OR(NOT(ISNUMBER($M10)),NOT(ISNUMBER($G10)),$G10<=0),"",$M10/$G10) | S10: =IF(NOT(ISNUMBER($M10)),"",$M10-IF(ISNUMBER($R10),$R10,0)) | U10: =IF(COUNTA($B10,$C10,$D10,$G10,$H10)=0,"",IF(IF($B10=""," · Falta fecha","")&IF($C10=""," · Falta proveedor","")&IF(AND($D10<>"",COUNTIF(tblProductos[SKU],$D10)=0)," · SKU no existe","")&IF($D10=""," · Falta SKU","")&IF(OR($G10="",NOT(ISNUMBER($G10)),$G10<=0)," · Cantidad inválida","")&IF($H10=""," · Falta costo unitario","")&IF(AND($P10="Pagado",$Q10="")," · Pago sin fecha","")&IF(AND(ISNUMBER($R10),ISNUMBER($M10),$R10>N($M10)+0.01)," · Pagado > total","")&IF(AND(ISNUMBER($R10),$R10>0,$Q10="")," · Monto pagado sin fecha","")="","OK",MID(IF($B10=""," · Falta fecha","")&IF($C10=""," · Falta proveedor","")&IF(AND($D10<>"",COUNTIF(tblProductos[SKU],$D10)=0)," · SKU no existe","")&IF($D10=""," · Falta SKU","")&IF(OR($G10="",NOT(ISNUMBER($G10)),$G10<=0)," · Cantidad inválida","")&IF($H10=""," · Falta costo unitario","")&IF(AND($P10="Pagado",$Q10="")," · Pago sin fecha","")&IF(AND(ISNUMBER($R10),ISNUMBER($M10),$R10>N($M10)+0.01)," · Pagado > total","")&IF(AND(ISNUMBER($R10),$R10>0,$Q10="")," · Monto pagado sin fecha",""),4,900)))
A11: =IF(COUNTA($B11,$C11,$D11,$G11,$H11)=0,"","C-"&TEXT(ROW()-6,"0000")) | E11: =IF($D11="","",IFERROR(IF(INDEX(tblProductos[Nombre del producto],MATCH($D11,tblProductos[SKU],0))="","",INDEX(tblProductos[Nombre del producto],MATCH($D11,tblProductos[SKU],0))),"")) | F11: =IF($D11="","",IFERROR(IF(INDEX(tblProductos[Categoría],MATCH($D11,tblProductos[SKU],0))="","",INDEX(tblProductos[Categoría],MATCH($D11,tblProductos[SKU],0))),"")) | I11: =IF(OR($G11="",$H11=""),"",$G11*$H11) | M11: =IF(NOT(ISNUMBER($I11)),"",$I11+SUM($J11:$L11)) | N11: =IF(OR(NOT(ISNUMBER($M11)),NOT(ISNUMBER($G11)),$G11<=0),"",$M11/$G11) | S11: =IF(NOT(ISNUMBER($M11)),"",$M11-IF(ISNUMBER($R11),$R11,0)) | U11: =IF(COUNTA($B11,$C11,$D11,$G11,$H11)=0,"",IF(IF($B11=""," · Falta fecha","")&IF($C11=""," · Falta proveedor","")&IF(AND($D11<>"",COUNTIF(tblProductos[SKU],$D11)=0)," · SKU no existe","")&IF($D11=""," · Falta SKU","")&IF(OR($G11="",NOT(ISNUMBER($G11)),$G11<=0)," · Cantidad inválida","")&IF($H11=""," · Falta costo unitario","")&IF(AND($P11="Pagado",$Q11="")," · Pago sin fecha","")&IF(AND(ISNUMBER($R11),ISNUMBER($M11),$R11>N($M11)+0.01)," · Pagado > total","")&IF(AND(ISNUMBER($R11),$R11>0,$Q11="")," · Monto pagado sin fecha","")="","OK",MID(IF($B11=""," · Falta fecha","")&IF($C11=""," · Falta proveedor","")&IF(AND($D11<>"",COUNTIF(tblProductos[SKU],$D11)=0)," · SKU no existe","")&IF($D11=""," · Falta SKU","")&IF(OR($G11="",NOT(ISNUMBER($G11)),$G11<=0)," · Cantidad inválida","")&IF($H11=""," · Falta costo unitario","")&IF(AND($P11="Pagado",$Q11="")," · Pago sin fecha","")&IF(AND(ISNUMBER($R11),ISNUMBER($M11),$R11>N($M11)+0.01)," · Pagado > total","")&IF(AND(ISNUMBER($R11),$R11>0,$Q11="")," · Monto pagado sin fecha",""),4,900)))
A12: =IF(COUNTA($B12,$C12,$D12,$G12,$H12)=0,"","C-"&TEXT(ROW()-6,"0000")) | E12: =IF($D12="","",IFERROR(IF(INDEX(tblProductos[Nombre del producto],MATCH($D12,tblProductos[SKU],0))="","",INDEX(tblProductos[Nombre del producto],MATCH($D12,tblProductos[SKU],0))),"")) | F12: =IF($D12="","",IFERROR(IF(INDEX(tblProductos[Categoría],MATCH($D12,tblProductos[SKU],0))="","",INDEX(tblProductos[Categoría],MATCH($D12,tblProductos[SKU],0))),"")) | I12: =IF(OR($G12="",$H12=""),"",$G12*$H12) | M12: =IF(NOT(ISNUMBER($I12)),"",$I12+SUM($J12:$L12)) | N12: =IF(OR(NOT(ISNUMBER($M12)),NOT(ISNUMBER($G12)),$G12<=0),"",$M12/$G12) | S12: =IF(NOT(ISNUMBER($M12)),"",$M12-IF(ISNUMBER($R12),$R12,0)) | U12: =IF(COUNTA($B12,$C12,$D12,$G12,$H12)=0,"",IF(IF($B12=""," · Falta fecha","")&IF($C12=""," · Falta proveedor","")&IF(AND($D12<>"",COUNTIF(tblProductos[SKU],$D12)=0)," · SKU no existe","")&IF($D12=""," · Falta SKU","")&IF(OR($G12="",NOT(ISNUMBER($G12)),$G12<=0)," · Cantidad inválida","")&IF($H12=""," · Falta costo unitario","")&IF(AND($P12="Pagado",$Q12="")," · Pago sin fecha","")&IF(AND(ISNUMBER($R12),ISNUMBER($M12),$R12>N($M12)+0.01)," · Pagado > total","")&IF(AND(ISNUMBER($R12),$R12>0,$Q12="")," · Monto pagado sin fecha","")="","OK",MID(IF($B12=""," · Falta fecha","")&IF($C12=""," · Falta proveedor","")&IF(AND($D12<>"",COUNTIF(tblProductos[SKU],$D12)=0)," · SKU no existe","")&IF($D12=""," · Falta SKU","")&IF(OR($G12="",NOT(ISNUMBER($G12)),$G12<=0)," · Cantidad inválida","")&IF($H12=""," · Falta costo unitario","")&IF(AND($P12="Pagado",$Q12="")," · Pago sin fecha","")&IF(AND(ISNUMBER($R12),ISNUMBER($M12),$R12>N($M12)+0.01)," · Pagado > total","")&IF(AND(ISNUMBER($R12),$R12>0,$Q12="")," · Monto pagado sin fecha",""),4,900)))
A13: =IF(COUNTA($B13,$C13,$D13,$G13,$H13)=0,"","C-"&TEXT(ROW()-6,"0000")) | E13: =IF($D13="","",IFERROR(IF(INDEX(tblProductos[Nombre del producto],MATCH($D13,tblProductos[SKU],0))="","",INDEX(tblProductos[Nombre del producto],MATCH($D13,tblProductos[SKU],0))),"")) | F13: =IF($D13="","",IFERROR(IF(INDEX(tblProductos[Categoría],MATCH($D13,tblProductos[SKU],0))="","",INDEX(tblProductos[Categoría],MATCH($D13,tblProductos[SKU],0))),"")) | I13: =IF(OR($G13="",$H13=""),"",$G13*$H13) | M13: =IF(NOT(ISNUMBER($I13)),"",$I13+SUM($J13:$L13)) | N13: =IF(OR(NOT(ISNUMBER($M13)),NOT(ISNUMBER($G13)),$G13<=0),"",$M13/$G13) | S13: =IF(NOT(ISNUMBER($M13)),"",$M13-IF(ISNUMBER($R13),$R13,0)) | U13: =IF(COUNTA($B13,$C13,$D13,$G13,$H13)=0,"",IF(IF($B13=""," · Falta fecha","")&IF($C13=""," · Falta proveedor","")&IF(AND($D13<>"",COUNTIF(tblProductos[SKU],$D13)=0)," · SKU no existe","")&IF($D13=""," · Falta SKU","")&IF(OR($G13="",NOT(ISNUMBER($G13)),$G13<=0)," · Cantidad inválida","")&IF($H13=""," · Falta costo unitario","")&IF(AND($P13="Pagado",$Q13="")," · Pago sin fecha","")&IF(AND(ISNUMBER($R13),ISNUMBER($M13),$R13>N($M13)+0.01)," · Pagado > total","")&IF(AND(ISNUMBER($R13),$R13>0,$Q13="")," · Monto pagado sin fecha","")="","OK",MID(IF($B13=""," · Falta fecha","")&IF($C13=""," · Falta proveedor","")&IF(AND($D13<>"",COUNTIF(tblProductos[SKU],$D13)=0)," · SKU no existe","")&IF($D13=""," · Falta SKU","")&IF(OR($G13="",NOT(ISNUMBER($G13)),$G13<=0)," · Cantidad inválida","")&IF($H13=""," · Falta costo unitario","")&IF(AND($P13="Pagado",$Q13="")," · Pago sin fecha","")&IF(AND(ISNUMBER($R13),ISNUMBER($M13),$R13>N($M13)+0.01)," · Pagado > total","")&IF(AND(ISNUMBER($R13),$R13>0,$Q13="")," · Monto pagado sin fecha",""),4,900)))
A14: =IF(COUNTA($B14,$C14,$D14,$G14,$H14)=0,"","C-"&TEXT(ROW()-6,"0000")) | E14: =IF($D14="","",IFERROR(IF(INDEX(tblProductos[Nombre del producto],MATCH($D14,tblProductos[SKU],0))="","",INDEX(tblProductos[Nombre del producto],MATCH($D14,tblProductos[SKU],0))),"")) | F14: =IF($D14="","",IFERROR(IF(INDEX(tblProductos[Categoría],MATCH($D14,tblProductos[SKU],0))="","",INDEX(tblProductos[Categoría],MATCH($D14,tblProductos[SKU],0))),"")) | I14: =IF(OR($G14="",$H14=""),"",$G14*$H14) | M14: =IF(NOT(ISNUMBER($I14)),"",$I14+SUM($J14:$L14)) | N14: =IF(OR(NOT(ISNUMBER($M14)),NOT(ISNUMBER($G14)),$G14<=0),"",$M14/$G14) | S14: =IF(NOT(ISNUMBER($M14)),"",$M14-IF(ISNUMBER($R14),$R14,0)) | U14: =IF(COUNTA($B14,$C14,$D14,$G14,$H14)=0,"",IF(IF($B14=""," · Falta fecha","")&IF($C14=""," · Falta proveedor","")&IF(AND($D14<>"",COUNTIF(tblProductos[SKU],$D14)=0)," · SKU no existe","")&IF($D14=""," · Falta SKU","")&IF(OR($G14="",NOT(ISNUMBER($G14)),$G14<=0)," · Cantidad inválida","")&IF($H14=""," · Falta costo unitario","")&IF(AND($P14="Pagado",$Q14="")," · Pago sin fecha","")&IF(AND(ISNUMBER($R14),ISNUMBER($M14),$R14>N($M14)+0.01)," · Pagado > total","")&IF(AND(ISNUMBER($R14),$R14>0,$Q14="")," · Monto pagado sin fecha","")="","OK",MID(IF($B14=""," · Falta fecha","")&IF($C14=""," · Falta proveedor","")&IF(AND($D14<>"",COUNTIF(tblProductos[SKU],$D14)=0)," · SKU no existe","")&IF($D14=""," · Falta SKU","")&IF(OR($G14="",NOT(ISNUMBER($G14)),$G14<=0)," · Cantidad inválida","")&IF($H14=""," · Falta costo unitario","")&IF(AND($P14="Pagado",$Q14="")," · Pago sin fecha","")&IF(AND(ISNUMBER($R14),ISNUMBER($M14),$R14>N($M14)+0.01)," · Pagado > total","")&IF(AND(ISNUMBER($R14),$R14>0,$Q14="")," · Monto pagado sin fecha",""),4,900)))
A15: =IF(COUNTA($B15,$C15,$D15,$G15,$H15)=0,"","C-"&TEXT(ROW()-6,"0000")) | E15: =IF($D15="","",IFERROR(IF(INDEX(tblProductos[Nombre del producto],MATCH($D15,tblProductos[SKU],0))="","",INDEX(tblProductos[Nombre del producto],MATCH($D15,tblProductos[SKU],0))),"")) | F15: =IF($D15="","",IFERROR(IF(INDEX(tblProductos[Categoría],MATCH($D15,tblProductos[SKU],0))="","",INDEX(tblProductos[Categoría],MATCH($D15,tblProductos[SKU],0))),"")) | I15: =IF(OR($G15="",$H15=""),"",$G15*$H15) | M15: =IF(NOT(ISNUMBER($I15)),"",$I15+SUM($J15:$L15)) | N15: =IF(OR(NOT(ISNUMBER($M15)),NOT(ISNUMBER($G15)),$G15<=0),"",$M15/$G15) | S15: =IF(NOT(ISNUMBER($M15)),"",$M15-IF(ISNUMBER($R15),$R15,0)) | U15: =IF(COUNTA($B15,$C15,$D15,$G15,$H15)=0,"",IF(IF($B15=""," · Falta fecha","")&IF($C15=""," · Falta proveedor","")&IF(AND($D15<>"",COUNTIF(tblProductos[SKU],$D15)=0)," · SKU no existe","")&IF($D15=""," · Falta SKU","")&IF(OR($G15="",NOT(ISNUMBER($G15)),$G15<=0)," · Cantidad inválida","")&IF($H15=""," · Falta costo unitario","")&IF(AND($P15="Pagado",$Q15="")," · Pago sin fecha","")&IF(AND(ISNUMBER($R15),ISNUMBER($M15),$R15>N($M15)+0.01)," · Pagado > total","")&IF(AND(ISNUMBER($R15),$R15>0,$Q15="")," · Monto pagado sin fecha","")="","OK",MID(IF($B15=""," · Falta fecha","")&IF($C15=""," · Falta proveedor","")&IF(AND($D15<>"",COUNTIF(tblProductos[SKU],$D15)=0)," · SKU no existe","")&IF($D15=""," · Falta SKU","")&IF(OR($G15="",NOT(ISNUMBER($G15)),$G15<=0)," · Cantidad inválida","")&IF($H15=""," · Falta costo unitario","")&IF(AND($P15="Pagado",$Q15="")," · Pago sin fecha","")&IF(AND(ISNUMBER($R15),ISNUMBER($M15),$R15>N($M15)+0.01)," · Pagado > total","")&IF(AND(ISNUMBER($R15),$R15>0,$Q15="")," · Monto pagado sin fecha",""),4,900)))
A16: =IF(COUNTA($B16,$C16,$D16,$G16,$H16)=0,"","C-"&TEXT(ROW()-6,"0000")) | E16: =IF($D16="","",IFERROR(IF(INDEX(tblProductos[Nombre del producto],MATCH($D16,tblProductos[SKU],0))="","",INDEX(tblProductos[Nombre del producto],MATCH($D16,tblProductos[SKU],0))),"")) | F16: =IF($D16="","",IFERROR(IF(INDEX(tblProductos[Categoría],MATCH($D16,tblProductos[SKU],0))="","",INDEX(tblProductos[Categoría],MATCH($D16,tblProductos[SKU],0))),"")) | I16: =IF(OR($G16="",$H16=""),"",$G16*$H16) | M16: =IF(NOT(ISNUMBER($I16)),"",$I16+SUM($J16:$L16)) | N16: =IF(OR(NOT(ISNUMBER($M16)),NOT(ISNUMBER($G16)),$G16<=0),"",$M16/$G16) | S16: =IF(NOT(ISNUMBER($M16)),"",$M16-IF(ISNUMBER($R16),$R16,0)) | U16: =IF(COUNTA($B16,$C16,$D16,$G16,$H16)=0,"",IF(IF($B16=""," · Falta fecha","")&IF($C16=""," · Falta proveedor","")&IF(AND($D16<>"",COUNTIF(tblProductos[SKU],$D16)=0)," · SKU no existe","")&IF($D16=""," · Falta SKU","")&IF(OR($G16="",NOT(ISNUMBER($G16)),$G16<=0)," · Cantidad inválida","")&IF($H16=""," · Falta costo unitario","")&IF(AND($P16="Pagado",$Q16="")," · Pago sin fecha","")&IF(AND(ISNUMBER($R16),ISNUMBER($M16),$R16>N($M16)+0.01)," · Pagado > total","")&IF(AND(ISNUMBER($R16),$R16>0,$Q16="")," · Monto pagado sin fecha","")="","OK",MID(IF($B16=""," · Falta fecha","")&IF($C16=""," · Falta proveedor","")&IF(AND($D16<>"",COUNTIF(tblProductos[SKU],$D16)=0)," · SKU no existe","")&IF($D16=""," · Falta SKU","")&IF(OR($G16="",NOT(ISNUMBER($G16)),$G16<=0)," · Cantidad inválida","")&IF($H16=""," · Falta costo unitario","")&IF(AND($P16="Pagado",$Q16="")," · Pago sin fecha","")&IF(AND(ISNUMBER($R16),ISNUMBER($M16),$R16>N($M16)+0.01)," · Pagado > total","")&IF(AND(ISNUMBER($R16),$R16>0,$Q16="")," · Monto pagado sin fecha",""),4,900)))
A17: =IF(COUNTA($B17,$C17,$D17,$G17,$H17)=0,"","C-"&TEXT(ROW()-6,"0000")) | E17: =IF($D17="","",IFERROR(IF(INDEX(tblProductos[Nombre del producto],MATCH($D17,tblProductos[SKU],0))="","",INDEX(tblProductos[Nombre del producto],MATCH($D17,tblProductos[SKU],0))),"")) | F17: =IF($D17="","",IFERROR(IF(INDEX(tblProductos[Categoría],MATCH($D17,tblProductos[SKU],0))="","",INDEX(tblProductos[Categoría],MATCH($D17,tblProductos[SKU],0))),"")) | I17: =IF(OR($G17="",$H17=""),"",$G17*$H17) | M17: =IF(NOT(ISNUMBER($I17)),"",$I17+SUM($J17:$L17)) | N17: =IF(OR(NOT(ISNUMBER($M17)),NOT(ISNUMBER($G17)),$G17<=0),"",$M17/$G17) | S17: =IF(NOT(ISNUMBER($M17)),"",$M17-IF(ISNUMBER($R17),$R17,0)) | U17: =IF(COUNTA($B17,$C17,$D17,$G17,$H17)=0,"",IF(IF($B17=""," · Falta fecha","")&IF($C17=""," · Falta proveedor","")&IF(AND($D17<>"",COUNTIF(tblProductos[SKU],$D17)=0)," · SKU no existe","")&IF($D17=""," · Falta SKU","")&IF(OR($G17="",NOT(ISNUMBER($G17)),$G17<=0)," · Cantidad inválida","")&IF($H17=""," · Falta costo unitario","")&IF(AND($P17="Pagado",$Q17="")," · Pago sin fecha","")&IF(AND(ISNUMBER($R17),ISNUMBER($M17),$R17>N($M17)+0.01)," · Pagado > total","")&IF(AND(ISNUMBER($R17),$R17>0,$Q17="")," · Monto pagado sin fecha","")="","OK",MID(IF($B17=""," · Falta fecha","")&IF($C17=""," · Falta proveedor","")&IF(AND($D17<>"",COUNTIF(tblProductos[SKU],$D17)=0)," · SKU no existe","")&IF($D17=""," · Falta SKU","")&IF(OR($G17="",NOT(ISNUMBER($G17)),$G17<=0)," · Cantidad inválida","")&IF($H17=""," · Falta costo unitario","")&IF(AND($P17="Pagado",$Q17="")," · Pago sin fecha","")&IF(AND(ISNUMBER($R17),ISNUMBER($M17),$R17>N($M17)+0.01)," · Pagado > total","")&IF(AND(ISNUMBER($R17),$R17>0,$Q17="")," · Monto pagado sin fecha",""),4,900)))
A18: =IF(COUNTA($B18,$C18,$D18,$G18,$H18)=0,"","C-"&TEXT(ROW()-6,"0000")) | E18: =IF($D18="","",IFERROR(IF(INDEX(tblProductos[Nombre del producto],MATCH($D18,tblProductos[SKU],0))="","",INDEX(tblProductos[Nombre del producto],MATCH($D18,tblProductos[SKU],0))),"")) | F18: =IF($D18="","",IFERROR(IF(INDEX(tblProductos[Categoría],MATCH($D18,tblProductos[SKU],0))="","",INDEX(tblProductos[Categoría],MATCH($D18,tblProductos[SKU],0))),"")) | I18: =IF(OR($G18="",$H18=""),"",$G18*$H18) | M18: =IF(NOT(ISNUMBER($I18)),"",$I18+SUM($J18:$L18)) | N18: =IF(OR(NOT(ISNUMBER($M18)),NOT(ISNUMBER($G18)),$G18<=0),"",$M18/$G18) | S18: =IF(NOT(ISNUMBER($M18)),"",$M18-IF(ISNUMBER($R18),$R18,0)) | U18: =IF(COUNTA($B18,$C18,$D18,$G18,$H18)=0,"",IF(IF($B18=""," · Falta fecha","")&IF($C18=""," · Falta proveedor","")&IF(AND($D18<>"",COUNTIF(tblProductos[SKU],$D18)=0)," · SKU no existe","")&IF($D18=""," · Falta SKU","")&IF(OR($G18="",NOT(ISNUMBER($G18)),$G18<=0)," · Cantidad inválida","")&IF($H18=""," · Falta costo unitario","")&IF(AND($P18="Pagado",$Q18="")," · Pago sin fecha","")&IF(AND(ISNUMBER($R18),ISNUMBER($M18),$R18>N($M18)+0.01)," · Pagado > total","")&IF(AND(ISNUMBER($R18),$R18>0,$Q18="")," · Monto pagado sin fecha","")="","OK",MID(IF($B18=""," · Falta fecha","")&IF($C18=""," · Falta proveedor","")&IF(AND($D18<>"",COUNTIF(tblProductos[SKU],$D18)=0)," · SKU no existe","")&IF($D18=""," · Falta SKU","")&IF(OR($G18="",NOT(ISNUMBER($G18)),$G18<=0)," · Cantidad inválida","")&IF($H18=""," · Falta costo unitario","")&IF(AND($P18="Pagado",$Q18="")," · Pago sin fecha","")&IF(AND(ISNUMBER($R18),ISNUMBER($M18),$R18>N($M18)+0.01)," · Pagado > total","")&IF(AND(ISNUMBER($R18),$R18>0,$Q18="")," · Monto pagado sin fecha",""),4,900)))
... A306: =IF(COUNTA($B306,$C306,$D306,$G306,$H306)=0,"","C-"&TEXT(ROW()-6,"0000")) | E306: =IF($D306="","",IFERROR(IF(INDEX(tblProductos[Nombre del producto],MATCH($D306,tblProductos[SKU],0))="","",INDEX(tblProductos[Nombre del producto],MATCH($D306,tblProductos[SKU],0))),"")) | F306: =IF($D306="","",IFERROR(IF(INDEX(tblProductos[Categoría],MATCH($D306,tblProductos[SKU],0))="","",INDEX(tblProductos[Categoría],MATCH($D306,tblProductos[SKU],0))),"")) | I306: =IF(OR($G306="",$H306=""),"",$G306*$H306) | M306: =IF(NOT(ISNUMBER($I306)),"",$I306+SUM($J306:$L306)) | N306: =IF(OR(NOT(ISNUMBER($M306)),NOT(ISNUMBER($G306)),$G306<=0),"",$M306/$G306) | S306: =IF(NOT(ISNUMBER($M306)),"",$M306-IF(ISNUMBER($R306),$R306,0)) | U306: =IF(COUNTA($B306,$C306,$D306,$G306,$H306)=0,"",IF(IF($B306=""," · Falta fecha","")&IF($C306=""," · Falta proveedor","")&IF(AND($D306<>"",COUNTIF(tblProductos[SKU],$D306)=0)," · SKU no existe","")&IF($D306=""," · Falta SKU","")&IF(OR($G306="",NOT(ISNUMBER($G306)),$G306<=0)," · Cantidad inválida","")&IF($H306=""," · Falta costo unitario","")&IF(AND($P306="Pagado",$Q306="")," · Pago sin fecha","")&IF(AND(ISNUMBER($R306),ISNUMBER($M306),$R306>N($M306)+0.01)," · Pagado > total","")&IF(AND(ISNUMBER($R306),$R306>0,$Q306="")," · Monto pagado sin fecha","")="","OK",MID(IF($B306=""," · Falta fecha","")&IF($C306=""," · Falta proveedor","")&IF(AND($D306<>"",COUNTIF(tblProductos[SKU],$D306)=0)," · SKU no existe","")&IF($D306=""," · Falta SKU","")&IF(OR($G306="",NOT(ISNUMBER($G306)),$G306<=0)," · Cantidad inválida","")&IF($H306=""," · Falta costo unitario","")&IF(AND($P306="Pagado",$Q306="")," · Pago sin fecha","")&IF(AND(ISNUMBER($R306),ISNUMBER($M306),$R306>N($M306)+0.01)," · Pagado > total","")&IF(AND(ISNUMBER($R306),$R306>0,$Q306="")," · Monto pagado sin fecha",""),4,900)))

Sheet INVENTARIO
A1: INVENTARIO — Existencias y valorización
A2: Hoja calculada: Stock actual = Stock inicial + Compras − Ventas + Ajustes. Solo se editan «Stock inicial» y «Ajustes» (mermas, devoluciones, conteos físicos).
A3: Costo unitario aplicado = costo promedio ponderado de las compras registradas; si aún no hay compras, se usa el COSTO REAL UNITARIO de la hoja COSTOS. Si no existe ninguno de los dos, el inventario queda PENDIENTE de valorizar (nunca se inventa un costo).
A6: SKU | B6: Producto | C6: Categoría | D6: Presentación | E6: Stock inicial | F6: Compras | G6: Ventas | H6: Ajustes | I6: Stock actual | J6: Stock mínimo | K6: Stock máximo | L6: Costo unitario estándar | M6: Costo promedio ponderado | N6: Costo unitario aplicado | O6: Método de costo | P6: VALOR DEL INVENTARIO | Q6: Precio de venta actual | R6: Valor a precio de venta | S6: ESTADO | T6: Unidades sugeridas a comprar | U6: Última compra | V6: Última venta | W6: Unidades vendidas (últimos 30 días) | X6: Cobertura estimada (días)
A7: =IFERROR(IF(INDEX(tblProductos[SKU],ROW()-6)="","",INDEX(tblProductos[SKU],ROW()-6)),"") | B7: =IF($A7="","",IFERROR(IF(INDEX(tblProductos[Nombre del producto],MATCH($A7,tblProductos[SKU],0))="","",INDEX(tblProductos[Nombre del producto],MATCH($A7,tblProductos[SKU],0))),"")) | C7: =IF($A7="","",IFERROR(IF(INDEX(tblProductos[Categoría],MATCH($A7,tblProductos[SKU],0))="","",INDEX(tblProductos[Categoría],MATCH($A7,tblProductos[SKU],0))),"")) | D7: =IF($A7="","",IFERROR(IF(INDEX(tblProductos[Presentación],MATCH($A7,tblProductos[SKU],0))="","",INDEX(tblProductos[Presentación],MATCH($A7,tblProductos[SKU],0))),"")) | F7: =IF($A7="","",SUMIFS(tblCompras[Cantidad],tblCompras[SKU],$A7)) | G7: =IF($A7="","",SUMIFS(tblVentas[Unidades efectivas],tblVentas[SKU],$A7)) | I7: =IF($A7="","",IF(ISNUMBER($E7),$E7,0)+$F7-$G7+IF(ISNUMBER($H7),$H7,0)) | J7: =IF($A7="","",IFERROR(IF(INDEX(tblProductos[Stock mínimo],MATCH($A7,tblProductos[SKU],0))="","",INDEX(tblProductos[Stock mínimo],MATCH($A7,tblProductos[SKU],0))),"")) | K7: =IF($A7="","",IFERROR(IF(INDEX(tblProductos[Stock máximo],MATCH($A7,tblProductos[SKU],0))="","",INDEX(tblProductos[Stock máximo],MATCH($A7,tblProductos[SKU],0))),"")) | L7: =IF($A7="","",IFERROR(IF(INDEX(tblCostos[COSTO REAL UNITARIO],MATCH($A7,tblCostos[SKU],0))="","PENDIENTE",INDEX(tblCostos[COSTO REAL UNITARIO],MATCH($A7,tblCostos[SKU],0))),"PENDIENTE")) | M7: =IF($A7="","",IF(SUMIFS(tblCompras[Cantidad],tblCompras[SKU],$A7)<=0,"",SUMIFS(tblCompras[Costo total de adquisición],tblCompras[SKU],$A7)/SUMIFS(tblCompras[Cantidad],tblCompras[SKU],$A7))) | N7: =IF($A7="","",IF(ISNUMBER($M7),$M7,IF(ISNUMBER($L7),$L7,""))) | O7: =IF($A7="","",IF(ISNUMBER($M7),"Promedio ponderado",IF(ISNUMBER($L7),"Costo estándar","PENDIENTE"))) | P7: =IF($A7="","",IF(OR(NOT(ISNUMBER($I7)),NOT(ISNUMBER($N7))),"PENDIENTE",$I7*$N7)) | Q7: =IF($A7="","",IFERROR(IF(INDEX(tblProductos[Precio de venta actual],MATCH($A7,tblProductos[SKU],0))="","PENDIENTE",INDEX(tblProductos[Precio de venta actual],MATCH($A7,tblProductos[SKU],0))),"PENDIENTE")) | R7: =IF($A7="","",IF(OR(NOT(ISNUMBER($I7)),NOT(ISNUMBER($Q7))),"PENDIENTE",$I7*$Q7)) | S7: =IF($A7="","",IF(NOT(ISNUMBER($I7)),"ERROR",IF($I7<0,"ERROR",IF($I7=0,"AGOTADO",IF(AND(ISNUMBER($J7),$I7<=N($J7)*MAX(1,IF(ISNUMBER(PAR_ALERTA_STOCK),PAR_ALERTA_STOCK,1))),"REABASTECER","OK"))))) | T7: =IF($A7="","",IF(OR(NOT(ISNUMBER($I7)),NOT(ISNUMBER($K7))),"",IF(OR($S7="REABASTECER",$S7="AGOTADO"),MAX(0,$K7-$I7),0))) | U7: =IF($A7="","",IFERROR(IF(SUMPRODUCT(MAX((tblCompras[SKU]=$A7)*(tblCompras[Fecha])))=0,"",SUMPRODUCT(MAX((tblCompras[SKU]=$A7)*(tblCompras[Fecha])))),"")) | V7: =IF($A7="","",IFERROR(IF(SUMPRODUCT(MAX((tblVentas[SKU]=$A7)*(tblVentas[Fecha])))=0,"",SUMPRODUCT(MAX((tblVentas[SKU]=$A7)*(tblVentas[Fecha])))),"")) | W7: =IF($A7="","",SUMIFS(tblVentas[Unidades efectivas],tblVentas[SKU],$A7,tblVentas[Fecha],">="&TODAY()-30,tblVentas[Fecha],"<="&TODAY())) | X7: =IF($A7="","",IF(OR(NOT(ISNUMBER($I7)),NOT(ISNUMBER($W7)),$W7<=0),"",ROUND($I7/($W7/30),0)))
A8: =IFERROR(IF(INDEX(tblProductos[SKU],ROW()-6)="","",INDEX(tblProductos[SKU],ROW()-6)),"") | B8: =IF($A8="","",IFERROR(IF(INDEX(tblProductos[Nombre del producto],MATCH($A8,tblProductos[SKU],0))="","",INDEX(tblProductos[Nombre del producto],MATCH($A8,tblProductos[SKU],0))),"")) | C8: =IF($A8="","",IFERROR(IF(INDEX(tblProductos[Categoría],MATCH($A8,tblProductos[SKU],0))="","",INDEX(tblProductos[Categoría],MATCH($A8,tblProductos[SKU],0))),"")) | D8: =IF($A8="","",IFERROR(IF(INDEX(tblProductos[Presentación],MATCH($A8,tblProductos[SKU],0))="","",INDEX(tblProductos[Presentación],MATCH($A8,tblProductos[SKU],0))),"")) | F8: =IF($A8="","",SUMIFS(tblCompras[Cantidad],tblCompras[SKU],$A8)) | G8: =IF($A8="","",SUMIFS(tblVentas[Unidades efectivas],tblVentas[SKU],$A8)) | I8: =IF($A8="","",IF(ISNUMBER($E8),$E8,0)+$F8-$G8+IF(ISNUMBER($H8),$H8,0)) | J8: =IF($A8="","",IFERROR(IF(INDEX(tblProductos[Stock mínimo],MATCH($A8,tblProductos[SKU],0))="","",INDEX(tblProductos[Stock mínimo],MATCH($A8,tblProductos[SKU],0))),"")) | K8: =IF($A8="","",IFERROR(IF(INDEX(tblProductos[Stock máximo],MATCH($A8,tblProductos[SKU],0))="","",INDEX(tblProductos[Stock máximo],MATCH($A8,tblProductos[SKU],0))),"")) | L8: =IF($A8="","",IFERROR(IF(INDEX(tblCostos[COSTO REAL UNITARIO],MATCH($A8,tblCostos[SKU],0))="","PENDIENTE",INDEX(tblCostos[COSTO REAL UNITARIO],MATCH($A8,tblCostos[SKU],0))),"PENDIENTE")) | M8: =IF($A8="","",IF(SUMIFS(tblCompras[Cantidad],tblCompras[SKU],$A8)<=0,"",SUMIFS(tblCompras[Costo total de adquisición],tblCompras[SKU],$A8)/SUMIFS(tblCompras[Cantidad],tblCompras[SKU],$A8))) | N8: =IF($A8="","",IF(ISNUMBER($M8),$M8,IF(ISNUMBER($L8),$L8,""))) | O8: =IF($A8="","",IF(ISNUMBER($M8),"Promedio ponderado",IF(ISNUMBER($L8),"Costo estándar","PENDIENTE"))) | P8: =IF($A8="","",IF(OR(NOT(ISNUMBER($I8)),NOT(ISNUMBER($N8))),"PENDIENTE",$I8*$N8)) | Q8: =IF($A8="","",IFERROR(IF(INDEX(tblProductos[Precio de venta actual],MATCH($A8,tblProductos[SKU],0))="","PENDIENTE",INDEX(tblProductos[Precio de venta actual],MATCH($A8,tblProductos[SKU],0))),"PENDIENTE")) | R8: =IF($A8="","",IF(OR(NOT(ISNUMBER($I8)),NOT(ISNUMBER($Q8))),"PENDIENTE",$I8*$Q8)) | S8: =IF($A8="","",IF(NOT(ISNUMBER($I8)),"ERROR",IF($I8<0,"ERROR",IF($I8=0,"AGOTADO",IF(AND(ISNUMBER($J8),$I8<=N($J8)*MAX(1,IF(ISNUMBER(PAR_ALERTA_STOCK),PAR_ALERTA_STOCK,1))),"REABASTECER","OK"))))) | T8: =IF($A8="","",IF(OR(NOT(ISNUMBER($I8)),NOT(ISNUMBER($K8))),"",IF(OR($S8="REABASTECER",$S8="AGOTADO"),MAX(0,$K8-$I8),0))) | U8: =IF($A8="","",IFERROR(IF(SUMPRODUCT(MAX((tblCompras[SKU]=$A8)*(tblCompras[Fecha])))=0,"",SUMPRODUCT(MAX((tblCompras[SKU]=$A8)*(tblCompras[Fecha])))),"")) | V8: =IF($A8="","",IFERROR(IF(SUMPRODUCT(MAX((tblVentas[SKU]=$A8)*(tblVentas[Fecha])))=0,"",SUMPRODUCT(MAX((tblVentas[SKU]=$A8)*(tblVentas[Fecha])))),"")) | W8: =IF($A8="","",SUMIFS(tblVentas[Unidades efectivas],tblVentas[SKU],$A8,tblVentas[Fecha],">="&TODAY()-30,tblVentas[Fecha],"<="&TODAY())) | X8: =IF($A8="","",IF(OR(NOT(ISNUMBER($I8)),NOT(ISNUMBER($W8)),$W8<=0),"",ROUND($I8/($W8/30),0)))
A9: =IFERROR(IF(INDEX(tblProductos[SKU],ROW()-6)="","",INDEX(tblProductos[SKU],ROW()-6)),"") | B9: =IF($A9="","",IFERROR(IF(INDEX(tblProductos[Nombre del producto],MATCH($A9,tblProductos[SKU],0))="","",INDEX(tblProductos[Nombre del producto],MATCH($A9,tblProductos[SKU],0))),"")) | C9: =IF($A9="","",IFERROR(IF(INDEX(tblProductos[Categoría],MATCH($A9,tblProductos[SKU],0))="","",INDEX(tblProductos[Categoría],MATCH($A9,tblProductos[SKU],0))),"")) | D9: =IF($A9="","",IFERROR(IF(INDEX(tblProductos[Presentación],MATCH($A9,tblProductos[SKU],0))="","",INDEX(tblProductos[Presentación],MATCH($A9,tblProductos[SKU],0))),"")) | F9: =IF($A9="","",SUMIFS(tblCompras[Cantidad],tblCompras[SKU],$A9)) | G9: =IF($A9="","",SUMIFS(tblVentas[Unidades efectivas],tblVentas[SKU],$A9)) | I9: =IF($A9="","",IF(ISNUMBER($E9),$E9,0)+$F9-$G9+IF(ISNUMBER($H9),$H9,0)) | J9: =IF($A9="","",IFERROR(IF(INDEX(tblProductos[Stock mínimo],MATCH($A9,tblProductos[SKU],0))="","",INDEX(tblProductos[Stock mínimo],MATCH($A9,tblProductos[SKU],0))),"")) | K9: =IF($A9="","",IFERROR(IF(INDEX(tblProductos[Stock máximo],MATCH($A9,tblProductos[SKU],0))="","",INDEX(tblProductos[Stock máximo],MATCH($A9,tblProductos[SKU],0))),"")) | L9: =IF($A9="","",IFERROR(IF(INDEX(tblCostos[COSTO REAL UNITARIO],MATCH($A9,tblCostos[SKU],0))="","PENDIENTE",INDEX(tblCostos[COSTO REAL UNITARIO],MATCH($A9,tblCostos[SKU],0))),"PENDIENTE")) | M9: =IF($A9="","",IF(SUMIFS(tblCompras[Cantidad],tblCompras[SKU],$A9)<=0,"",SUMIFS(tblCompras[Costo total de adquisición],tblCompras[SKU],$A9)/SUMIFS(tblCompras[Cantidad],tblCompras[SKU],$A9))) | N9: =IF($A9="","",IF(ISNUMBER($M9),$M9,IF(ISNUMBER($L9),$L9,""))) | O9: =IF($A9="","",IF(ISNUMBER($M9),"Promedio ponderado",IF(ISNUMBER($L9),"Costo estándar","PENDIENTE"))) | P9: =IF($A9="","",IF(OR(NOT(ISNUMBER($I9)),NOT(ISNUMBER($N9))),"PENDIENTE",$I9*$N9)) | Q9: =IF($A9="","",IFERROR(IF(INDEX(tblProductos[Precio de venta actual],MATCH($A9,tblProductos[SKU],0))="","PENDIENTE",INDEX(tblProductos[Precio de venta actual],MATCH($A9,tblProductos[SKU],0))),"PENDIENTE")) | R9: =IF($A9="","",IF(OR(NOT(ISNUMBER($I9)),NOT(ISNUMBER($Q9))),"PENDIENTE",$I9*$Q9)) | S9: =IF($A9="","",IF(NOT(ISNUMBER($I9)),"ERROR",IF($I9<0,"ERROR",IF($I9=0,"AGOTADO",IF(AND(ISNUMBER($J9),$I9<=N($J9)*MAX(1,IF(ISNUMBER(PAR_ALERTA_STOCK),PAR_ALERTA_STOCK,1))),"REABASTECER","OK"))))) | T9: =IF($A9="","",IF(OR(NOT(ISNUMBER($I9)),NOT(ISNUMBER($K9))),"",IF(OR($S9="REABASTECER",$S9="AGOTADO"),MAX(0,$K9-$I9),0))) | U9: =IF($A9="","",IFERROR(IF(SUMPRODUCT(MAX((tblCompras[SKU]=$A9)*(tblCompras[Fecha])))=0,"",SUMPRODUCT(MAX((tblCompras[SKU]=$A9)*(tblCompras[Fecha])))),"")) | V9: =IF($A9="","",IFERROR(IF(SUMPRODUCT(MAX((tblVentas[SKU]=$A9)*(tblVentas[Fecha])))=0,"",SUMPRODUCT(MAX((tblVentas[SKU]=$A9)*(tblVentas[Fecha])))),"")) | W9: =IF($A9="","",SUMIFS(tblVentas[Unidades efectivas],tblVentas[SKU],$A9,tblVentas[Fecha],">="&TODAY()-30,tblVentas[Fecha],"<="&TODAY())) | X9: =IF($A9="","",IF(OR(NOT(ISNUMBER($I9)),NOT(ISNUMBER($W9)),$W9<=0),"",ROUND($I9/($W9/30),0)))
A10: =IFERROR(IF(INDEX(tblProductos[SKU],ROW()-6)="","",INDEX(tblProductos[SKU],ROW()-6)),"") | B10: =IF($A10="","",IFERROR(IF(INDEX(tblProductos[Nombre del producto],MATCH($A10,tblProductos[SKU],0))="","",INDEX(tblProductos[Nombre del producto],MATCH($A10,tblProductos[SKU],0))),"")) | C10: =IF($A10="","",IFERROR(IF(INDEX(tblProductos[Categoría],MATCH($A10,tblProductos[SKU],0))="","",INDEX(tblProductos[Categoría],MATCH($A10,tblProductos[SKU],0))),"")) | D10: =IF($A10="","",IFERROR(IF(INDEX(tblProductos[Presentación],MATCH($A10,tblProductos[SKU],0))="","",INDEX(tblProductos[Presentación],MATCH($A10,tblProductos[SKU],0))),"")) | F10: =IF($A10="","",SUMIFS(tblCompras[Cantidad],tblCompras[SKU],$A10)) | G10: =IF($A10="","",SUMIFS(tblVentas[Unidades efectivas],tblVentas[SKU],$A10)) | I10: =IF($A10="","",IF(ISNUMBER($E10),$E10,0)+$F10-$G10+IF(ISNUMBER($H10),$H10,0)) | J10: =IF($A10="","",IFERROR(IF(INDEX(tblProductos[Stock mínimo],MATCH($A10,tblProductos[SKU],0))="","",INDEX(tblProductos[Stock mínimo],MATCH($A10,tblProductos[SKU],0))),"")) | K10: =IF($A10="","",IFERROR(IF(INDEX(tblProductos[Stock máximo],MATCH($A10,tblProductos[SKU],0))="","",INDEX(tblProductos[Stock máximo],MATCH($A10,tblProductos[SKU],0))),"")) | L10: =IF($A10="","",IFERROR(IF(INDEX(tblCostos[COSTO REAL UNITARIO],MATCH($A10,tblCostos[SKU],0))="","PENDIENTE",INDEX(tblCostos[COSTO REAL UNITARIO],MATCH($A10,tblCostos[SKU],0))),"PENDIENTE")) | M10: =IF($A10="","",IF(SUMIFS(tblCompras[Cantidad],tblCompras[SKU],$A10)<=0,"",SUMIFS(tblCompras[Costo total de adquisición],tblCompras[SKU],$A10)/SUMIFS(tblCompras[Cantidad],tblCompras[SKU],$A10))) | N10: =IF($A10="","",IF(ISNUMBER($M10),$M10,IF(ISNUMBER($L10),$L10,""))) | O10: =IF($A10="","",IF(ISNUMBER($M10),"Promedio ponderado",IF(ISNUMBER($L10),"Costo estándar","PENDIENTE"))) | P10: =IF($A10="","",IF(OR(NOT(ISNUMBER($I10)),NOT(ISNUMBER($N10))),"PENDIENTE",$I10*$N10)) | Q10: =IF($A10="","",IFERROR(IF(INDEX(tblProductos[Precio de venta actual],MATCH($A10,tblProductos[SKU],0))="","PENDIENTE",INDEX(tblProductos[Precio de venta actual],MATCH($A10,tblProductos[SKU],0))),"PENDIENTE")) | R10: =IF($A10="","",IF(OR(NOT(ISNUMBER($I10)),NOT(ISNUMBER($Q10))),"PENDIENTE",$I10*$Q10)) | S10: =IF($A10="","",IF(NOT(ISNUMBER($I10)),"ERROR",IF($I10<0,"ERROR",IF($I10=0,"AGOTADO",IF(AND(ISNUMBER($J10),$I10<=N($J10)*MAX(1,IF(ISNUMBER(PAR_ALERTA_STOCK),PAR_ALERTA_STOCK,1))),"REABASTECER","OK"))))) | T10: =IF($A10="","",IF(OR(NOT(ISNUMBER($I10)),NOT(ISNUMBER($K10))),"",IF(OR($S10="REABASTECER",$S10="AGOTADO"),MAX(0,$K10-$I10),0))) | U10: =IF($A10="","",IFERROR(IF(SUMPRODUCT(MAX((tblCompras[SKU]=$A10)*(tblCompras[Fecha])))=0,"",SUMPRODUCT(MAX((tblCompras[SKU]=$A10)*(tblCompras[Fecha])))),"")) | V10: =IF($A10="","",IFERROR(IF(SUMPRODUCT(MAX((tblVentas[SKU]=$A10)*(tblVentas[Fecha])))=0,"",SUMPRODUCT(MAX((tblVentas[SKU]=$A10)*(tblVentas[Fecha])))),"")) | W10: =IF($A10="","",SUMIFS(tblVentas[Unidades efectivas],tblVentas[SKU],$A10,tblVentas[Fecha],">="&TODAY()-30,tblVentas[Fecha],"<="&TODAY())) | X10: =IF($A10="","",IF(OR(NOT(ISNUMBER($I10)),NOT(ISNUMBER($W10)),$W10<=0),"",ROUND($I10/($W10/30),0)))
A11: =IFERROR(IF(INDEX(tblProductos[SKU],ROW()-6)="","",INDEX(tblProductos[SKU],ROW()-6)),"") | B11: =IF($A11="","",IFERROR(IF(INDEX(tblProductos[Nombre del producto],MATCH($A11,tblProductos[SKU],0))="","",INDEX(tblProductos[Nombre del producto],MATCH($A11,tblProductos[SKU],0))),"")) | C11: =IF($A11="","",IFERROR(IF(INDEX(tblProductos[Categoría],MATCH($A11,tblProductos[SKU],0))="","",INDEX(tblProductos[Categoría],MATCH($A11,tblProductos[SKU],0))),"")) | D11: =IF($A11="","",IFERROR(IF(INDEX(tblProductos[Presentación],MATCH($A11,tblProductos[SKU],0))="","",INDEX(tblProductos[Presentación],MATCH($A11,tblProductos[SKU],0))),"")) | F11: =IF($A11="","",SUMIFS(tblCompras[Cantidad],tblCompras[SKU],$A11)) | G11: =IF($A11="","",SUMIFS(tblVentas[Unidades efectivas],tblVentas[SKU],$A11)) | I11: =IF($A11="","",IF(ISNUMBER($E11),$E11,0)+$F11-$G11+IF(ISNUMBER($H11),$H11,0)) | J11: =IF($A11="","",IFERROR(IF(INDEX(tblProductos[Stock mínimo],MATCH($A11,tblProductos[SKU],0))="","",INDEX(tblProductos[Stock mínimo],MATCH($A11,tblProductos[SKU],0))),"")) | K11: =IF($A11="","",IFERROR(IF(INDEX(tblProductos[Stock máximo],MATCH($A11,tblProductos[SKU],0))="","",INDEX(tblProductos[Stock máximo],MATCH($A11,tblProductos[SKU],0))),"")) | L11: =IF($A11="","",IFERROR(IF(INDEX(tblCostos[COSTO REAL UNITARIO],MATCH($A11,tblCostos[SKU],0))="","PENDIENTE",INDEX(tblCostos[COSTO REAL UNITARIO],MATCH($A11,tblCostos[SKU],0))),"PENDIENTE")) | M11: =IF($A11="","",IF(SUMIFS(tblCompras[Cantidad],tblCompras[SKU],$A11)<=0,"",SUMIFS(tblCompras[Costo total de adquisición],tblCompras[SKU],$A11)/SUMIFS(tblCompras[Cantidad],tblCompras[SKU],$A11))) | N11: =IF($A11="","",IF(ISNUMBER($M11),$M11,IF(ISNUMBER($L11),$L11,""))) | O11: =IF($A11="","",IF(ISNUMBER($M11),"Promedio ponderado",IF(ISNUMBER($L11),"Costo estándar","PENDIENTE"))) | P11: =IF($A11="","",IF(OR(NOT(ISNUMBER($I11)),NOT(ISNUMBER($N11))),"PENDIENTE",$I11*$N11)) | Q11: =IF($A11="","",IFERROR(IF(INDEX(tblProductos[Precio de venta actual],MATCH($A11,tblProductos[SKU],0))="","PENDIENTE",INDEX(tblProductos[Precio de venta actual],MATCH($A11,tblProductos[SKU],0))),"PENDIENTE")) | R11: =IF($A11="","",IF(OR(NOT(ISNUMBER($I11)),NOT(ISNUMBER($Q11))),"PENDIENTE",$I11*$Q11)) | S11: =IF($A11="","",IF(NOT(ISNUMBER($I11)),"ERROR",IF($I11<0,"ERROR",IF($I11=0,"AGOTADO",IF(AND(ISNUMBER($J11),$I11<=N($J11)*MAX(1,IF(ISNUMBER(PAR_ALERTA_STOCK),PAR_ALERTA_STOCK,1))),"REABASTECER","OK"))))) | T11: =IF($A11="","",IF(OR(NOT(ISNUMBER($I11)),NOT(ISNUMBER($K11))),"",IF(OR($S11="REABASTECER",$S11="AGOTADO"),MAX(0,$K11-$I11),0))) | U11: =IF($A11="","",IFERROR(IF(SUMPRODUCT(MAX((tblCompras[SKU]=$A11)*(tblCompras[Fecha])))=0,"",SUMPRODUCT(MAX((tblCompras[SKU]=$A11)*(tblCompras[Fecha])))),"")) | V11: =IF($A11="","",IFERROR(IF(SUMPRODUCT(MAX((tblVentas[SKU]=$A11)*(tblVentas[Fecha])))=0,"",SUMPRODUCT(MAX((tblVentas[SKU]=$A11)*(tblVentas[Fecha])))),"")) | W11: =IF($A11="","",SUMIFS(tblVentas[Unidades efectivas],tblVentas[SKU],$A11,tblVentas[Fecha],">="&TODAY()-30,tblVentas[Fecha],"<="&TODAY())) | X11: =IF($A11="","",IF(OR(NOT(ISNUMBER($I11)),NOT(ISNUMBER($W11)),$W11<=0),"",ROUND($I11/($W11/30),0)))
A12: =IFERROR(IF(INDEX(tblProductos[SKU],ROW()-6)="","",INDEX(tblProductos[SKU],ROW()-6)),"") | B12: =IF($A12="","",IFERROR(IF(INDEX(tblProductos[Nombre del producto],MATCH($A12,tblProductos[SKU],0))="","",INDEX(tblProductos[Nombre del producto],MATCH($A12,tblProductos[SKU],0))),"")) | C12: =IF($A12="","",IFERROR(IF(INDEX(tblProductos[Categoría],MATCH($A12,tblProductos[SKU],0))="","",INDEX(tblProductos[Categoría],MATCH($A12,tblProductos[SKU],0))),"")) | D12: =IF($A12="","",IFERROR(IF(INDEX(tblProductos[Presentación],MATCH($A12,tblProductos[SKU],0))="","",INDEX(tblProductos[Presentación],MATCH($A12,tblProductos[SKU],0))),"")) | F12: =IF($A12="","",SUMIFS(tblCompras[Cantidad],tblCompras[SKU],$A12)) | G12: =IF($A12="","",SUMIFS(tblVentas[Unidades efectivas],tblVentas[SKU],$A12)) | I12: =IF($A12="","",IF(ISNUMBER($E12),$E12,0)+$F12-$G12+IF(ISNUMBER($H12),$H12,0)) | J12: =IF($A12="","",IFERROR(IF(INDEX(tblProductos[Stock mínimo],MATCH($A12,tblProductos[SKU],0))="","",INDEX(tblProductos[Stock mínimo],MATCH($A12,tblProductos[SKU],0))),"")) | K12: =IF($A12="","",IFERROR(IF(INDEX(tblProductos[Stock máximo],MATCH($A12,tblProductos[SKU],0))="","",INDEX(tblProductos[Stock máximo],MATCH($A12,tblProductos[SKU],0))),"")) | L12: =IF($A12="","",IFERROR(IF(INDEX(tblCostos[COSTO REAL UNITARIO],MATCH($A12,tblCostos[SKU],0))="","PENDIENTE",INDEX(tblCostos[COSTO REAL UNITARIO],MATCH($A12,tblCostos[SKU],0))),"PENDIENTE")) | M12: =IF($A12="","",IF(SUMIFS(tblCompras[Cantidad],tblCompras[SKU],$A12)<=0,"",SUMIFS(tblCompras[Costo total de adquisición],tblCompras[SKU],$A12)/SUMIFS(tblCompras[Cantidad],tblCompras[SKU],$A12))) | N12: =IF($A12="","",IF(ISNUMBER($M12),$M12,IF(ISNUMBER($L12),$L12,""))) | O12: =IF($A12="","",IF(ISNUMBER($M12),"Promedio ponderado",IF(ISNUMBER($L12),"Costo estándar","PENDIENTE"))) | P12: =IF($A12="","",IF(OR(NOT(ISNUMBER($I12)),NOT(ISNUMBER($N12))),"PENDIENTE",$I12*$N12)) | Q12: =IF($A12="","",IFERROR(IF(INDEX(tblProductos[Precio de venta actual],MATCH($A12,tblProductos[SKU],0))="","PENDIENTE",INDEX(tblProductos[Precio de venta actual],MATCH($A12,tblProductos[SKU],0))),"PENDIENTE")) | R12: =IF($A12="","",IF(OR(NOT(ISNUMBER($I12)),NOT(ISNUMBER($Q12))),"PENDIENTE",$I12*$Q12)) | S12: =IF($A12="","",IF(NOT(ISNUMBER($I12)),"ERROR",IF($I12<0,"ERROR",IF($I12=0,"AGOTADO",IF(AND(ISNUMBER($J12),$I12<=N($J12)*MAX(1,IF(ISNUMBER(PAR_ALERTA_STOCK),PAR_ALERTA_STOCK,1))),"REABASTECER","OK"))))) | T12: =IF($A12="","",IF(OR(NOT(ISNUMBER($I12)),NOT(ISNUMBER($K12))),"",IF(OR($S12="REABASTECER",$S12="AGOTADO"),MAX(0,$K12-$I12),0))) | U12: =IF($A12="","",IFERROR(IF(SUMPRODUCT(MAX((tblCompras[SKU]=$A12)*(tblCompras[Fecha])))=0,"",SUMPRODUCT(MAX((tblCompras[SKU]=$A12)*(tblCompras[Fecha])))),"")) | V12: =IF($A12="","",IFERROR(IF(SUMPRODUCT(MAX((tblVentas[SKU]=$A12)*(tblVentas[Fecha])))=0,"",SUMPRODUCT(MAX((tblVentas[SKU]=$A12)*(tblVentas[Fecha])))),"")) | W12: =IF($A12="","",SUMIFS(tblVentas[Unidades efectivas],tblVentas[SKU],$A12,tblVentas[Fecha],">="&TODAY()-30,tblVentas[Fecha],"<="&TODAY())) | X12: =IF($A12="","",IF(OR(NOT(ISNUMBER($I12)),NOT(ISNUMBER($W12)),$W12<=0),"",ROUND($I12/($W12/30),0)))
A13: =IFERROR(IF(INDEX(tblProductos[SKU],ROW()-6)="","",INDEX(tblProductos[SKU],ROW()-6)),"") | B13: =IF($A13="","",IFERROR(IF(INDEX(tblProductos[Nombre del producto],MATCH($A13,tblProductos[SKU],0))="","",INDEX(tblProductos[Nombre del producto],MATCH($A13,tblProductos[SKU],0))),"")) | C13: =IF($A13="","",IFERROR(IF(INDEX(tblProductos[Categoría],MATCH($A13,tblProductos[SKU],0))="","",INDEX(tblProductos[Categoría],MATCH($A13,tblProductos[SKU],0))),"")) | D13: =IF($A13="","",IFERROR(IF(INDEX(tblProductos[Presentación],MATCH($A13,tblProductos[SKU],0))="","",INDEX(tblProductos[Presentación],MATCH($A13,tblProductos[SKU],0))),"")) | F13: =IF($A13="","",SUMIFS(tblCompras[Cantidad],tblCompras[SKU],$A13)) | G13: =IF($A13="","",SUMIFS(tblVentas[Unidades efectivas],tblVentas[SKU],$A13)) | I13: =IF($A13="","",IF(ISNUMBER($E13),$E13,0)+$F13-$G13+IF(ISNUMBER($H13),$H13,0)) | J13: =IF($A13="","",IFERROR(IF(INDEX(tblProductos[Stock mínimo],MATCH($A13,tblProductos[SKU],0))="","",INDEX(tblProductos[Stock mínimo],MATCH($A13,tblProductos[SKU],0))),"")) | K13: =IF($A13="","",IFERROR(IF(INDEX(tblProductos[Stock máximo],MATCH($A13,tblProductos[SKU],0))="","",INDEX(tblProductos[Stock máximo],MATCH($A13,tblProductos[SKU],0))),"")) | L13: =IF($A13="","",IFERROR(IF(INDEX(tblCostos[COSTO REAL UNITARIO],MATCH($A13,tblCostos[SKU],0))="","PENDIENTE",INDEX(tblCostos[COSTO REAL UNITARIO],MATCH($A13,tblCostos[SKU],0))),"PENDIENTE")) | M13: =IF($A13="","",IF(SUMIFS(tblCompras[Cantidad],tblCompras[SKU],$A13)<=0,"",SUMIFS(tblCompras[Costo total de adquisición],tblCompras[SKU],$A13)/SUMIFS(tblCompras[Cantidad],tblCompras[SKU],$A13))) | N13: =IF($A13="","",IF(ISNUMBER($M13),$M13,IF(ISNUMBER($L13),$L13,""))) | O13: =IF($A13="","",IF(ISNUMBER($M13),"Promedio ponderado",IF(ISNUMBER($L13),"Costo estándar","PENDIENTE"))) | P13: =IF($A13="","",IF(OR(NOT(ISNUMBER($I13)),NOT(ISNUMBER($N13))),"PENDIENTE",$I13*$N13)) | Q13: =IF($A13="","",IFERROR(IF(INDEX(tblProductos[Precio de venta actual],MATCH($A13,tblProductos[SKU],0))="","PENDIENTE",INDEX(tblProductos[Precio de venta actual],MATCH($A13,tblProductos[SKU],0))),"PENDIENTE")) | R13: =IF($A13="","",IF(OR(NOT(ISNUMBER($I13)),NOT(ISNUMBER($Q13))),"PENDIENTE",$I13*$Q13)) | S13: =IF($A13="","",IF(NOT(ISNUMBER($I13)),"ERROR",IF($I13<0,"ERROR",IF($I13=0,"AGOTADO",IF(AND(ISNUMBER($J13),$I13<=N($J13)*MAX(1,IF(ISNUMBER(PAR_ALERTA_STOCK),PAR_ALERTA_STOCK,1))),"REABASTECER","OK"))))) | T13: =IF($A13="","",IF(OR(NOT(ISNUMBER($I13)),NOT(ISNUMBER($K13))),"",IF(OR($S13="REABASTECER",$S13="AGOTADO"),MAX(0,$K13-$I13),0))) | U13: =IF($A13="","",IFERROR(IF(SUMPRODUCT(MAX((tblCompras[SKU]=$A13)*(tblCompras[Fecha])))=0,"",SUMPRODUCT(MAX((tblCompras[SKU]=$A13)*(tblCompras[Fecha])))),"")) | V13: =IF($A13="","",IFERROR(IF(SUMPRODUCT(MAX((tblVentas[SKU]=$A13)*(tblVentas[Fecha])))=0,"",SUMPRODUCT(MAX((tblVentas[SKU]=$A13)*(tblVentas[Fecha])))),"")) | W13: =IF($A13="","",SUMIFS(tblVentas[Unidades efectivas],tblVentas[SKU],$A13,tblVentas[Fecha],">="&TODAY()-30,tblVentas[Fecha],"<="&TODAY())) | X13: =IF($A13="","",IF(OR(NOT(ISNUMBER($I13)),NOT(ISNUMBER($W13)),$W13<=0),"",ROUND($I13/($W13/30),0)))
A14: =IFERROR(IF(INDEX(tblProductos[SKU],ROW()-6)="","",INDEX(tblProductos[SKU],ROW()-6)),"") | B14: =IF($A14="","",IFERROR(IF(INDEX(tblProductos[Nombre del producto],MATCH($A14,tblProductos[SKU],0))="","",INDEX(tblProductos[Nombre del producto],MATCH($A14,tblProductos[SKU],0))),"")) | C14: =IF($A14="","",IFERROR(IF(INDEX(tblProductos[Categoría],MATCH($A14,tblProductos[SKU],0))="","",INDEX(tblProductos[Categoría],MATCH($A14,tblProductos[SKU],0))),"")) | D14: =IF($A14="","",IFERROR(IF(INDEX(tblProductos[Presentación],MATCH($A14,tblProductos[SKU],0))="","",INDEX(tblProductos[Presentación],MATCH($A14,tblProductos[SKU],0))),"")) | F14: =IF($A14="","",SUMIFS(tblCompras[Cantidad],tblCompras[SKU],$A14)) | G14: =IF($A14="","",SUMIFS(tblVentas[Unidades efectivas],tblVentas[SKU],$A14)) | I14: =IF($A14="","",IF(ISNUMBER($E14),$E14,0)+$F14-$G14+IF(ISNUMBER($H14),$H14,0)) | J14: =IF($A14="","",IFERROR(IF(INDEX(tblProductos[Stock mínimo],MATCH($A14,tblProductos[SKU],0))="","",INDEX(tblProductos[Stock mínimo],MATCH($A14,tblProductos[SKU],0))),"")) | K14: =IF($A14="","",IFERROR(IF(INDEX(tblProductos[Stock máximo],MATCH($A14,tblProductos[SKU],0))="","",INDEX(tblProductos[Stock máximo],MATCH($A14,tblProductos[SKU],0))),"")) | L14: =IF($A14="","",IFERROR(IF(INDEX(tblCostos[COSTO REAL UNITARIO],MATCH($A14,tblCostos[SKU],0))="","PENDIENTE",INDEX(tblCostos[COSTO REAL UNITARIO],MATCH($A14,tblCostos[SKU],0))),"PENDIENTE")) | M14: =IF($A14="","",IF(SUMIFS(tblCompras[Cantidad],tblCompras[SKU],$A14)<=0,"",SUMIFS(tblCompras[Costo total de adquisición],tblCompras[SKU],$A14)/SUMIFS(tblCompras[Cantidad],tblCompras[SKU],$A14))) | N14: =IF($A14="","",IF(ISNUMBER($M14),$M14,IF(ISNUMBER($L14),$L14,""))) | O14: =IF($A14="","",IF(ISNUMBER($M14),"Promedio ponderado",IF(ISNUMBER($L14),"Costo estándar","PENDIENTE"))) | P14: =IF($A14="","",IF(OR(NOT(ISNUMBER($I14)),NOT(ISNUMBER($N14))),"PENDIENTE",$I14*$N14)) | Q14: =IF($A14="","",IFERROR(IF(INDEX(tblProductos[Precio de venta actual],MATCH($A14,tblProductos[SKU],0))="","PENDIENTE",INDEX(tblProductos[Precio de venta actual],MATCH($A14,tblProductos[SKU],0))),"PENDIENTE")) | R14: =IF($A14="","",IF(OR(NOT(ISNUMBER($I14)),NOT(ISNUMBER($Q14))),"PENDIENTE",$I14*$Q14)) | S14: =IF($A14="","",IF(NOT(ISNUMBER($I14)),"ERROR",IF($I14<0,"ERROR",IF($I14=0,"AGOTADO",IF(AND(ISNUMBER($J14),$I14<=N($J14)*MAX(1,IF(ISNUMBER(PAR_ALERTA_STOCK),PAR_ALERTA_STOCK,1))),"REABASTECER","OK"))))) | T14: =IF($A14="","",IF(OR(NOT(ISNUMBER($I14)),NOT(ISNUMBER($K14))),"",IF(OR($S14="REABASTECER",$S14="AGOTADO"),MAX(0,$K14-$I14),0))) | U14: =IF($A14="","",IFERROR(IF(SUMPRODUCT(MAX((tblCompras[SKU]=$A14)*(tblCompras[Fecha])))=0,"",SUMPRODUCT(MAX((tblCompras[SKU]=$A14)*(tblCompras[Fecha])))),"")) | V14: =IF($A14="","",IFERROR(IF(SUMPRODUCT(MAX((tblVentas[SKU]=$A14)*(tblVentas[Fecha])))=0,"",SUMPRODUCT(MAX((tblVentas[SKU]=$A14)*(tblVentas[Fecha])))),"")) | W14: =IF($A14="","",SUMIFS(tblVentas[Unidades efectivas],tblVentas[SKU],$A14,tblVentas[Fecha],">="&TODAY()-30,tblVentas[Fecha],"<="&TODAY())) | X14: =IF($A14="","",IF(OR(NOT(ISNUMBER($I14)),NOT(ISNUMBER($W14)),$W14<=0),"",ROUND($I14/($W14/30),0)))
A15: =IFERROR(IF(INDEX(tblProductos[SKU],ROW()-6)="","",INDEX(tblProductos[SKU],ROW()-6)),"") | B15: =IF($A15="","",IFERROR(IF(INDEX(tblProductos[Nombre del producto],MATCH($A15,tblProductos[SKU],0))="","",INDEX(tblProductos[Nombre del producto],MATCH($A15,tblProductos[SKU],0))),"")) | C15: =IF($A15="","",IFERROR(IF(INDEX(tblProductos[Categoría],MATCH($A15,tblProductos[SKU],0))="","",INDEX(tblProductos[Categoría],MATCH($A15,tblProductos[SKU],0))),"")) | D15: =IF($A15="","",IFERROR(IF(INDEX(tblProductos[Presentación],MATCH($A15,tblProductos[SKU],0))="","",INDEX(tblProductos[Presentación],MATCH($A15,tblProductos[SKU],0))),"")) | F15: =IF($A15="","",SUMIFS(tblCompras[Cantidad],tblCompras[SKU],$A15)) | G15: =IF($A15="","",SUMIFS(tblVentas[Unidades efectivas],tblVentas[SKU],$A15)) | I15: =IF($A15="","",IF(ISNUMBER($E15),$E15,0)+$F15-$G15+IF(ISNUMBER($H15),$H15,0)) | J15: =IF($A15="","",IFERROR(IF(INDEX(tblProductos[Stock mínimo],MATCH($A15,tblProductos[SKU],0))="","",INDEX(tblProductos[Stock mínimo],MATCH($A15,tblProductos[SKU],0))),"")) | K15: =IF($A15="","",IFERROR(IF(INDEX(tblProductos[Stock máximo],MATCH($A15,tblProductos[SKU],0))="","",INDEX(tblProductos[Stock máximo],MATCH($A15,tblProductos[SKU],0))),"")) | L15: =IF($A15="","",IFERROR(IF(INDEX(tblCostos[COSTO REAL UNITARIO],MATCH($A15,tblCostos[SKU],0))="","PENDIENTE",INDEX(tblCostos[COSTO REAL UNITARIO],MATCH($A15,tblCostos[SKU],0))),"PENDIENTE")) | M15: =IF($A15="","",IF(SUMIFS(tblCompras[Cantidad],tblCompras[SKU],$A15)<=0,"",SUMIFS(tblCompras[Costo total de adquisición],tblCompras[SKU],$A15)/SUMIFS(tblCompras[Cantidad],tblCompras[SKU],$A15))) | N15: =IF($A15="","",IF(ISNUMBER($M15),$M15,IF(ISNUMBER($L15),$L15,""))) | O15: =IF($A15="","",IF(ISNUMBER($M15),"Promedio ponderado",IF(ISNUMBER($L15),"Costo estándar","PENDIENTE"))) | P15: =IF($A15="","",IF(OR(NOT(ISNUMBER($I15)),NOT(ISNUMBER($N15))),"PENDIENTE",$I15*$N15)) | Q15: =IF($A15="","",IFERROR(IF(INDEX(tblProductos[Precio de venta actual],MATCH($A15,tblProductos[SKU],0))="","PENDIENTE",INDEX(tblProductos[Precio de venta actual],MATCH($A15,tblProductos[SKU],0))),"PENDIENTE")) | R15: =IF($A15="","",IF(OR(NOT(ISNUMBER($I15)),NOT(ISNUMBER($Q15))),"PENDIENTE",$I15*$Q15)) | S15: =IF($A15="","",IF(NOT(ISNUMBER($I15)),"ERROR",IF($I15<0,"ERROR",IF($I15=0,"AGOTADO",IF(AND(ISNUMBER($J15),$I15<=N($J15)*MAX(1,IF(ISNUMBER(PAR_ALERTA_STOCK),PAR_ALERTA_STOCK,1))),"REABASTECER","OK"))))) | T15: =IF($A15="","",IF(OR(NOT(ISNUMBER($I15)),NOT(ISNUMBER($K15))),"",IF(OR($S15="REABASTECER",$S15="AGOTADO"),MAX(0,$K15-$I15),0))) | U15: =IF($A15="","",IFERROR(IF(SUMPRODUCT(MAX((tblCompras[SKU]=$A15)*(tblCompras[Fecha])))=0,"",SUMPRODUCT(MAX((tblCompras[SKU]=$A15)*(tblCompras[Fecha])))),"")) | V15: =IF($A15="","",IFERROR(IF(SUMPRODUCT(MAX((tblVentas[SKU]=$A15)*(tblVentas[Fecha])))=0,"",SUMPRODUCT(MAX((tblVentas[SKU]=$A15)*(tblVentas[Fecha])))),"")) | W15: =IF($A15="","",SUMIFS(tblVentas[Unidades efectivas],tblVentas[SKU],$A15,tblVentas[Fecha],">="&TODAY()-30,tblVentas[Fecha],"<="&TODAY())) | X15: =IF($A15="","",IF(OR(NOT(ISNUMBER($I15)),NOT(ISNUMBER($W15)),$W15<=0),"",ROUND($I15/($W15/30),0)))
A16: =IFERROR(IF(INDEX(tblProductos[SKU],ROW()-6)="","",INDEX(tblProductos[SKU],ROW()-6)),"") | B16: =IF($A16="","",IFERROR(IF(INDEX(tblProductos[Nombre del producto],MATCH($A16,tblProductos[SKU],0))="","",INDEX(tblProductos[Nombre del producto],MATCH($A16,tblProductos[SKU],0))),"")) | C16: =IF($A16="","",IFERROR(IF(INDEX(tblProductos[Categoría],MATCH($A16,tblProductos[SKU],0))="","",INDEX(tblProductos[Categoría],MATCH($A16,tblProductos[SKU],0))),"")) | D16: =IF($A16="","",IFERROR(IF(INDEX(tblProductos[Presentación],MATCH($A16,tblProductos[SKU],0))="","",INDEX(tblProductos[Presentación],MATCH($A16,tblProductos[SKU],0))),"")) | F16: =IF($A16="","",SUMIFS(tblCompras[Cantidad],tblCompras[SKU],$A16)) | G16: =IF($A16="","",SUMIFS(tblVentas[Unidades efectivas],tblVentas[SKU],$A16)) | I16: =IF($A16="","",IF(ISNUMBER($E16),$E16,0)+$F16-$G16+IF(ISNUMBER($H16),$H16,0)) | J16: =IF($A16="","",IFERROR(IF(INDEX(tblProductos[Stock mínimo],MATCH($A16,tblProductos[SKU],0))="","",INDEX(tblProductos[Stock mínimo],MATCH($A16,tblProductos[SKU],0))),"")) | K16: =IF($A16="","",IFERROR(IF(INDEX(tblProductos[Stock máximo],MATCH($A16,tblProductos[SKU],0))="","",INDEX(tblProductos[Stock máximo],MATCH($A16,tblProductos[SKU],0))),"")) | L16: =IF($A16="","",IFERROR(IF(INDEX(tblCostos[COSTO REAL UNITARIO],MATCH($A16,tblCostos[SKU],0))="","PENDIENTE",INDEX(tblCostos[COSTO REAL UNITARIO],MATCH($A16,tblCostos[SKU],0))),"PENDIENTE")) | M16: =IF($A16="","",IF(SUMIFS(tblCompras[Cantidad],tblCompras[SKU],$A16)<=0,"",SUMIFS(tblCompras[Costo total de adquisición],tblCompras[SKU],$A16)/SUMIFS(tblCompras[Cantidad],tblCompras[SKU],$A16))) | N16: =IF($A16="","",IF(ISNUMBER($M16),$M16,IF(ISNUMBER($L16),$L16,""))) | O16: =IF($A16="","",IF(ISNUMBER($M16),"Promedio ponderado",IF(ISNUMBER($L16),"Costo estándar","PENDIENTE"))) | P16: =IF($A16="","",IF(OR(NOT(ISNUMBER($I16)),NOT(ISNUMBER($N16))),"PENDIENTE",$I16*$N16)) | Q16: =IF($A16="","",IFERROR(IF(INDEX(tblProductos[Precio de venta actual],MATCH($A16,tblProductos[SKU],0))="","PENDIENTE",INDEX(tblProductos[Precio de venta actual],MATCH($A16,tblProductos[SKU],0))),"PENDIENTE")) | R16: =IF($A16="","",IF(OR(NOT(ISNUMBER($I16)),NOT(ISNUMBER($Q16))),"PENDIENTE",$I16*$Q16)) | S16: =IF($A16="","",IF(NOT(ISNUMBER($I16)),"ERROR",IF($I16<0,"ERROR",IF($I16=0,"AGOTADO",IF(AND(ISNUMBER($J16),$I16<=N($J16)*MAX(1,IF(ISNUMBER(PAR_ALERTA_STOCK),PAR_ALERTA_STOCK,1))),"REABASTECER","OK"))))) | T16: =IF($A16="","",IF(OR(NOT(ISNUMBER($I16)),NOT(ISNUMBER($K16))),"",IF(OR($S16="REABASTECER",$S16="AGOTADO"),MAX(0,$K16-$I16),0))) | U16: =IF($A16="","",IFERROR(IF(SUMPRODUCT(MAX((tblCompras[SKU]=$A16)*(tblCompras[Fecha])))=0,"",SUMPRODUCT(MAX((tblCompras[SKU]=$A16)*(tblCompras[Fecha])))),"")) | V16: =IF($A16="","",IFERROR(IF(SUMPRODUCT(MAX((tblVentas[SKU]=$A16)*(tblVentas[Fecha])))=0,"",SUMPRODUCT(MAX((tblVentas[SKU]=$A16)*(tblVentas[Fecha])))),"")) | W16: =IF($A16="","",SUMIFS(tblVentas[Unidades efectivas],tblVentas[SKU],$A16,tblVentas[Fecha],">="&TODAY()-30,tblVentas[Fecha],"<="&TODAY())) | X16: =IF($A16="","",IF(OR(NOT(ISNUMBER($I16)),NOT(ISNUMBER($W16)),$W16<=0),"",ROUND($I16/($W16/30),0)))
A17: =IFERROR(IF(INDEX(tblProductos[SKU],ROW()-6)="","",INDEX(tblProductos[SKU],ROW()-6)),"") | B17: =IF($A17="","",IFERROR(IF(INDEX(tblProductos[Nombre del producto],MATCH($A17,tblProductos[SKU],0))="","",INDEX(tblProductos[Nombre del producto],MATCH($A17,tblProductos[SKU],0))),"")) | C17: =IF($A17="","",IFERROR(IF(INDEX(tblProductos[Categoría],MATCH($A17,tblProductos[SKU],0))="","",INDEX(tblProductos[Categoría],MATCH($A17,tblProductos[SKU],0))),"")) | D17: =IF($A17="","",IFERROR(IF(INDEX(tblProductos[Presentación],MATCH($A17,tblProductos[SKU],0))="","",INDEX(tblProductos[Presentación],MATCH($A17,tblProductos[SKU],0))),"")) | F17: =IF($A17="","",SUMIFS(tblCompras[Cantidad],tblCompras[SKU],$A17)) | G17: =IF($A17="","",SUMIFS(tblVentas[Unidades efectivas],tblVentas[SKU],$A17)) | I17: =IF($A17="","",IF(ISNUMBER($E17),$E17,0)+$F17-$G17+IF(ISNUMBER($H17),$H17,0)) | J17: =IF($A17="","",IFERROR(IF(INDEX(tblProductos[Stock mínimo],MATCH($A17,tblProductos[SKU],0))="","",INDEX(tblProductos[Stock mínimo],MATCH($A17,tblProductos[SKU],0))),"")) | K17: =IF($A17="","",IFERROR(IF(INDEX(tblProductos[Stock máximo],MATCH($A17,tblProductos[SKU],0))="","",INDEX(tblProductos[Stock máximo],MATCH($A17,tblProductos[SKU],0))),"")) | L17: =IF($A17="","",IFERROR(IF(INDEX(tblCostos[COSTO REAL UNITARIO],MATCH($A17,tblCostos[SKU],0))="","PENDIENTE",INDEX(tblCostos[COSTO REAL UNITARIO],MATCH($A17,tblCostos[SKU],0))),"PENDIENTE")) | M17: =IF($A17="","",IF(SUMIFS(tblCompras[Cantidad],tblCompras[SKU],$A17)<=0,"",SUMIFS(tblCompras[Costo total de adquisición],tblCompras[SKU],$A17)/SUMIFS(tblCompras[Cantidad],tblCompras[SKU],$A17))) | N17: =IF($A17="","",IF(ISNUMBER($M17),$M17,IF(ISNUMBER($L17),$L17,""))) | O17: =IF($A17="","",IF(ISNUMBER($M17),"Promedio ponderado",IF(ISNUMBER($L17),"Costo estándar","PENDIENTE"))) | P17: =IF($A17="","",IF(OR(NOT(ISNUMBER($I17)),NOT(ISNUMBER($N17))),"PENDIENTE",$I17*$N17)) | Q17: =IF($A17="","",IFERROR(IF(INDEX(tblProductos[Precio de venta actual],MATCH($A17,tblProductos[SKU],0))="","PENDIENTE",INDEX(tblProductos[Precio de venta actual],MATCH($A17,tblProductos[SKU],0))),"PENDIENTE")) | R17: =IF($A17="","",IF(OR(NOT(ISNUMBER($I17)),NOT(ISNUMBER($Q17))),"PENDIENTE",$I17*$Q17)) | S17: =IF($A17="","",IF(NOT(ISNUMBER($I17)),"ERROR",IF($I17<0,"ERROR",IF($I17=0,"AGOTADO",IF(AND(ISNUMBER($J17),$I17<=N($J17)*MAX(1,IF(ISNUMBER(PAR_ALERTA_STOCK),PAR_ALERTA_STOCK,1))),"REABASTECER","OK"))))) | T17: =IF($A17="","",IF(OR(NOT(ISNUMBER($I17)),NOT(ISNUMBER($K17))),"",IF(OR($S17="REABASTECER",$S17="AGOTADO"),MAX(0,$K17-$I17),0))) | U17: =IF($A17="","",IFERROR(IF(SUMPRODUCT(MAX((tblCompras[SKU]=$A17)*(tblCompras[Fecha])))=0,"",SUMPRODUCT(MAX((tblCompras[SKU]=$A17)*(tblCompras[Fecha])))),"")) | V17: =IF($A17="","",IFERROR(IF(SUMPRODUCT(MAX((tblVentas[SKU]=$A17)*(tblVentas[Fecha])))=0,"",SUMPRODUCT(MAX((tblVentas[SKU]=$A17)*(tblVentas[Fecha])))),"")) | W17: =IF($A17="","",SUMIFS(tblVentas[Unidades efectivas],tblVentas[SKU],$A17,tblVentas[Fecha],">="&TODAY()-30,tblVentas[Fecha],"<="&TODAY())) | X17: =IF($A17="","",IF(OR(NOT(ISNUMBER($I17)),NOT(ISNUMBER($W17)),$W17<=0),"",ROUND($I17/($W17/30),0)))
